Workbook

Sheet Допущения
A1: Допущения финмодели QuipQuill — все входные данные (синие ячейки можно менять)
A2: Синий — ввод, чёрный — формула, зелёный — ссылка на другой лист. Валюта модели — USD. Дата расчёта: 17.10.2026. Месяц 1 модели = ноябрь 2026.
A4: Параметр | B4: Ед. | C4: Пессим. | D4: Базовый | E4: Оптим. | F4: Источник / обоснование
A6: Общие
A7: Курс RUB за 1 USD | B7: ₽ | C7: =$D$7 | D7: 83 | E7: =$D$7 | F7: ЦБ РФ / рынок, окт. 2026 ≈ 83 (диапазон 2026: 71–86). Пересчитать на дату вложения
A8: Курс GEL за 1 USD | B8: ₾ | C8: =$D$8 | D8: 2.65 | E8: =$D$8 | F8: НБГ, 2026 ≈ 2,62–2,70
A9: Месяц выхода MVP в магазины | B9: мес. | C9: 6 | D9: 5 | E9: 4 | F9: Цель пользователя: 3–6 мес. Месяц 5 = март 2027
A10: Месяц регистрации ООО | B10: мес. | C10: =$D$10 | D10: 2 | E10: =$D$10 | F10: Декабрь 2026: до подачи в магазины (D-U-N-S для Apple/Google)
A12: Цены моделей OpenRouter, $ за 1 млн токенов
A13: Haiku 5.5 — вход | B13: $/1M | C13: =$D$13 | D13: 0.1 | E13: =$D$13 | F13: openrouter.ai/api/v1/models, 17.10.2026 (до 100K токенов контекста)
A14: Haiku 5.5 — выход | B14: $/1M | C14: =$D$14 | D14: 0.5 | E14: =$D$14 | F14: там же
A15: Haiku 5.5 — чтение кэша | B15: $/1M | C15: =$D$15 | D15: 0.01 | E15: =$D$15 | F15: там же
A16: Haiku 5.5 — запись кэша | B16: $/1M | C16: =$D$16 | D16: 0.125 | E16: =$D$16 | F16: там же
A17: Sonnet 5.5 — вход | B17: $/1M | C17: =$D$17 | D17: 2 | E17: =$D$17 | F17: там же
A18: Sonnet 5.5 — выход | B18: $/1M | C18: =$D$18 | D18: 10 | E18: =$D$18 | F18: там же
A19: Sonnet 5.5 — чтение кэша | B19: $/1M | C19: =$D$19 | D19: 0.1 | E19: =$D$19 | F19: там же
A20: Sonnet 5.5 — запись кэша | B20: $/1M | C20: =$D$20 | D20: 2.5 | E20: =$D$20 | F20: там же
A22: Профиль хода (из тестов 6.2i: 12 ходов игрока, 2 прогона)
A23: Некэшированный вход за ход | B23: ток. | C23: =$D$23 | D23: 9800 | E23: =$D$23 | F23: Среднее: 29,5K вход − 19,7K из кэша
A24: Вход из кэша за ход | B24: ток. | C24: =$D$24 | D24: 19700 | E24: =$D$24 | F24: Среднее по 12 ходам
A25: Выход за ход | B25: ток. | C25: =$D$25 | D25: 1310 | E25: =$D$25 | F25: Среднее по 12 ходам
A26: Доля некэш. входа, идущая в запись кэша | B26: доля | C26: =$D$26 | D26: 0.15 | E26: =$D$26 | F26: Подбор: модель даёт $0,00187 при фактическом среднем $0,00186
A27: Доля токенов хода у мастера (gm) | B27: доля | C27: =$D$27 | D27: 0.65 | E27: =$D$27 | F27: Оценка: gm — 3 из ~6 вызовов, но самые длинные промпты
A28: Множитель длинных сессий (рост контекста, повторы) | B28: x | C28: 1.5 | D28: 1.3 | E28: 1.15 | F28: Ходы в тестах дорожали с $0,0011 до $0,0028 за 7 ходов; запас на сводки и повторы
A29: Модерация на ход (Llama Guard 4 / перехват кризиса) | B29: $ | C29: 0.0003 | D29: 0.0002 | E29: 0.0001 | F29: Llama Guard 4: $0,18/1M; ~1–1,5K токенов на проверку ввода и выборочно ответа
A31: Тарифы (цены — в магазинах, без налога с продаж США)
A32: Free: ходов в неделю | B32: ходов | C32: =$D$32 | D32: 30 | E32: =$D$32 | F32: ≈ одна сессия в неделю; дешёвая воронка
A33: Комфорт: ходов за сессию | B33: ходов | C33: =$D$33 | D33: 45 | E33: =$D$33 | F33: ~45–60 мин игры, 1 ход ≈ 1–1,3 мин с чтением
A34: Комфорт: сессий в неделю | B34: сессий | C34: =$D$34 | D34: 6 | E34: =$D$34 | F34: Активный игрок: почти ежедневно
A35: Teen 13–17 (строгий режим): цена | B35: $/мес | C35: =$D$35 | D35: 4.99 | E35: =$D$35 | F35: Дешёвый тариф для школьников (идея пользователя)
A36: Teen: ходов в месяц | B36: ходов | C36: =$D$36 | D36: 600 | E36: =$D$36 | F36: ½ комфортного объёма
A37: Standard: цена | B37: $/мес | C37: =$D$37 | D37: 9.99 | E37: =$D$37 | F37: Рынок: c.ai+ $9,99; AI Dungeon $9,99; NovelAI $10
A38: Standard: ходов в месяц | B38: ходов | C38: =$D$38 | D38: 1200 | E38: =$D$38 | F38: Комфортный объём (см. «Себестоимость»)
A39: Premium (мастер на Sonnet): цена | B39: $/мес | C39: =$D$39 | D39: 19.99 | E39: =$D$39 | F39: Рынок: NovelAI Opus $25; Friends & Fables $19,95–39,95
A40: Premium: ходов в месяц, всего | B40: ходов | C40: =$D$40 | D40: 1200 | E40: =$D$40 | F40: Комфортный объём
A41: Premium: из них ходов на Sonnet | B41: ходов | C41: =$D$41 | D41: 300 | E41: =$D$41 | F41: Остальные — на Haiku
A42: Legend (10 000 ходов): цена | B42: $/мес | C42: =$D$42 | D42: 39.99 | E42: =$D$42 | F42: Для энтузиастов; см. расчёт маржи
A43: Legend: ходов в месяц | B43: ходов | C43: =$D$43 | D43: 10000 | E43: =$D$43 | F43: Запрошенный объём
A44: Доля платящих: Teen | B44: доля | C44: =$D$44 | D44: 0.15 | E44: =$D$44 | F44: Оценка
A45: Доля платящих: Standard | B45: доля | C45: =$D$45 | D45: 0.6 | E45: =$D$45 | F45: Оценка
A46: Доля платящих: Premium | B46: доля | C46: =$D$46 | D46: 0.2 | E46: =$D$46 | F46: Оценка
A47: Доля платящих: Legend | B47: доля | C47: =$D$47 | D47: 0.05 | E47: =$D$47 | F47: Оценка
A48: Средняя выборка лимита платящими | B48: доля | C48: 0.55 | D48: 0.45 | E48: 0.4 | F48: Типично 30–50% у подписок с лимитом; пессимизм — выше
A49: Ходов в месяц на активного free | B49: ходов | C49: 75 | D49: 60 | E49: 50 | F49: При лимите 30 в неделю (макс. ~130)
A51: Каналы оплаты и налоги с продаж
A52: Комиссия App Store / Google Play на подписки | B52: доля | C52: =$D$52 | D52: 0.15 | E52: =$D$52 | F52: Apple Small Business Program 15%; Google — 15% на подписки (10% с 30.06.2026 + сбор за биллинг)
A53: Доля оплат через веб (внешняя ссылка в США, Paddle) | B53: доля | C53: 0.15 | D53: 0.3 | E53: 0.4 | F53: США: после Epic v. Apple 0% комиссии Apple за внешние ссылки (дело в Верховном суде)
A54: Paddle: процент | B54: доля | C54: =$D$54 | D54: 0.05 | E54: =$D$54 | F54: Paddle 5% + $0,50, Merchant of Record — платит НДС/sales tax
A55: Paddle: фикс. за транзакцию | B55: $ | C55: =$D$55 | D55: 0.5 | E55: =$D$55 | F55: там же
A56: НДС ЕС/Канады, включённый в цену (средневзвеш.) | B56: доля | C56: 0.06 | D56: 0.05 | E56: 0.04 | F56: ≈30% выручки из ЕС × ~20% НДС; в США цена без налога
A57: Налог на прибыль (база — Virtual Zone 0%) | B57: доля | C57: 0.15 | D57: 0 | E57: 0 | F57: VZ: 0% на IT-доход от нерезидентов; пессимизм — без VZ, 15% «эстонской» модели
A59: Воронка и удержание
A60: CPI (стоимость установки, смешанная iOS/Android, США/ЕС/Канада) | B60: $ | C60: 4.5 | D60: 3 | E60: 2 | F60: Бенчмарки 2026: iOS $5,8, Android $1,9; TikTok $1–4,5
A61: Органические установки в месяц выхода | B61: уст. | C61: 600 | D61: 1200 | E61: 2000 | F61: Лист ожидания с прототипа + контент в TikTok/Reddit/Discord
A62: Рост органики в месяц | B62: доля | C62: 0.04 | D62: 0.08 | E62: 0.1 | F62: Контент-маркетинг, ASO, сарафан
A63: Потолок органики | B63: уст./мес | C63: 8000 | D63: 20000 | E63: 30000 | F63: Ограничение насыщения ниши
A64: Вирусность (доп. установок на 1 установку) | B64: x | C64: 0.05 | D64: 0.15 | E64: 0.25 | F64: Шеринг сцен, кооператив позже
A65: Активация (сыграл ≥1 сессию) | B65: доля | C65: 0.5 | D65: 0.6 | E65: 0.7 | F65: Онбординг: персонаж + первая сцена
A66: Удержание активных free месяц к месяцу | B66: доля | C66: 0.3 | D66: 0.4 | E66: 0.5 | F66: Развлекательные приложения: D30 5–10%; активное ядро держится дольше
A67: Конверсия активированного в платящего (1-й мес.) | B67: доля | C67: 0.02 | D67: 0.035 | E67: 0.05 | F67: RevenueCat 2026: freemium download→paid 2,1% (D35), игры 1,3%; ИИ-RP монетизируются лучше
A68: Ежемесячная конверсия базы free | B68: доля | C68: 0.002 | D68: 0.004 | E68: 0.006 | F68: Догоняющие покупки (лимит кончился)
A69: Отток платящих в месяц | B69: доля | C69: 0.2 | D69: 0.14 | E69: 0.1 | F69: RevenueCat: к 3-му продлению месячные планы удерживают 78–81%
A71: Прототип и донаты (до выхода MVP)
A72: Активных игроков прототипа в 1-й месяц | B72: чел. | C72: 200 | D72: 400 | E72: 800 | F72: Веб-демо (ADR 39) + Discord + Reddit
A73: Рост аудитории прототипа в месяц | B73: доля | C73: 0.15 | D73: 0.25 | E73: 0.35 | F73: Лист ожидания
A74: Ходов в месяц на игрока прототипа | B74: ходов | C74: =$D$74 | D74: 40 | E74: =$D$74 | F74: Строгий дневной лимит на демо
A75: Доля донатящих | B75: доля | C75: 0.01 | D75: 0.015 | E75: 0.02 | F75: Ko-fi/Patreon: 1–3% активной аудитории
A76: Средний донат в месяц | B76: $ | C76: 5 | D76: 6 | E76: 7 | F76: Ko-fi $3–5 за «кофе», Patreon $5–10
A77: Комиссия платформы донатов и PayPal/Payoneer | B77: доля | C77: =$D$77 | D77: 0.08 | E77: =$D$77 | F77: Ko-fi 0–5% + PayPal ~3%
A78: Доля игроков прототипа, перешедших в MVP | B78: доля | C78: =$D$78 | D78: 0.5 | E78: =$D$78 | F78: Оценка
A80: Затраты
A81: Маркетинг до выхода, в месяц | B81: $ | C81: =$D$81 | D81: 300 | E81: =$D$81 | F81: Тесты креативов TikTok/Reddit, микро-блогеры
A82: Доп. маркетинг в месяц выхода | B82: $ | C82: =$D$82 | D82: 2000 | E82: =$D$82 | F82: Запуск: Product Hunt, блогеры, реклама
A83: Маркетинг после выхода, минимум в месяц | B83: $ | C83: 600 | D83: 800 | E83: 1000 | F83: Пока выручка мала
A84: Реинвест чистой выручки в маркетинг | B84: доля | C84: =$D$84 | D84: 0.3 | E84: =$D$84 | F84: Маркетинг = max(минимум, доля × выручка прошлого месяца)
A85: Инфраструктура, база в месяц | B85: $ | C85: =$D$85 | D85: 40 | E85: =$D$85 | F85: VPS 2 GB + бэкапы + почта + мониторинг (сейчас VPS 1 GB)
A86: Инфраструктура на 1 активного в месяц | B86: $ | C86: =$D$86 | D86: 0.01 | E86: =$D$86 | F86: Postgres, RabbitMQ, трафик WebSocket
A87: SaaS-инструменты в месяц | B87: $ | C87: =$D$87 | D87: 30 | E87: =$D$87 | F87: RevenueCat (бесплатно до $2,5K MRR), аналитика, дизайн
A88: Бухгалтерия ООО в месяц | B88: $ | C88: =$D$88 | D88: 150 | E88: =$D$88 | F88: Оценка по рынку Тбилиси, нужны КП (≈400 GEL)
A89: Юр. сопровождение после выхода, в месяц | B89: $ | C89: =$D$89 | D89: 100 | E89: =$D$89 | F89: Обновления ToS, запросы магазинов, жалобы
A90: Apple Developer Program в год | B90: $ | C90: =$D$90 | D90: 99 | E90: =$D$90 | F90: developer.apple.com
A91: Google Play, разово | B91: $ | C91: =$D$91 | D91: 25 | E91: =$D$91 | F91: play.google.com/console
A92: Контент / SMM-подрядчик в месяц (со 2-го месяца после выхода) | B92: $ | C92: =$D$92 | D92: 400 | E92: =$D$92 | F92: Частичная занятость, можно долей из пула
A93: Проверка возраста (Teen) за проверку | B93: $ | C93: =$D$93 | D93: 0.15 | E93: =$D$93 | F93: Didit ~$0,10, iDenfy $0,55–0,75; Apple/Google API бесплатно
A94: Выплаты основателям — с месяца | B94: мес. | C94: =$D$94 | D94: 13 | E94: =$D$94 | F94: До этого основатели без зарплаты
A95: Выплаты основателям в месяц (на двоих), максимум | B95: $ | C95: =$D$95 | D95: 2000 | E95: =$D$95 | F95: Через ИП (1%) по договорам услуг
A96: Выплаты основателям — не больше доли прибыли прошлого месяца | B96: доля | C96: =$D$96 | D96: 0.5 | E96: =$D$96 | F96: Платим из прибыли, а не из вложений
A98: Оценка проекта
A99: Ставка дисконтирования (годовая) | B99: доля | C99: =$D$99 | D99: 0.5 | E99: =$D$99 | F99: Венчурная стадия pre-seed: 40–60%
A100: Терминальная стоимость: множитель к ARR 36-го месяца | B100: x | C100: 1 | D100: 2 | E100: 3 | F100: Потребительские подписки: 1–4x ARR
A102: Вложения (тыс. ₽). Выбранный вариант → лист «Модель_*»
A103: Выбранный вариант вложений (1 — мин., 2 — средний, 3 — макс.) | B103: № | C103: =$D$103 | D103: 2 | E103: =$D$103 | F103: Меняйте, чтобы пересчитать кассу
A104: Вариант 1 «Минимум»: партнёр / я | B104: ₽ | C104: 300000 | D104: 200000 | E104: =C104+D104 | F104: C — партнёр, D — я (основатель-разработчик), E — итого
A105: Вариант 2 «Средний»: партнёр / я | B105: ₽ | C105: 650000 | D105: 350000 | E105: =C105+D105 | F105: C — партнёр, D — я (основатель-разработчик), E — итого
A106: Вариант 3 «Максимум»: партнёр / я | B106: ₽ | C106: 1000000 | D106: 500000 | E106: =C106+D106 | F106: C — партнёр, D — я (основатель-разработчик), E — итого
A107: Партнёр: доля вложений в 1-м месяце (остальное — в месяц выхода) | B107: доля | C107: =$D$107 | D107: 0.5 | E107: =$D$107 | F107: Транши снижают риск партнёра
A108: Я: доступно сразу | B108: ₽ | C108: =$D$108 | D108: 200000 | E108: =$D$108 | F108: Со слов пользователя; остальное — по 1/3 в мес. 2–4 (половина зарплаты)

Sheet Сценарии
A1: Сводка по сценариям
A3: Показатель | B3: Пессим. | C3: Базовый | D3: Оптим.
A4: Выход MVP (месяц №) | B4: ='Допущения'!$C$9 | C4: ='Допущения'!$D$9 | D4: ='Допущения'!$E$9
A5: Первый месяц с EBITDA ≥ 0 (№) | B5: ='Модель_П'!$B$68 | C5: ='Модель_Б'!$B$68 | D5: ='Модель_О'!$B$68
A6: Устойчивая безубыточность: EBITDA ≥ 0 и дальше (№ мес.) | B6: ='Модель_П'!$B$69 | C6: ='Модель_Б'!$B$69 | D6: ='Модель_О'!$B$69
A7: Устойчивая безубыточность (дата) | B7: ='Модель_П'!$B$70 | C7: ='Модель_Б'!$B$70 | D7: ='Модель_О'!$B$70
A8: Окупаемость: накопленный поток ≥ 0 (№ мес.) | B8: ='Модель_П'!$B$71 | C8: ='Модель_Б'!$B$71 | D8: ='Модель_О'!$B$71
A9: Пиковая потребность в финансировании, $ | B9: ='Модель_П'!$B$72 | C9: ='Модель_Б'!$B$72 | D9: ='Модель_О'!$B$72
A10: То же, ₽ | B10: ='Модель_П'!$B$73 | C10: ='Модель_Б'!$B$73 | D10: ='Модель_О'!$B$73
A11: Чистая выручка, год 1, $ | B11: ='Модель_П'!$B$74 | C11: ='Модель_Б'!$B$74 | D11: ='Модель_О'!$B$74
A12: Чистая выручка, год 2, $ | B12: ='Модель_П'!$B$75 | C12: ='Модель_Б'!$B$75 | D12: ='Модель_О'!$B$75
A13: Чистая выручка, год 3, $ | B13: ='Модель_П'!$B$76 | C13: ='Модель_Б'!$B$76 | D13: ='Модель_О'!$B$76
A14: EBITDA, год 1, $ | B14: ='Модель_П'!$B$77 | C14: ='Модель_Б'!$B$77 | D14: ='Модель_О'!$B$77
A15: EBITDA, год 2, $ | B15: ='Модель_П'!$B$78 | C15: ='Модель_Б'!$B$78 | D15: ='Модель_О'!$B$78
A16: EBITDA, год 3, $ | B16: ='Модель_П'!$B$79 | C16: ='Модель_Б'!$B$79 | D16: ='Модель_О'!$B$79
A17: Активные, мес. 12 | B17: ='Модель_П'!$B$83 | C17: ='Модель_Б'!$B$83 | D17: ='Модель_О'!$B$83
A18: Активные, мес. 36 | B18: ='Модель_П'!$B$84 | C18: ='Модель_Б'!$B$84 | D18: ='Модель_О'!$B$84
A19: Платящие, мес. 12 | B19: ='Модель_П'!$B$80 | C19: ='Модель_Б'!$B$80 | D19: ='Модель_О'!$B$80
A20: Платящие, мес. 24 | B20: ='Модель_П'!$B$81 | C20: ='Модель_Б'!$B$81 | D20: ='Модель_О'!$B$81
A21: Платящие, мес. 36 | B21: ='Модель_П'!$B$82 | C21: ='Модель_Б'!$B$82 | D21: ='Модель_О'!$B$82
A22: MRR, мес. 12, $ | B22: ='Модель_П'!$B$85 | C22: ='Модель_Б'!$B$85 | D22: ='Модель_О'!$B$85
A23: MRR, мес. 24, $ | B23: ='Модель_П'!$B$86 | C23: ='Модель_Б'!$B$86 | D23: ='Модель_О'!$B$86
A24: MRR, мес. 36, $ | B24: ='Модель_П'!$B$87 | C24: ='Модель_Б'!$B$87 | D24: ='Модель_О'!$B$87
A25: ARR, мес. 36, $ | B25: ='Модель_П'!$B$88 | C25: ='Модель_Б'!$B$88 | D25: ='Модель_О'!$B$88
A26: CAC средний (маркетинг / новые платящие после выхода), $ | B26: ='Модель_П'!$B$89 | C26: ='Модель_Б'!$B$89 | D26: ='Модель_О'!$B$89
A27: LTV платящего (чистая выручка × маржа / отток), $ | B27: ='Модель_П'!$B$90 | C27: ='Модель_Б'!$B$90 | D27: ='Модель_О'!$B$90
A28: LTV / CAC | B28: ='Модель_П'!$B$91 | C28: ='Модель_Б'!$B$91 | D28: ='Модель_О'!$B$91
A29: Валовая маржа за 36 мес. | B29: ='Модель_П'!$B$92 | C29: ='Модель_Б'!$B$92 | D29: ='Модель_О'!$B$92
A30: NPV операционного потока + терминальная стоимость, $ | B30: ='Модель_П'!$B$93 | C30: ='Модель_Б'!$B$93 | D30: ='Модель_О'!$B$93
A31: IRR годовая | B31: ='Модель_П'!$B$94 | C31: ='Модель_Б'!$B$94 | D31: ='Модель_О'!$B$94
A32: Мин. касса: вариант 1, $ | B32: ='Модель_П'!$B$96 | C32: ='Модель_Б'!$B$96 | D32: ='Модель_О'!$B$96
A33: Мин. касса: вариант 2, $ | B33: ='Модель_П'!$B$97 | C33: ='Модель_Б'!$B$97 | D33: ='Модель_О'!$B$97
A34: Мин. касса: вариант 3, $ | B34: ='Модель_П'!$B$98 | C34: ='Модель_Б'!$B$98 | D34: ='Модель_О'!$B$98
A36: Касса на конец месяца, $ (выбранный вариант вложений) — для графика
A37: Месяц | B37: Пессимистичный | C37: Базовый | D37: Оптимистичный
A38: 1 | B38: ='Модель_П'!C55 | C38: ='Модель_Б'!C55 | D38: ='Модель_О'!C55
A39: 2 | B39: ='Модель_П'!D55 | C39: ='Модель_Б'!D55 | D39: ='Модель_О'!D55
A40: 3 | B40: ='Модель_П'!E55 | C40: ='Модель_Б'!E55 | D40: ='Модель_О'!E55
A41: 4 | B41: ='Модель_П'!F55 | C41: ='Модель_Б'!F55 | D41: ='Модель_О'!F55
A42: 5 | B42: ='Модель_П'!G55 | C42: ='Модель_Б'!G55 | D42: ='Модель_О'!G55
A43: 6 | B43: ='Модель_П'!H55 | C43: ='Модель_Б'!H55 | D43: ='Модель_О'!H55
A44: 7 | B44: ='Модель_П'!I55 | C44: ='Модель_Б'!I55 | D44: ='Модель_О'!I55
A45: 8 | B45: ='Модель_П'!J55 | C45: ='Модель_Б'!J55 | D45: ='Модель_О'!J55
A46: 9 | B46: ='Модель_П'!K55 | C46: ='Модель_Б'!K55 | D46: ='Модель_О'!K55
A47: 10 | B47: ='Модель_П'!L55 | C47: ='Модель_Б'!L55 | D47: ='Модель_О'!L55
A48: 11 | B48: ='Модель_П'!M55 | C48: ='Модель_Б'!M55 | D48: ='Модель_О'!M55
A49: 12 | B49: ='Модель_П'!N55 | C49: ='Модель_Б'!N55 | D49: ='Модель_О'!N55
A50: 13 | B50: ='Модель_П'!O55 | C50: ='Модель_Б'!O55 | D50: ='Модель_О'!O55
A51: 14 | B51: ='Модель_П'!P55 | C51: ='Модель_Б'!P55 | D51: ='Модель_О'!P55
A52: 15 | B52: ='Модель_П'!Q55 | C52: ='Модель_Б'!Q55 | D52: ='Модель_О'!Q55
A53: 16 | B53: ='Модель_П'!R55 | C53: ='Модель_Б'!R55 | D53: ='Модель_О'!R55
A54: 17 | B54: ='Модель_П'!S55 | C54: ='Модель_Б'!S55 | D54: ='Модель_О'!S55
A55: 18 | B55: ='Модель_П'!T55 | C55: ='Модель_Б'!T55 | D55: ='Модель_О'!T55
A56: 19 | B56: ='Модель_П'!U55 | C56: ='Модель_Б'!U55 | D56: ='Модель_О'!U55
A57: 20 | B57: ='Модель_П'!V55 | C57: ='Модель_Б'!V55 | D57: ='Модель_О'!V55
A58: 21 | B58: ='Модель_П'!W55 | C58: ='Модель_Б'!W55 | D58: ='Модель_О'!W55
A59: 22 | B59: ='Модель_П'!X55 | C59: ='Модель_Б'!X55 | D59: ='Модель_О'!X55
A60: 23 | B60: ='Модель_П'!Y55 | C60: ='Модель_Б'!Y55 | D60: ='Модель_О'!Y55
A61: 24 | B61: ='Модель_П'!Z55 | C61: ='Модель_Б'!Z55 | D61: ='Модель_О'!Z55
A62: 25 | B62: ='Модель_П'!AA55 | C62: ='Модель_Б'!AA55 | D62: ='Модель_О'!AA55
A63: 26 | B63: ='Модель_П'!AB55 | C63: ='Модель_Б'!AB55 | D63: ='Модель_О'!AB55
A64: 27 | B64: ='Модель_П'!AC55 | C64: ='Модель_Б'!AC55 | D64: ='Модель_О'!AC55
A65: 28 | B65: ='Модель_П'!AD55 | C65: ='Модель_Б'!AD55 | D65: ='Модель_О'!AD55
A66: 29 | B66: ='Модель_П'!AE55 | C66: ='Модель_Б'!AE55 | D66: ='Модель_О'!AE55
A67: 30 | B67: ='Модель_П'!AF55 | C67: ='Модель_Б'!AF55 | D67: ='Модель_О'!AF55
A68: 31 | B68: ='Модель_П'!AG55 | C68: ='Модель_Б'!AG55 | D68: ='Модель_О'!AG55
A69: 32 | B69: ='Модель_П'!AH55 | C69: ='Модель_Б'!AH55 | D69: ='Модель_О'!AH55
A70: 33 | B70: ='Модель_П'!AI55 | C70: ='Модель_Б'!AI55 | D70: ='Модель_О'!AI55
A71: 34 | B71: ='Модель_П'!AJ55 | C71: ='Модель_Б'!AJ55 | D71: ='Модель_О'!AJ55
A72: 35 | B72: ='Модель_П'!AK55 | C72: ='Модель_Б'!AK55 | D72: ='Модель_О'!AK55
A73: 36 | B73: ='Модель_П'!AL55 | C73: ='Модель_Б'!AL55 | D73: ='Модель_О'!AL55
A75: Платящие на конец месяца — для графика | B75: Пессимистичный | C75: Базовый | D75: Оптимистичный
A76: 1 | B76: ='Модель_П'!C21 | C76: ='Модель_Б'!C21 | D76: ='Модель_О'!C21
A77: 2 | B77: ='Модель_П'!D21 | C77: ='Модель_Б'!D21 | D77: ='Модель_О'!D21
A78: 3 | B78: ='Модель_П'!E21 | C78: ='Модель_Б'!E21 | D78: ='Модель_О'!E21
A79: 4 | B79: ='Модель_П'!F21 | C79: ='Модель_Б'!F21 | D79: ='Модель_О'!F21
A80: 5 | B80: ='Модель_П'!G21 | C80: ='Модель_Б'!G21 | D80: ='Модель_О'!G21
A81: 6 | B81: ='Модель_П'!H21 | C81: ='Модель_Б'!H21 | D81: ='Модель_О'!H21
A82: 7 | B82: ='Модель_П'!I21 | C82: ='Модель_Б'!I21 | D82: ='Модель_О'!I21
A83: 8 | B83: ='Модель_П'!J21 | C83: ='Модель_Б'!J21 | D83: ='Модель_О'!J21
A84: 9 | B84: ='Модель_П'!K21 | C84: ='Модель_Б'!K21 | D84: ='Модель_О'!K21
A85: 10 | B85: ='Модель_П'!L21 | C85: ='Модель_Б'!L21 | D85: ='Модель_О'!L21
A86: 11 | B86: ='Модель_П'!M21 | C86: ='Модель_Б'!M21 | D86: ='Модель_О'!M21
A87: 12 | B87: ='Модель_П'!N21 | C87: ='Модель_Б'!N21 | D87: ='Модель_О'!N21
A88: 13 | B88: ='Модель_П'!O21 | C88: ='Модель_Б'!O21 | D88: ='Модель_О'!O21
A89: 14 | B89: ='Модель_П'!P21 | C89: ='Модель_Б'!P21 | D89: ='Модель_О'!P21
A90: 15 | B90: ='Модель_П'!Q21 | C90: ='Модель_Б'!Q21 | D90: ='Модель_О'!Q21
A91: 16 | B91: ='Модель_П'!R21 | C91: ='Модель_Б'!R21 | D91: ='Модель_О'!R21
A92: 17 | B92: ='Модель_П'!S21 | C92: ='Модель_Б'!S21 | D92: ='Модель_О'!S21
A93: 18 | B93: ='Модель_П'!T21 | C93: ='Модель_Б'!T21 | D93: ='Модель_О'!T21
A94: 19 | B94: ='Модель_П'!U21 | C94: ='Модель_Б'!U21 | D94: ='Модель_О'!U21
A95: 20 | B95: ='Модель_П'!V21 | C95: ='Модель_Б'!V21 | D95: ='Модель_О'!V21
A96: 21 | B96: ='Модель_П'!W21 | C96: ='Модель_Б'!W21 | D96: ='Модель_О'!W21
A97: 22 | B97: ='Модель_П'!X21 | C97: ='Модель_Б'!X21 | D97: ='Модель_О'!X21
A98: 23 | B98: ='Модель_П'!Y21 | C98: ='Модель_Б'!Y21 | D98: ='Модель_О'!Y21
A99: 24 | B99: ='Модель_П'!Z21 | C99: ='Модель_Б'!Z21 | D99: ='Модель_О'!Z21
A100: 25 | B100: ='Модель_П'!AA21 | C100: ='Модель_Б'!AA21 | D100: ='Модель_О'!AA21
A101: 26 | B101: ='Модель_П'!AB21 | C101: ='Модель_Б'!AB21 | D101: ='Модель_О'!AB21
A102: 27 | B102: ='Модель_П'!AC21 | C102: ='Модель_Б'!AC21 | D102: ='Модель_О'!AC21
A103: 28 | B103: ='Модель_П'!AD21 | C103: ='Модель_Б'!AD21 | D103: ='Модель_О'!AD21
...

Sheet Себестоимость
A1: Себестоимость хода, лимиты и цена подписки
A2: «Запрос» = ход игрока: все вызовы guard + gm + npc + generator за одну реплику. Колонки C–E — сценарии.
A4: Показатель | B4: Ед. | C4: Пессим. | D4: Базовый | E4: Оптим. | F4: Формула / комментарий
A5: Ход на Haiku, токены теста | B5: $ | C5: =('Допущения'!$C$23*(1-'Допущения'!$C$26)*'Допущения'!$C$13+'Допущения'!$C$23*'Допущения'!$C$26*'Допущения'!$C$16+'Допущения'!$C$24*'Допущения'!$C$15+'Допущения'!$C$25*'Допущения'!$C$14)/1000000 | D5: =('Допущения'!$D$23*(1-'Допущения'!$D$26)*'Допущения'!$D$13+'Допущения'!$D$23*'Допущения'!$D$26*'Допущения'!$D$16+'Допущения'!$D$24*'Допущения'!$D$15+'Допущения'!$D$25*'Допущения'!$D$14)/1000000 | E5: =('Допущения'!$E$23*(1-'Допущения'!$E$26)*'Допущения'!$E$13+'Допущения'!$E$23*'Допущения'!$E$26*'Допущения'!$E$16+'Допущения'!$E$24*'Допущения'!$E$15+'Допущения'!$E$25*'Допущения'!$E$14)/1000000 | F5: Проверка: фактическое среднее по тестам $0,00186
A6: Тот же ход целиком на Sonnet | B6: $ | C6: =('Допущения'!$C$23*(1-'Допущения'!$C$26)*'Допущения'!$C$17+'Допущения'!$C$23*'Допущения'!$C$26*'Допущения'!$C$20+'Допущения'!$C$24*'Допущения'!$C$19+'Допущения'!$C$25*'Допущения'!$C$18)/1000000 | D6: =('Допущения'!$D$23*(1-'Допущения'!$D$26)*'Допущения'!$D$17+'Допущения'!$D$23*'Допущения'!$D$26*'Допущения'!$D$20+'Допущения'!$D$24*'Допущения'!$D$19+'Допущения'!$D$25*'Допущения'!$D$18)/1000000 | E6: =('Допущения'!$E$23*(1-'Допущения'!$E$26)*'Допущения'!$E$17+'Допущения'!$E$23*'Допущения'!$E$26*'Допущения'!$E$20+'Допущения'!$E$24*'Допущения'!$E$19+'Допущения'!$E$25*'Допущения'!$E$18)/1000000 | F6: Справочно: в Premium на Sonnet только мастер
A7: Себестоимость хода Haiku (с запасом и модерацией) | B7: $ | C7: =$C$5*'Допущения'!$C$28+'Допущения'!$C$29 | D7: =$D$5*'Допущения'!$D$28+'Допущения'!$D$29 | E7: =$E$5*'Допущения'!$E$28+'Допущения'!$E$29 | F7: × множитель длинных сессий + модерация
A8: Себестоимость хода Premium (мастер на Sonnet, прочие — Haiku) | B8: $ | C8: =('Допущения'!$C$27*$C$6+(1-'Допущения'!$C$27)*$C$5)*'Допущения'!$C$28+'Допущения'!$C$29 | D8: =('Допущения'!$D$27*$D$6+(1-'Допущения'!$D$27)*$D$5)*'Допущения'!$D$28+'Допущения'!$D$29 | E8: =('Допущения'!$E$27*$E$6+(1-'Допущения'!$E$27)*$E$5)*'Допущения'!$E$28+'Допущения'!$E$29
A9: Premium-ход дороже Haiku-хода в | B9: x | C9: =$C$8/$C$7 | D9: =$D$8/$D$7 | E9: =$E$8/$E$7
A10: Чистыми с $1 цены (после магазинов, Paddle %, НДС) | B10: доля | C10: =(1-'Допущения'!$C$56)*((1-'Допущения'!$C$53)*(1-'Допущения'!$C$52)+'Допущения'!$C$53*(1-'Допущения'!$C$54)) | D10: =(1-'Допущения'!$D$56)*((1-'Допущения'!$D$53)*(1-'Допущения'!$D$52)+'Допущения'!$D$53*(1-'Допущения'!$D$54)) | E10: =(1-'Допущения'!$E$56)*((1-'Допущения'!$E$53)*(1-'Допущения'!$E$52)+'Допущения'!$E$53*(1-'Допущения'!$E$54)) | F10: Фикс. $0,50 Paddle вычитается отдельно
A11: Комфортный объём, ходов в месяц | B11: ходов | C11: =ROUNDUP('Допущения'!$C$33*'Допущения'!$C$34*52/12/100,0)*100 | D11: =ROUNDUP('Допущения'!$D$33*'Допущения'!$D$34*52/12/100,0)*100 | E11: =ROUNDUP('Допущения'!$E$33*'Допущения'!$E$34*52/12/100,0)*100 | F11: сессия × сессий в неделю × 4,33, вверх до сотни
A12: ARPPU брутто (средневзвешенная цена) | B12: $ | C12: ='Допущения'!$C$44*'Допущения'!$C$35+'Допущения'!$C$45*'Допущения'!$C$37+'Допущения'!$C$46*'Допущения'!$C$39+'Допущения'!$C$47*'Допущения'!$C$42 | D12: ='Допущения'!$D$44*'Допущения'!$D$35+'Допущения'!$D$45*'Допущения'!$D$37+'Допущения'!$D$46*'Допущения'!$D$39+'Допущения'!$D$47*'Допущения'!$D$42 | E12: ='Допущения'!$E$44*'Допущения'!$E$35+'Допущения'!$E$45*'Допущения'!$E$37+'Допущения'!$E$46*'Допущения'!$E$39+'Допущения'!$E$47*'Допущения'!$E$42 | F12: Σ доля × цена
A13: Чистая выручка на платящего | B13: $ | C13: ='Допущения'!$C$44*('Допущения'!$C$35*$C$10-'Допущения'!$C$53*'Допущения'!$C$55)+'Допущения'!$C$45*('Допущения'!$C$37*$C$10-'Допущения'!$C$53*'Допущения'!$C$55)+'Допущения'!$C$46*('Допущения'!$C$39*$C$10-'Допущения'!$C$53*'Допущения'!$C$55)+'Допущения'!$C$47*('Допущения'!$C$42*$C$10-'Допущения'!$C$53*'Допущения'!$C$55) | D13: ='Допущения'!$D$44*('Допущения'!$D$35*$D$10-'Допущения'!$D$53*'Допущения'!$D$55)+'Допущения'!$D$45*('Допущения'!$D$37*$D$10-'Допущения'!$D$53*'Допущения'!$D$55)+'Допущения'!$D$46*('Допущения'!$D$39*$D$10-'Допущения'!$D$53*'Допущения'!$D$55)+'Допущения'!$D$47*('Допущения'!$D$42*$D$10-'Допущения'!$D$53*'Допущения'!$D$55) | E13: ='Допущения'!$E$44*('Допущения'!$E$35*$E$10-'Допущения'!$E$53*'Допущения'!$E$55)+'Допущения'!$E$45*('Допущения'!$E$37*$E$10-'Допущения'!$E$53*'Допущения'!$E$55)+'Допущения'!$E$46*('Допущения'!$E$39*$E$10-'Допущения'!$E$53*'Допущения'!$E$55)+'Допущения'!$E$47*('Допущения'!$E$42*$E$10-'Допущения'!$E$53*'Допущения'!$E$55)
A14: Ожидаемые затраты на LLM на платящего | B14: $ | C14: ='Допущения'!$C$44*(('Допущения'!$C$36-0)*$C$7+0*$C$8)*'Допущения'!$C$48+'Допущения'!$C$45*(('Допущения'!$C$38-0)*$C$7+0*$C$8)*'Допущения'!$C$48+'Допущения'!$C$46*(('Допущения'!$C$40-'Допущения'!$C$41)*$C$7+'Допущения'!$C$41*$C$8)*'Допущения'!$C$48+'Допущения'!$C$47*(('Допущения'!$C$43-0)*$C$7+0*$C$8)*'Допущения'!$C$48 | D14: ='Допущения'!$D$44*(('Допущения'!$D$36-0)*$D$7+0*$D$8)*'Допущения'!$D$48+'Допущения'!$D$45*(('Допущения'!$D$38-0)*$D$7+0*$D$8)*'Допущения'!$D$48+'Допущения'!$D$46*(('Допущения'!$D$40-'Допущения'!$D$41)*$D$7+'Допущения'!$D$41*$D$8)*'Допущения'!$D$48+'Допущения'!$D$47*(('Допущения'!$D$43-0)*$D$7+0*$D$8)*'Допущения'!$D$48 | E14: ='Допущения'!$E$44*(('Допущения'!$E$36-0)*$E$7+0*$E$8)*'Допущения'!$E$48+'Допущения'!$E$45*(('Допущения'!$E$38-0)*$E$7+0*$E$8)*'Допущения'!$E$48+'Допущения'!$E$46*(('Допущения'!$E$40-'Допущения'!$E$41)*$E$7+'Допущения'!$E$41*$E$8)*'Допущения'!$E$48+'Допущения'!$E$47*(('Допущения'!$E$43-0)*$E$7+0*$E$8)*'Допущения'!$E$48 | F14: × средняя выборка лимита
A15: Валовая маржа платящего | B15: доля | C15: =IFERROR(($C$13-$C$14)/$C$13,0) | D15: =IFERROR(($D$13-$D$14)/$D$13,0) | E15: =IFERROR(($E$13-$E$14)/$E$13,0)
A16: Затраты на активного free в месяц | B16: $ | C16: ='Допущения'!$C$49*$C$7 | D16: ='Допущения'!$D$49*$D$7 | E16: ='Допущения'!$E$49*$E$7
A18: Себестоимость подписки по объёмам (базовый сценарий), лимит недели = ¼ месячного
A19: Целевая валовая маржа | D19: 0.7 | F19: Ориентир для подписок с ИИ: 60–75%
A21: Объём / модель | B21: Ходов в мес. | C21: Ходов в неделю (¼) | D21: Неделя 4: дней (мес. 28/30/31) | E21: Неделя 4: ходов в день (при 31 дне) | F21: Себест. при 100% лимита, $ | G21: Себест. ожидаемая, $ | H21: Цена при марже 70% от 100% лимита, $ | I21: Цена при марже 70% от ожидаемой, $ | J21: Себест. в ₽ (100%)
A22: 1 000 ходов — Haiku | B22: =1000 | C22: =B22/4 | D22: 7 / 9 / 10 | E22: =C22/10 | F22: =B22*$D$7 | G22: =F22*'Допущения'!$D$48 | H22: =(F22/(1-$D$19)+'Допущения'!$D$53*'Допущения'!$D$55)/$D$10 | I22: =(G22/(1-$D$19)+'Допущения'!$D$53*'Допущения'!$D$55)/$D$10 | J22: =F22*'Допущения'!$D$7
A23: Комфорт — Haiku | B23: =$D$11 | C23: =B23/4 | D23: 7 / 9 / 10 | E23: =C23/10 | F23: =B23*$D$7 | G23: =F23*'Допущения'!$D$48 | H23: =(F23/(1-$D$19)+'Допущения'!$D$53*'Допущения'!$D$55)/$D$10 | I23: =(G23/(1-$D$19)+'Допущения'!$D$53*'Допущения'!$D$55)/$D$10 | J23: =F23*'Допущения'!$D$7
A24: 10 000 ходов — Haiku | B24: =10000 | C24: =B24/4 | D24: 7 / 9 / 10 | E24: =C24/10 | F24: =B24*$D$7 | G24: =F24*'Допущения'!$D$48 | H24: =(F24/(1-$D$19)+'Допущения'!$D$53*'Допущения'!$D$55)/$D$10 | I24: =(G24/(1-$D$19)+'Допущения'!$D$53*'Допущения'!$D$55)/$D$10 | J24: =F24*'Допущения'!$D$7
A25: 1 000 ходов — мастер на Sonnet | B25: =1000 | C25: =B25/4 | D25: 7 / 9 / 10 | E25: =C25/10 | F25: =B25*$D$8 | G25: =F25*'Допущения'!$D$48 | H25: =(F25/(1-$D$19)+'Допущения'!$D$53*'Допущения'!$D$55)/$D$10 | I25: =(G25/(1-$D$19)+'Допущения'!$D$53*'Допущения'!$D$55)/$D$10 | J25: =F25*'Допущения'!$D$7
A26: Комфорт — мастер на Sonnet | B26: =$D$11 | C26: =B26/4 | D26: 7 / 9 / 10 | E26: =C26/10 | F26: =B26*$D$8 | G26: =F26*'Допущения'!$D$48 | H26: =(F26/(1-$D$19)+'Допущения'!$D$53*'Допущения'!$D$55)/$D$10 | I26: =(G26/(1-$D$19)+'Допущения'!$D$53*'Допущения'!$D$55)/$D$10 | J26: =F26*'Допущения'!$D$7
A27: 10 000 ходов — мастер на Sonnet | B27: =10000 | C27: =B27/4 | D27: 7 / 9 / 10 | E27: =C27/10 | F27: =B27*$D$8 | G27: =F27*'Допущения'!$D$48 | H27: =(F27/(1-$D$19)+'Допущения'!$D$53*'Допущения'!$D$55)/$D$10 | I27: =(G27/(1-$D$19)+'Допущения'!$D$53*'Допущения'!$D$55)/$D$10 | J27: =F27*'Допущения'!$D$7
A28: Free (30 в неделю) | B28: ='Допущения'!$D$32*4 | C28: =B28/4 | D28: 7 / 9 / 10 | E28: =C28/10 | F28: =B28*$D$7 | G28: =F28*'Допущения'!$D$48 | H28: =(F28/(1-$D$19)+'Допущения'!$D$53*'Допущения'!$D$55)/$D$10 | I28: =(G28/(1-$D$19)+'Допущения'!$D$53*'Допущения'!$D$55)/$D$10 | J28: =F28*'Допущения'!$D$7
A29: Окна лимита привязаны к дате подписки: недели 1–3 — по 7 дней, неделя 4 — с 22-го дня до продления (7–10 дней в зависимости от длины месяца). Неиспользованный остаток недели не переносится.
A31: Рекомендуемая тарифная сетка (базовый сценарий)
A32: Тариф | B32: Цена, $/мес | C32: Ходов в мес. | D32: Ходов в неделю | E32: Из них Sonnet | F32: Себест. 100% лимита, $ | G32: Себест. ожидаемая, $ | H32: Чистая выручка, $ | I32: Маржа при 100% лимита | J32: Маржа ожидаемая
A33: Free | B33: 0 | C33: ='Допущения'!$D$32*4 | D33: ='Допущения'!$D$32 | E33: 0 | F33: =C33*$D$7 | G33: ='Допущения'!$D$49*$D$7 | H33: 0 | I33: — | J33: —
A34: Teen 13–17 | B34: ='Допущения'!$D$35 | C34: ='Допущения'!$D$36 | D34: =C34/4 | E34: 0 | F34: =(('Допущения'!$D$36-0)*$D$7+0*$D$8) | G34: =(('Допущения'!$D$36-0)*$D$7+0*$D$8)*'Допущения'!$D$48 | H34: =('Допущения'!$D$35*$D$10-'Допущения'!$D$53*'Допущения'!$D$55) | I34: =IFERROR((H34-F34)/H34,0) | J34: =IFERROR((H34-G34)/H34,0)
A35: Standard | B35: ='Допущения'!$D$37 | C35: ='Допущения'!$D$38 | D35: =C35/4 | E35: 0 | F35: =(('Допущения'!$D$38-0)*$D$7+0*$D$8) | G35: =(('Допущения'!$D$38-0)*$D$7+0*$D$8)*'Допущения'!$D$48 | H35: =('Допущения'!$D$37*$D$10-'Допущения'!$D$53*'Допущения'!$D$55) | I35: =IFERROR((H35-F35)/H35,0) | J35: =IFERROR((H35-G35)/H35,0)
A36: Premium | B36: ='Допущения'!$D$39 | C36: ='Допущения'!$D$40 | D36: =C36/4 | E36: ='Допущения'!$D$41 | F36: =(('Допущения'!$D$40-'Допущения'!$D$41)*$D$7+'Допущения'!$D$41*$D$8) | G36: =(('Допущения'!$D$40-'Допущения'!$D$41)*$D$7+'Допущения'!$D$41*$D$8)*'Допущения'!$D$48 | H36: =('Допущения'!$D$39*$D$10-'Допущения'!$D$53*'Допущения'!$D$55) | I36: =IFERROR((H36-F36)/H36,0) | J36: =IFERROR((H36-G36)/H36,0)
A37: Legend 10 000 | B37: ='Допущения'!$D$42 | C37: ='Допущения'!$D$43 | D37: =C37/4 | E37: 0 | F37: =(('Допущения'!$D$43-0)*$D$7+0*$D$8) | G37: =(('Допущения'!$D$43-0)*$D$7+0*$D$8)*'Допущения'!$D$48 | H37: =('Допущения'!$D$42*$D$10-'Допущения'!$D$53*'Допущения'!$D$55) | I37: =IFERROR((H37-F37)/H37,0) | J37: =IFERROR((H37-G37)/H37,0)
A38: Отрицательная маржа при 100% лимита — риск «китов». Защита: недельные окна, мягкое замедление после 80% лимита, честное «fair use» в условиях.

Sheet Старт
A1: Стартовые разовые затраты (регулярные — в «Модель_*»)
A2: Месяц — номер месяца модели (1 = ноябрь 2026). Суммы — оценки по открытым источникам на 17.10.2026; по юр. услугам запросить 2–3 КП.
A4: Статья | B4: Этап | C4: Месяц | D4: Сумма, $ | E4: Сумма, ₽ | F4: Обязательность | G4: Источник / комментарий
A5: Домен .com/.app + почта на год | B5: 0. Прототип | C5: =1 | D5: 40 | E5: =D5*'Допущения'!$D$7 | F5: обяз. | G5: Cloudflare Registrar / Namecheap
A6: Б/у Android-телефон для тестов | B6: 0. Прототип | C6: =1 | D6: 150 | E6: =D6*'Допущения'!$D$7 | F6: желат. | G6: Сейчас — эмулятор; нужен реальный девайс
A7: Госпошлина ООО, юр. адрес на год, переводы и нотариус | B7: 1. До MVP | C7: ='Допущения'!$D$10 | D7: 250 | E7: =D7*'Допущения'!$D$7 | F7: обяз. | G7: Дом юстиции: 100–200 GEL; юр. адрес ~$100–150/год
A8: Юрист: устав ООО с вестингом + соглашение участников | B8: 1. До MVP | C8: ='Допущения'!$D$10 | D8: 1000 | E8: =D8*'Допущения'!$D$7 | F8: обяз. | G8: Под ключ $500–1000 + SHA; запросить КП
A9: Регистрация ИП ×2 + статус малого бизнеса (1%) | B9: 1. До MVP | C9: ='Допущения'!$D$10 | D9: 200 | E9: =D9*'Допущения'!$D$7 | F9: желат. | G9: Для выплат основателям по договорам услуг
A10: Разрешения на работу (Special Labour Permit) ×2 с сопровождением | B10: 1. До MVP | C10: ='Допущения'!$D$10 | D10: 600 | E10: =D10*'Допущения'!$D$7 | F10: обяз. | G10: С 01.03.2026 нужны директору ООО и ИП-иностранцу; пошлину уточнить
A11: Статус Virtual Zone (заявка через провайдера) | B11: 1. До MVP | C11: ='Допущения'!$D$10+1 | D11: 670 | E11: =D11*'Допущения'!$D$7 | F11: обяз. | G11: 1 500 GEL + НДС (ExpatHub) ≈ $670
A12: Товарный знак США (USPTO), 2 класса (9, 41) | B12: 1. До MVP | C12: ='Допущения'!$D$10+1 | D12: 700 | E12: =D12*'Допущения'!$D$7 | F12: желат. | G12: $350 за класс (2026)
A13: Патентный поверенный (поиск, подача) | B13: 1. До MVP | C13: ='Допущения'!$D$10+1 | D13: 500 | E13: =D13*'Допущения'!$D$7 | F13: желат. | G13: Оценка
A14: ToS, Privacy Policy, AI-дисклеймеры, политика безопасности — проверка юристом | B14: 1. До MVP | C14: ='Допущения'!$D$9-1 | D14: 1200 | E14: =D14*'Допущения'!$D$7 | F14: обяз. | G14: COPPA, GDPR, CCPA, SB 243, EU AI Act ст. 50
A15: Материалы магазинов: иконка, скриншоты, трейлер | B15: 1. До MVP | C15: ='Допущения'!$D$9-1 | D15: 300 | E15: =D15*'Допущения'!$D$7 | F15: обяз. | G15: Делаю сам + генерация; бюджет на стоки/озвучку
A16: Набор тестов безопасности (кризисные сценарии), red-teaming | B16: 1. До MVP | C16: ='Допущения'!$D$9-1 | D16: 300 | E16: =D16*'Допущения'!$D$7 | F16: обяз. | G16: Внешний тестировщик-модератор, разово
A17: Товарный знак ЕС (EUIPO), 2 класса | B17: 2. После выхода | C17: ='Допущения'!$D$9+4 | D17: 1050 | E17: =D17*'Допущения'!$D$7 | F17: желат. | G17: €850 + €50 ≈ $1 050
A18: Итого разовые | D18: =SUM(D5:D17) | E18: =SUM(E5:E17)
A19: в т. ч. обязательные | D19: =SUMIF(F5:F17,"обяз.",D5:D17) | E19: =D19*'Допущения'!$D$7
A21: Бюджет до выхода MVP включительно (из модели, все затраты)
A22: Пессимистичный: расходы мес. 1 … выход | D22: ='Модель_П'!$B$99 | E22: =D22*'Допущения'!$D$7
A23: Базовый: расходы мес. 1 … выход | D23: ='Модель_Б'!$B$99 | E23: =D23*'Допущения'!$D$7
A24: Оптимистичный: расходы мес. 1 … выход | D24: ='Модель_О'!$B$99 | E24: =D24*'Допущения'!$D$7
A25: Резерв на непредвиденное | C25: 0.15
A26: Базовый: стартовый бюджет с резервом | D26: =D23*(1+C25) | E26: =D26*'Допущения'!$D$7

Sheet Модель_Б
A1: Финмодель на 36 месяцев — сценарий: Базовый
A2: Все значения считаются формулами из листов «Допущения», «Себестоимость», «Старт».
B5: Итого / знач.
A6: Месяц № | C6: 1 | D6: 2 | E6: 3 | F6: 4 | G6: 5 | H6: 6 | I6: 7 | J6: 8 | K6: 9 | L6: 10 | M6: 11 | N6: 12 | O6: 13 | P6: 14 | Q6: 15 | R6: 16 | S6: 17 | T6: 18 | U6: 19 | V6: 20 | W6: 21 | X6: 22 | Y6: 23 | Z6: 24 | AA6: 25 | AB6: 26 | AC6: 27 | AD6: 28 | AE6: 29 | AF6: 30 | AG6: 31 | AH6: 32 | AI6: 33 | AJ6: 34 | AK6: 35 | AL6: 36
A7: Месяц | C7: ноя 2026 | D7: дек 2026 | E7: янв 2027 | F7: фев 2027 | G7: мар 2027 | H7: апр 2027 | I7: май 2027 | J7: июн 2027 | K7: июл 2027 | L7: авг 2027 | M7: сен 2027 | N7: окт 2027 | O7: ноя 2027 | P7: дек 2027 | Q7: янв 2028 | R7: фев 2028 | S7: мар 2028 | T7: апр 2028 | U7: май 2028 | V7: июн 2028 | W7: июл 2028 | X7: авг 2028 | Y7: сен 2028 | Z7: окт 2028 | AA7: ноя 2028 | AB7: дек 2028 | AC7: янв 2029 | AD7: фев 2029 | AE7: мар 2029 | AF7: апр 2029 | AG7: май 2029 | AH7: июн 2029 | AI7: июл 2029 | AJ7: авг 2029 | AK7: сен 2029 | AL7: окт 2029
A8: Год проекта | C8: 1 | D8: 1 | E8: 1 | F8: 1 | G8: 1 | H8: 1 | I8: 1 | J8: 1 | K8: 1 | L8: 1 | M8: 1 | N8: 1 | O8: 2 | P8: 2 | Q8: 2 | R8: 2 | S8: 2 | T8: 2 | U8: 2 | V8: 2 | W8: 2 | X8: 2 | Y8: 2 | Z8: 2 | AA8: 3 | AB8: 3 | AC8: 3 | AD8: 3 | AE8: 3 | AF8: 3 | AG8: 3 | AH8: 3 | AI8: 3 | AJ8: 3 | AK8: 3 | AL8: 3
A9: Рынок (1 = MVP вышел) | C9: =IF(C6>='Допущения'!$D$9,1,0) | D9: =IF(D6>='Допущения'!$D$9,1,0) | E9: =IF(E6>='Допущения'!$D$9,1,0) | F9: =IF(F6>='Допущения'!$D$9,1,0) | G9: =IF(G6>='Допущения'!$D$9,1,0) | H9: =IF(H6>='Допущения'!$D$9,1,0) | I9: =IF(I6>='Допущения'!$D$9,1,0) | J9: =IF(J6>='Допущения'!$D$9,1,0) | ... AL9: =IF(AL6>='Допущения'!$D$9,1,0)
A10: ВОРОНКА
A11: Маркетинг, $ | B11: =SUM(C11:AL11) | C11: =IF(C9=1,MAX('Допущения'!$D$83,'Допущения'!$D$84*0)+IF(C6='Допущения'!$D$9,'Допущения'!$D$82,0),'Допущения'!$D$81) | D11: =IF(D9=1,MAX('Допущения'!$D$83,'Допущения'!$D$84*C28)+IF(D6='Допущения'!$D$9,'Допущения'!$D$82,0),'Допущения'!$D$81) | E11: =IF(E9=1,MAX('Допущения'!$D$83,'Допущения'!$D$84*D28)+IF(E6='Допущения'!$D$9,'Допущения'!$D$82,0),'Допущения'!$D$81) | F11: =IF(F9=1,MAX('Допущения'!$D$83,'Допущения'!$D$84*E28)+IF(F6='Допущения'!$D$9,'Допущения'!$D$82,0),'Допущения'!$D$81) | G11: =IF(G9=1,MAX('Допущения'!$D$83,'Допущения'!$D$84*F28)+IF(G6='Допущения'!$D$9,'Допущения'!$D$82,0),'Допущения'!$D$81) | H11: =IF(H9=1,MAX('Допущения'!$D$83,'Допущения'!$D$84*G28)+IF(H6='Допущения'!$D$9,'Допущения'!$D$82,0),'Допущения'!$D$81) | I11: =IF(I9=1,MAX('Допущения'!$D$83,'Допущения'!$D$84*H28)+IF(I6='Допущения'!$D$9,'Допущения'!$D$82,0),'Допущения'!$D$81) | J11: =IF(J9=1,MAX('Допущения'!$D$83,'Допущения'!$D$84*I28)+IF(J6='Допущения'!$D$9,'Допущения'!$D$82,0),'Допущения'!$D$81) | K11: =IF(K9=1,MAX('Допущения'!$D$83,'Допущения'!$D$84*J28)+IF(K6='Допущения'!$D$9,'Допущения'!$D$82,0),'Допущения'!$D$81) | ... AL11: =IF(AL9=1,MAX('Допущения'!$D$83,'Допущения'!$D$84*AK28)+IF(AL6='Допущения'!$D$9,'Допущения'!$D$82,0),'Допущения'!$D$81)
A12: Платные установки | B12: =SUM(C12:AL12) | C12: =IF(C9=1,C11/'Допущения'!$D$60,0) | D12: =IF(D9=1,D11/'Допущения'!$D$60,0) | E12: =IF(E9=1,E11/'Допущения'!$D$60,0) | F12: =IF(F9=1,F11/'Допущения'!$D$60,0) | G12: =IF(G9=1,G11/'Допущения'!$D$60,0) | H12: =IF(H9=1,H11/'Допущения'!$D$60,0) | I12: =IF(I9=1,I11/'Допущения'!$D$60,0) | J12: =IF(J9=1,J11/'Допущения'!$D$60,0) | ... AL12: =IF(AL9=1,AL11/'Допущения'!$D$60,0)
A13: Органические установки | B13: =SUM(C13:AL13) | C13: =IF(C9=1,MIN('Допущения'!$D$63,'Допущения'!$D$61*(1+'Допущения'!$D$62)^(C6-'Допущения'!$D$9)),0) | D13: =IF(D9=1,MIN('Допущения'!$D$63,'Допущения'!$D$61*(1+'Допущения'!$D$62)^(D6-'Допущения'!$D$9)),0) | E13: =IF(E9=1,MIN('Допущения'!$D$63,'Допущения'!$D$61*(1+'Допущения'!$D$62)^(E6-'Допущения'!$D$9)),0) | F13: =IF(F9=1,MIN('Допущения'!$D$63,'Допущения'!$D$61*(1+'Допущения'!$D$62)^(F6-'Допущения'!$D$9)),0) | G13: =IF(G9=1,MIN('Допущения'!$D$63,'Допущения'!$D$61*(1+'Допущения'!$D$62)^(G6-'Допущения'!$D$9)),0) | H13: =IF(H9=1,MIN('Допущения'!$D$63,'Допущения'!$D$61*(1+'Допущения'!$D$62)^(H6-'Допущения'!$D$9)),0) | I13: =IF(I9=1,MIN('Допущения'!$D$63,'Допущения'!$D$61*(1+'Допущения'!$D$62)^(I6-'Допущения'!$D$9)),0) | J13: =IF(J9=1,MIN('Допущения'!$D$63,'Допущения'!$D$61*(1+'Допущения'!$D$62)^(J6-'Допущения'!$D$9)),0) | ... AL13: =IF(AL9=1,MIN('Допущения'!$D$63,'Допущения'!$D$61*(1+'Допущения'!$D$62)^(AL6-'Допущения'!$D$9)),0)
A14: Вирусные установки | B14: =SUM(C14:AL14) | C14: =(C12+C13)*'Допущения'!$D$64 | D14: =(D12+D13)*'Допущения'!$D$64 | E14: =(E12+E13)*'Допущения'!$D$64 | F14: =(F12+F13)*'Допущения'!$D$64 | G14: =(G12+G13)*'Допущения'!$D$64 | H14: =(H12+H13)*'Допущения'!$D$64 | I14: =(I12+I13)*'Допущения'!$D$64 | J14: =(J12+J13)*'Допущения'!$D$64 | ... AL14: =(AL12+AL13)*'Допущения'!$D$64
A15: Всего установок | B15: =SUM(C15:AL15) | C15: =C12+C13+C14 | D15: =D12+D13+D14 | E15: =E12+E13+E14 | F15: =F12+F13+F14 | G15: =G12+G13+G14 | H15: =H12+H13+H14 | I15: =I12+I13+I14 | J15: =J12+J13+J14 | ... AL15: =AL12+AL13+AL14
A16: Новые активированные | B16: =SUM(C16:AL16) | C16: =C15*'Допущения'!$D$65+IF(C6='Допущения'!$D$9,0*'Допущения'!$D$78,0) | D16: =D15*'Допущения'!$D$65+IF(D6='Допущения'!$D$9,C17*'Допущения'!$D$78,0) | E16: =E15*'Допущения'!$D$65+IF(E6='Допущения'!$D$9,D17*'Допущения'!$D$78,0) | F16: =F15*'Допущения'!$D$65+IF(F6='Допущения'!$D$9,E17*'Допущения'!$D$78,0) | G16: =G15*'Допущения'!$D$65+IF(G6='Допущения'!$D$9,F17*'Допущения'!$D$78,0) | H16: =H15*'Допущения'!$D$65+IF(H6='Допущения'!$D$9,G17*'Допущения'!$D$78,0) | I16: =I15*'Допущения'!$D$65+IF(I6='Допущения'!$D$9,H17*'Допущения'!$D$78,0) | J16: =J15*'Допущения'!$D$65+IF(J6='Допущения'!$D$9,I17*'Допущения'!$D$78,0) | K16: =K15*'Допущения'!$D$65+IF(K6='Допущения'!$D$9,J17*'Допущения'!$D$78,0) | ... AL16: =AL15*'Допущения'!$D$65+IF(AL6='Допущения'!$D$9,AK17*'Допущения'!$D$78,0)
A17: Игроки прототипа (до выхода) | C17: =IF(C9=1,0,'Допущения'!$D$72*(1+'Допущения'!$D$73)^(C6-1)) | D17: =IF(D9=1,0,'Допущения'!$D$72*(1+'Допущения'!$D$73)^(D6-1)) | E17: =IF(E9=1,0,'Допущения'!$D$72*(1+'Допущения'!$D$73)^(E6-1)) | F17: =IF(F9=1,0,'Допущения'!$D$72*(1+'Допущения'!$D$73)^(F6-1)) | G17: =IF(G9=1,0,'Допущения'!$D$72*(1+'Допущения'!$D$73)^(G6-1)) | H17: =IF(H9=1,0,'Допущения'!$D$72*(1+'Допущения'!$D$73)^(H6-1)) | I17: =IF(I9=1,0,'Допущения'!$D$72*(1+'Допущения'!$D$73)^(I6-1)) | J17: =IF(J9=1,0,'Допущения'!$D$72*(1+'Допущения'!$D$73)^(J6-1)) | ... AL17: =IF(AL9=1,0,'Допущения'!$D$72*(1+'Допущения'!$D$73)^(AL6-1))
A18: Активные free (на конец мес.) | C18: =IF(C9=1,0*(1-'Допущения'!$D$68)*'Допущения'!$D$66+C16*(1-'Допущения'!$D$67),0) | D18: =IF(D9=1,C18*(1-'Допущения'!$D$68)*'Допущения'!$D$66+D16*(1-'Допущения'!$D$67),0) | E18: =IF(E9=1,D18*(1-'Допущения'!$D$68)*'Допущения'!$D$66+E16*(1-'Допущения'!$D$67),0) | F18: =IF(F9=1,E18*(1-'Допущения'!$D$68)*'Допущения'!$D$66+F16*(1-'Допущения'!$D$67),0) | G18: =IF(G9=1,F18*(1-'Допущения'!$D$68)*'Допущения'!$D$66+G16*(1-'Допущения'!$D$67),0) | H18: =IF(H9=1,G18*(1-'Допущения'!$D$68)*'Допущения'!$D$66+H16*(1-'Допущения'!$D$67),0) | I18: =IF(I9=1,H18*(1-'Допущения'!$D$68)*'Допущения'!$D$66+I16*(1-'Допущения'!$D$67),0) | J18: =IF(J9=1,I18*(1-'Допущения'!$D$68)*'Допущения'!$D$66+J16*(1-'Допущения'!$D$67),0) | K18: =IF(K9=1,J18*(1-'Допущения'!$D$68)*'Допущения'!$D$66+K16*(1-'Допущения'!$D$67),0) | ... AL18: =IF(AL9=1,AK18*(1-'Допущения'!$D$68)*'Допущения'!$D$66+AL16*(1-'Допущения'!$D$67),0)
A19: Новые платящие | B19: =SUM(C19:AL19) | C19: =IF(C9=1,C16*'Допущения'!$D$67+0*'Допущения'!$D$68,0) | D19: =IF(D9=1,D16*'Допущения'!$D$67+C18*'Допущения'!$D$68,0) | E19: =IF(E9=1,E16*'Допущения'!$D$67+D18*'Допущения'!$D$68,0) | F19: =IF(F9=1,F16*'Допущения'!$D$67+E18*'Допущения'!$D$68,0) | G19: =IF(G9=1,G16*'Допущения'!$D$67+F18*'Допущения'!$D$68,0) | H19: =IF(H9=1,H16*'Допущения'!$D$67+G18*'Допущения'!$D$68,0) | I19: =IF(I9=1,I16*'Допущения'!$D$67+H18*'Допущения'!$D$68,0) | J19: =IF(J9=1,J16*'Допущения'!$D$67+I18*'Допущения'!$D$68,0) | K19: =IF(K9=1,K16*'Допущения'!$D$67+J18*'Допущения'!$D$68,0) | ... AL19: =IF(AL9=1,AL16*'Допущения'!$D$67+AK18*'Допущения'!$D$68,0)
A20: Ушедшие платящие | B20: =SUM(C20:AL20) | C20: =0*'Допущения'!$D$69 | D20: =C21*'Допущения'!$D$69 | E20: =D21*'Допущения'!$D$69 | F20: =E21*'Допущения'!$D$69 | G20: =F21*'Допущения'!$D$69 | H20: =G21*'Допущения'!$D$69 | I20: =H21*'Допущения'!$D$69 | J20: =I21*'Допущения'!$D$69 | K20: =J21*'Допущения'!$D$69 | ... AL20: =AK21*'Допущения'!$D$69
A21: Платящие (на конец мес.) | C21: =0+C19-C20 | D21: =C21+D19-D20 | E21: =D21+E19-E20 | F21: =E21+F19-F20 | G21: =F21+G19-G20 | H21: =G21+H19-H20 | I21: =H21+I19-I20 | J21: =I21+J19-J20 | K21: =J21+K19-K20 | ... AL21: =AK21+AL19-AL20
A22: Активные пользователи всего | C22: =C17+C18+C21 | D22: =D17+D18+D21 | E22: =E17+E18+E21 | F22: =F17+F18+F21 | G22: =G17+G18+G21 | H22: =H17+H18+H21 | I22: =I17+I18+I21 | J22: =J17+J18+J21 | ... AL22: =AL17+AL18+AL21
A23: ВЫРУЧКА, $
A24: Оплаты подписок (брутто) | B24: =SUM(C24:AL24) | C24: =C21*'Себестоимость'!$D$12 | D24: =D21*'Себестоимость'!$D$12 | E24: =E21*'Себестоимость'!$D$12 | F24: =F21*'Себестоимость'!$D$12 | G24: =G21*'Себестоимость'!$D$12 | H24: =H21*'Себестоимость'!$D$12 | I24: =I21*'Себестоимость'!$D$12 | J24: =J21*'Себестоимость'!$D$12 | ... AL24: =AL21*'Себестоимость'!$D$12
A25: Комиссии магазинов/Paddle и НДС | B25: =SUM(C25:AL25) | C25: =C24-C26 | D25: =D24-D26 | E25: =E24-E26 | F25: =F24-F26 | G25: =G24-G26 | H25: =H24-H26 | I25: =I24-I26 | J25: =J24-J26 | ... AL25: =AL24-AL26
A26: Чистая выручка подписок | B26: =SUM(C26:AL26) | C26: =C21*'Себестоимость'!$D$13 | D26: =D21*'Себестоимость'!$D$13 | E26: =E21*'Себестоимость'!$D$13 | F26: =F21*'Себестоимость'!$D$13 | G26: =G21*'Себестоимость'!$D$13 | H26: =H21*'Себестоимость'!$D$13 | I26: =I21*'Себестоимость'!$D$13 | J26: =J21*'Себестоимость'!$D$13 | ... AL26: =AL21*'Себестоимость'!$D$13
A27: Донаты (чистые) | B27: =SUM(C27:AL27) | C27: =C17*'Допущения'!$D$75*'Допущения'!$D$76*(1-'Допущения'!$D$77) | D27: =D17*'Допущения'!$D$75*'Допущения'!$D$76*(1-'Допущения'!$D$77) | E27: =E17*'Допущения'!$D$75*'Допущения'!$D$76*(1-'Допущения'!$D$77) | F27: =F17*'Допущения'!$D$75*'Допущения'!$D$76*(1-'Допущения'!$D$77) | G27: =G17*'Допущения'!$D$75*'Допущения'!$D$76*(1-'Допущения'!$D$77) | H27: =H17*'Допущения'!$D$75*'Допущения'!$D$76*(1-'Допущения'!$D$77) | I27: =I17*'Допущения'!$D$75*'Допущения'!$D$76*(1-'Допущения'!$D$77) | J27: =J17*'Допущения'!$D$75*'Допущения'!$D$76*(1-'Допущения'!$D$77) | ... AL27: =AL17*'Допущения'!$D$75*'Допущения'!$D$76*(1-'Допущения'!$D$77)
A28: Итого чистая выручка | B28: =SUM(C28:AL28) | C28: =C26+C27 | D28: =D26+D27 | E28: =E26+E27 | F28: =F26+F27 | G28: =G26+G27 | H28: =H26+H27 | I28: =I26+I27 | J28: =J26+J27 | ... AL28: =AL26+AL27
A29: ПЕРЕМЕННЫЕ ЗАТРАТЫ, $
A30: LLM: платящие | B30: =SUM(C30:AL30) | C30: =C21*'Себестоимость'!$D$14 | D30: =D21*'Себестоимость'!$D$14 | E30: =E21*'Себестоимость'!$D$14 | F30: =F21*'Себестоимость'!$D$14 | G30: =G21*'Себестоимость'!$D$14 | H30: =H21*'Себестоимость'!$D$14 | I30: =I21*'Себестоимость'!$D$14 | J30: =J21*'Себестоимость'!$D$14 | ... AL30: =AL21*'Себестоимость'!$D$14
A31: LLM: free и прототип | B31: =SUM(C31:AL31) | C31: =C18*'Себестоимость'!$D$16+C17*'Допущения'!$D$74*'Себестоимость'!$D$7 | D31: =D18*'Себестоимость'!$D$16+D17*'Допущения'!$D$74*'Себестоимость'!$D$7 | E31: =E18*'Себестоимость'!$D$16+E17*'Допущения'!$D$74*'Себестоимость'!$D$7 | F31: =F18*'Себестоимость'!$D$16+F17*'Допущения'!$D$74*'Себестоимость'!$D$7 | G31: =G18*'Себестоимость'!$D$16+G17*'Допущения'!$D$74*'Себестоимость'!$D$7 | H31: =H18*'Себестоимость'!$D$16+H17*'Допущения'!$D$74*'Себестоимость'!$D$7 | I31: =I18*'Себестоимость'!$D$16+I17*'Допущения'!$D$74*'Себестоимость'!$D$7 | J31: =J18*'Себестоимость'!$D$16+J17*'Допущения'!$D$74*'Себестоимость'!$D$7 | ... AL31: =AL18*'Себестоимость'!$D$16+AL17*'Допущения'!$D$74*'Себестоимость'!$D$7
A32: Проверка возраста | B32: =SUM(C32:AL32) | C32: =C19*'Допущения'!$D$44*'Допущения'!$D$93 | D32: =D19*'Допущения'!$D$44*'Допущения'!$D$93 | E32: =E19*'Допущения'!$D$44*'Допущения'!$D$93 | F32: =F19*'Допущения'!$D$44*'Допущения'!$D$93 | G32: =G19*'Допущения'!$D$44*'Допущения'!$D$93 | H32: =H19*'Допущения'!$D$44*'Допущения'!$D$93 | I32: =I19*'Допущения'!$D$44*'Допущения'!$D$93 | J32: =J19*'Допущения'!$D$44*'Допущения'!$D$93 | ... AL32: =AL19*'Допущения'!$D$44*'Допущения'!$D$93
A33: Инфраструктура (на пользователя) | B33: =SUM(C33:AL33) | C33: =C22*'Допущения'!$D$86 | D33: =D22*'Допущения'!$D$86 | E33: =E22*'Допущения'!$D$86 | F33: =F22*'Допущения'!$D$86 | G33: =G22*'Допущения'!$D$86 | H33: =H22*'Допущения'!$D$86 | I33: =I22*'Допущения'!$D$86 | J33: =J22*'Допущения'!$D$86 | ... AL33: =AL22*'Допущения'!$D$86
A34: Итого переменные | B34: =SUM(C34:AL34) | C34: =SUM(C30:C33) | D34: =SUM(D30:D33) | E34: =SUM(E30:E33) | F34: =SUM(F30:F33) | G34: =SUM(G30:G33) | H34: =SUM(H30:H33) | I34: =SUM(I30:I33) | J34: =SUM(J30:J33) | ... AL34: =SUM(AL30:AL33)
A35: Валовая прибыль | B35: =SUM(C35:AL35) | C35: =C28-C34 | D35: =D28-D34 | E35: =E28-E34 | F35: =F28-F34 | G35: =G28-G34 | H35: =H28-H34 | I35: =I28-I34 | J35: =J28-J34 | ... AL35: =AL28-AL34
A36: Валовая маржа | B36: =IFERROR(B35/B28,0) | C36: =IFERROR(C35/C28,0) | D36: =IFERROR(D35/D28,0) | E36: =IFERROR(E35/E28,0) | F36: =IFERROR(F35/F28,0) | G36: =IFERROR(G35/G28,0) | H36: =IFERROR(H35/H28,0) | I36: =IFERROR(I35/I28,0) | ... AL36: =IFERROR(AL35/AL28,0)
A37: ПОСТОЯННЫЕ ЗАТРАТЫ И МАРКЕТИНГ, $
A38: Инфраструктура (база) | B38: =SUM(C38:AL38) | C38: ='Допущения'!$D$85 | D38: ='Допущения'!$D$85 | E38: ='Допущения'!$D$85 | F38: ='Допущения'!$D$85 | G38: ='Допущения'!$D$85 | H38: ='Допущения'!$D$85 | I38: ='Допущения'!$D$85 | J38: ='Допущения'!$D$85 | ... AL38: ='Допущения'!$D$85
A39: SaaS-инструменты | B39: =SUM(C39:AL39) | C39: ='Допущения'!$D$87 | D39: ='Допущения'!$D$87 | E39: ='Допущения'!$D$87 | F39: ='Допущения'!$D$87 | G39: ='Допущения'!$D$87 | H39: ='Допущения'!$D$87 | I39: ='Допущения'!$D$87 | J39: ='Допущения'!$D$87 | ... AL39: ='Допущения'!$D$87
A40: Бухгалтерия | B40: =SUM(C40:AL40) | C40: =IF(C6>='Допущения'!$D$10,'Допущения'!$D$88,0) | D40: =IF(D6>='Допущения'!$D$10,'Допущения'!$D$88,0) | E40: =IF(E6>='Допущения'!$D$10,'Допущения'!$D$88,0) | F40: =IF(F6>='Допущения'!$D$10,'Допущения'!$D$88,0) | G40: =IF(G6>='Допущения'!$D$10,'Допущения'!$D$88,0) | H40: =IF(H6>='Допущения'!$D$10,'Допущения'!$D$88,0) | I40: =IF(I6>='Допущения'!$D$10,'Допущения'!$D$88,0) | J40: =IF(J6>='Допущения'!$D$10,'Допущения'!$D$88,0) | ... AL40: =IF(AL6>='Допущения'!$D$10,'Допущения'!$D$88,0)
A41: Юр. сопровождение | B41: =SUM(C41:AL41) | C41: =IF(C9=1,'Допущения'!$D$89,0) | D41: =IF(D9=1,'Допущения'!$D$89,0) | E41: =IF(E9=1,'Допущения'!$D$89,0) | F41: =IF(F9=1,'Допущения'!$D$89,0) | G41: =IF(G9=1,'Допущения'!$D$89,0) | H41: =IF(H9=1,'Допущения'!$D$89,0) | I41: =IF(I9=1,'Допущения'!$D$89,0) | J41: =IF(J9=1,'Допущения'!$D$89,0) | ... AL41: =IF(AL9=1,'Допущения'!$D$89,0)
A42: Магазины приложений | B42: =SUM(C42:AL42) | C42: =IF(C6='Допущения'!$D$9-1,'Допущения'!$D$90+'Допущения'!$D$91,0)+IF(AND(C6>'Допущения'!$D$9-1,MOD(C6-('Допущения'!$D$9-1),12)=0),'Допущения'!$D$90,0) | D42: =IF(D6='Допущения'!$D$9-1,'Допущения'!$D$90+'Допущения'!$D$91,0)+IF(AND(D6>'Допущения'!$D$9-1,MOD(D6-('Допущения'!$D$9-1),12)=0),'Допущения'!$D$90,0) | E42: =IF(E6='Допущения'!$D$9-1,'Допущения'!$D$90+'Допущения'!$D$91,0)+IF(AND(E6>'Допущения'!$D$9-1,MOD(E6-('Допущения'!$D$9-1),12)=0),'Допущения'!$D$90,0) | F42: =IF(F6='Допущения'!$D$9-1,'Допущения'!$D$90+'Допущения'!$D$91,0)+IF(AND(F6>'Допущения'!$D$9-1,MOD(F6-('Допущения'!$D$9-1),12)=0),'Допущения'!$D$90,0) | G42: =IF(G6='Допущения'!$D$9-1,'Допущения'!$D$90+'Допущения'!$D$91,0)+IF(AND(G6>'Допущения'!$D$9-1,MOD(G6-('Допущения'!$D$9-1),12)=0),'Допущения'!$D$90,0) | H42: =IF(H6='Допущения'!$D$9-1,'Допущения'!$D$90+'Допущения'!$D$91,0)+IF(AND(H6>'Допущения'!$D$9-1,MOD(H6-('Допущения'!$D$9-1),12)=0),'Допущения'!$D$90,0) | I42: =IF(I6='Допущения'!$D$9-1,'Допущения'!$D$90+'Допущения'!$D$91,0)+IF(AND(I6>'Допущения'!$D$9-1,MOD(I6-('Допущения'!$D$9-1),12)=0),'Допущения'!$D$90,0) | J42: =IF(J6='Допущения'!$D$9-1,'Допущения'!$D$90+'Допущения'!$D$91,0)+IF(AND(J6>'Допущения'!$D$9-1,MOD(J6-('Допущения'!$D$9-1),12)=0),'Допущения'!$D$90,0) | ... AL42: =IF(AL6='Допущения'!$D$9-1,'Допущения'!$D$90+'Допущения'!$D$91,0)+IF(AND(AL6>'Допущения'!$D$9-1,MOD(AL6-('Допущения'!$D$9-1),12)=0),'Допущения'!$D$90,0)
A43: Разовые стартовые (лист «Старт») | B43: =SUM(C43:AL43) | C43: =SUMIF('Старт'!$C$5:$C$17,C6,'Старт'!$D$5:$D$17) | D43: =SUMIF('Старт'!$C$5:$C$17,D6,'Старт'!$D$5:$D$17) | E43: =SUMIF('Старт'!$C$5:$C$17,E6,'Старт'!$D$5:$D$17) | F43: =SUMIF('Старт'!$C$5:$C$17,F6,'Старт'!$D$5:$D$17) | G43: =SUMIF('Старт'!$C$5:$C$17,G6,'Старт'!$D$5:$D$17) | H43: =SUMIF('Старт'!$C$5:$C$17,H6,'Старт'!$D$5:$D$17) | I43: =SUMIF('Старт'!$C$5:$C$17,I6,'Старт'!$D$5:$D$17) | J43: =SUMIF('Старт'!$C$5:$C$17,J6,'Старт'!$D$5:$D$17) | ... AL43: =SUMIF('Старт'!$C$5:$C$17,AL6,'Старт'!$D$5:$D$17)
A44: Контент / SMM | B44: =SUM(C44:AL44) | C44: =IF(C6>'Допущения'!$D$9,'Допущения'!$D$92,0) | D44: =IF(D6>'Допущения'!$D$9,'Допущения'!$D$92,0) | E44: =IF(E6>'Допущения'!$D$9,'Допущения'!$D$92,0) | F44: =IF(F6>'Допущения'!$D$9,'Допущения'!$D$92,0) | G44: =IF(G6>'Допущения'!$D$9,'Допущения'!$D$92,0) | H44: =IF(H6>'Допущения'!$D$9,'Допущения'!$D$92,0) | I44: =IF(I6>'Допущения'!$D$9,'Допущения'!$D$92,0) | J44: =IF(J6>'Допущения'!$D$9,'Допущения'!$D$92,0) | ... AL44: =IF(AL6>'Допущения'!$D$9,'Допущения'!$D$92,0)
A45: Маркетинг | B45: =SUM(C45:AL45) | C45: =C11 | D45: =D11 | E45: =E11 | F45: =F11 | G45: =G11 | H45: =H11 | I45: =I11 | J45: =J11 | ... AL45: =AL11
A46: Выплаты основателям | B46: =SUM(C46:AL46) | C46: =IF(C6>='Допущения'!$D$94,MIN('Допущения'!$D$95,MAX(0,'Допущения'!$D$96*(0+0))),0) | D46: =IF(D6>='Допущения'!$D$94,MIN('Допущения'!$D$95,MAX(0,'Допущения'!$D$96*(C48+C46))),0) | E46: =IF(E6>='Допущения'!$D$94,MIN('Допущения'!$D$95,MAX(0,'Допущения'!$D$96*(D48+D46))),0) | F46: =IF(F6>='Допущения'!$D$94,MIN('Допущения'!$D$95,MAX(0,'Допущения'!$D$96*(E48+E46))),0) | G46: =IF(G6>='Допущения'!$D$94,MIN('Допущения'!$D$95,MAX(0,'Допущения'!$D$96*(F48+F46))),0) | H46: =IF(H6>='Допущения'!$D$94,MIN('Допущения'!$D$95,MAX(0,'Допущения'!$D$96*(G48+G46))),0) | I46: =IF(I6>='Допущения'!$D$94,MIN('Допущения'!$D$95,MAX(0,'Допущения'!$D$96*(H48+H46))),0) | J46: =IF(J6>='Допущения'!$D$94,MIN('Допущения'!$D$95,MAX(0,'Допущения'!$D$96*(I48+I46))),0) | K46: =IF(K6>='Допущения'!$D$94,MIN('Допущения'!$D$95,MAX(0,'Допущения'!$D$96*(J48+J46))),0) | ... AL46: =IF(AL6>='Допущения'!$D$94,MIN('Допущения'!$D$95,MAX(0,'Допущения'!$D$96*(AK48+AK46))),0)
A47: Итого постоянные + маркетинг | B47: =SUM(C47:AL47) | C47: =SUM(C38:C46) | D47: =SUM(D38:D46) | E47: =SUM(E38:E46) | F47: =SUM(F38:F46) | G47: =SUM(G38:G46) | H47: =SUM(H38:H46) | I47: =SUM(I38:I46) | J47: =SUM(J38:J46) | ... AL47: =SUM(AL38:AL46)
A48: EBITDA | B48: =SUM(C48:AL48) | C48: =C35-C47 | D48: =D35-D47 | E48: =E35-E47 | F48: =F35-F47 | G48: =G35-G47 | H48: =H35-H47 | I48: =I35-I47 | J48: =J35-J47 | ... AL48: =AL35-AL47
A49: Налог на прибыль | B49: =SUM(C49:AL49) | C49: =MAX(0,C48)*'Допущения'!$D$57 | D49: =MAX(0,D48)*'Допущения'!$D$57 | E49: =MAX(0,E48)*'Допущения'!$D$57 | F49: =MAX(0,F48)*'Допущения'!$D$57 | G49: =MAX(0,G48)*'Допущения'!$D$57 | H49: =MAX(0,H48)*'Допущения'!$D$57 | I49: =MAX(0,I48)*'Допущения'!$D$57 | J49: =MAX(0,J48)*'Допущения'!$D$57 | ... AL49: =MAX(0,AL48)*'Допущения'!$D$57
A50: Операционный денежный поток | B50: =SUM(C50:AL50) | C50: =C48-C49 | D50: =D48-D49 | E50: =E48-E49 | F50: =F48-F49 | G50: =G48-G49 | H50: =H48-H49 | I50: =I48-I49 | J50: =J48-J49 | ... AL50: =AL48-AL49
A51: Накопленный операционный поток | B51: =MIN(C51:AL51) | C51: =0+C50 | D51: =C51+D50 | E51: =D51+E50 | F51: =E51+F50 | G51: =F51+G50 | H51: =G51+H50 | I51: =H51+I50 | J51: =I51+J50 | K51: =J51+K50 | ... AL51: =AK51+AL50
A52: ВЛОЖЕНИЯ И КАССА, $
A53: Вложения партнёра (выбранный вариант) | B53: =SUM(C53:AL53) | C53: =(IF(C6=1,INDEX('Допущения'!$C$104:$C$106,'Допущения'!$D$103)*'Допущения'!$D$107,0)+IF(C6='Допущения'!$D$9,INDEX('Допущения'!$C$104:$C$106,'Допущения'!$D$103)*(1-'Допущения'!$D$107),0))/'Допущения'!$D$7 | D53: =(IF(D6=1,INDEX('Допущения'!$C$104:$C$106,'Допущения'!$D$103)*'Допущения'!$D$107,0)+IF(D6='Допущения'!$D$9,INDEX('Допущения'!$C$104:$C$106,'Допущения'!$D$103)*(1-'Допущения'!$D$107),0))/'Допущения'!$D$7 | E53: =(IF(E6=1,INDEX('Допущения'!$C$104:$C$106,'Допущения'!$D$103)*'Допущения'!$D$107,0)+IF(E6='Допущения'!$D$9,INDEX('Допущения'!$C$104:$C$106,'Допущения'!$D$103)*(1-'Допущения'!$D$107),0))/'Допущения'!$D$7 | F53: =(IF(F6=1,INDEX('Допущения'!$C$104:$C$106,'Допущения'!$D$103)*'Допущения'!$D$107,0)+IF(F6='Допущения'!$D$9,INDEX('Допущения'!$C$104:$C$106,'Допущения'!$D$103)*(1-'Допущения'!$D$107),0))/'Допущения'!$D$7 | G53: =(IF(G6=1,INDEX('Допущения'!$C$104:$C$106,'Допущения'!$D$103)*'Допущения'!$D$107,0)+IF(G6='Допущения'!$D$9,INDEX('Допущения'!$C$104:$C$106,'Допущения'!$D$103)*(1-'Допущения'!$D$107),0))/'Допущения'!$D$7 | H53: =(IF(H6=1,INDEX('Допущения'!$C$104:$C$106,'Допущения'!$D$103)*'Допущения'!$D$107,0)+IF(H6='Допущения'!$D$9,INDEX('Допущения'!$C$104:$C$106,'Допущения'!$D$103)*(1-'Допущения'!$D$107),0))/'Допущения'!$D$7 | I53: =(IF(I6=1,INDEX('Допущения'!$C$104:$C$106,'Допущения'!$D$103)*'Допущения'!$D$107,0)+IF(I6='Допущения'!$D$9,INDEX('Допущения'!$C$104:$C$106,'Допущения'!$D$103)*(1-'Допущения'!$D$107),0))/'Допущения'!$D$7 | J53: =(IF(J6=1,INDEX('Допущения'!$C$104:$C$106,'Допущения'!$D$103)*'Допущения'!$D$107,0)+IF(J6='Допущения'!$D$9,INDEX('Допущения'!$C$104:$C$106,'Допущения'!$D$103)*(1-'Допущения'!$D$107),0))/'Допущения'!$D$7 | ... AL53: =(IF(AL6=1,INDEX('Допущения'!$C$104:$C$106,'Допущения'!$D$103)*'Допущения'!$D$107,0)+IF(AL6='Допущения'!$D$9,INDEX('Допущения'!$C$104:$C$106,'Допущения'!$D$103)*(1-'Допущения'!$D$107),0))/'Допущения'!$D$7
A54: Мои вложения (выбранный вариант) | B54: =SUM(C54:AL54) | C54: =(IF(C6=1,MIN(INDEX('Допущения'!$D$104:$D$106,'Допущения'!$D$103),'Допущения'!$D$108),0)+IF(AND(C6>=2,C6<=4),MAX(0,INDEX('Допущения'!$D$104:$D$106,'Допущения'!$D$103)-'Допущения'!$D$108)/3,0))/'Допущения'!$D$7 | D54: =(IF(D6=1,MIN(INDEX('Допущения'!$D$104:$D$106,'Допущения'!$D$103),'Допущения'!$D$108),0)+IF(AND(D6>=2,D6<=4),MAX(0,INDEX('Допущения'!$D$104:$D$106,'Допущения'!$D$103)-'Допущения'!$D$108)/3,0))/'Допущения'!$D$7 | E54: =(IF(E6=1,MIN(INDEX('Допущения'!$D$104:$D$106,'Допущения'!$D$103),'Допущения'!$D$108),0)+IF(AND(E6>=2,E6<=4),MAX(0,INDEX('Допущения'!$D$104:$D$106,'Допущения'!$D$103)-'Допущения'!$D$108)/3,0))/'Допущения'!$D$7 | F54: =(IF(F6=1,MIN(INDEX('Допущения'!$D$104:$D$106,'Допущения'!$D$103),'Допущения'!$D$108),0)+IF(AND(F6>=2,F6<=4),MAX(0,INDEX('Допущения'!$D$104:$D$106,'Допущения'!$D$103)-'Допущения'!$D$108)/3,0))/'Допущения'!$D$7 | G54: =(IF(G6=1,MIN(INDEX('Допущения'!$D$104:$D$106,'Допущения'!$D$103),'Допущения'!$D$108),0)+IF(AND(G6>=2,G6<=4),MAX(0,INDEX('Допущения'!$D$104:$D$106,'Допущения'!$D$103)-'Допущения'!$D$108)/3,0))/'Допущения'!$D$7 | H54: =(IF(H6=1,MIN(INDEX('Допущения'!$D$104:$D$106,'Допущения'!$D$103),'Допущения'!$D$108),0)+IF(AND(H6>=2,H6<=4),MAX(0,INDEX('Допущения'!$D$104:$D$106,'Допущения'!$D$103)-'Допущения'!$D$108)/3,0))/'Допущения'!$D$7 | I54: =(IF(I6=1,MIN(INDEX('Допущения'!$D$104:$D$106,'Допущения'!$D$103),'Допущения'!$D$108),0)+IF(AND(I6>=2,I6<=4),MAX(0,INDEX('Допущения'!$D$104:$D$106,'Допущения'!$D$103)-'Допущения'!$D$108)/3,0))/'Допущения'!$D$7 | J54: =(IF(J6=1,MIN(INDEX('Допущения'!$D$104:$D$106,'Допущения'!$D$103),'Допущения'!$D$108),0)+IF(AND(J6>=2,J6<=4),MAX(0,INDEX('Допущения'!$D$104:$D$106,'Допущения'!$D$103)-'Допущения'!$D$108)/3,0))/'Допущения'!$D$7 | ... AL54: =(IF(AL6=1,MIN(INDEX('Допущения'!$D$104:$D$106,'Допущения'!$D$103),'Допущения'!$D$108),0)+IF(AND(AL6>=2,AL6<=4),MAX(0,INDEX('Допущения'!$D$104:$D$106,'Допущения'!$D$103)-'Допущения'!$D$108)/3,0))/'Допущения'!$D$7
A55: Касса на конец месяца | B55: =MIN(C55:AL55) | C55: =0+C50+C53+C54 | D55: =C55+D50+D53+D54 | E55: =D55+E50+E53+E54 | F55: =E55+F50+F53+F54 | G55: =F55+G50+G53+G54 | H55: =G55+H50+H53+H54 | I55: =H55+I50+I53+I54 | J55: =I55+J50+J53+J54 | K55: =J55+K50+K53+K54 | ... AL55: =AK55+AL50+AL53+AL54
A56: Касса при варианте 1 «Минимум» | B56: =MIN(C56:AL56) | C56: =C51+('Допущения'!$C$104*'Допущения'!$D$107+IF(C6>='Допущения'!$D$9,'Допущения'!$C$104*(1-'Допущения'!$D$107),0)+MIN('Допущения'!$D$104,'Допущения'!$D$108)+MAX(0,'Допущения'!$D$104-'Допущения'!$D$108)*MIN(MAX(C6-1,0),3)/3)/'Допущения'!$D$7 | D56: =D51+('Допущения'!$C$104*'Допущения'!$D$107+IF(D6>='Допущения'!$D$9,'Допущения'!$C$104*(1-'Допущения'!$D$107),0)+MIN('Допущения'!$D$104,'Допущения'!$D$108)+MAX(0,'Допущения'!$D$104-'Допущения'!$D$108)*MIN(MAX(D6-1,0),3)/3)/'Допущения'!$D$7 | E56: =E51+('Допущения'!$C$104*'Допущения'!$D$107+IF(E6>='Допущения'!$D$9,'Допущения'!$C$104*(1-'Допущения'!$D$107),0)+MIN('Допущения'!$D$104,'Допущения'!$D$108)+MAX(0,'Допущения'!$D$104-'Допущения'!$D$108)*MIN(MAX(E6-1,0),3)/3)/'Допущения'!$D$7 | F56: =F51+('Допущения'!$C$104*'Допущения'!$D$107+IF(F6>='Допущения'!$D$9,'Допущения'!$C$104*(1-'Допущения'!$D$107),0)+MIN('Допущения'!$D$104,'Допущения'!$D$108)+MAX(0,'Допущения'!$D$104-'Допущения'!$D$108)*MIN(MAX(F6-1,0),3)/3)/'Допущения'!$D$7 | G56: =G51+('Допущения'!$C$104*'Допущения'!$D$107+IF(G6>='Допущения'!$D$9,'Допущения'!$C$104*(1-'Допущения'!$D$107),0)+MIN('Допущения'!$D$104,'Допущения'!$D$108)+MAX(0,'Допущения'!$D$104-'Допущения'!$D$108)*MIN(MAX(G6-1,0),3)/3)/'Допущения'!$D$7 | H56: =H51+('Допущения'!$C$104*'Допущения'!$D$107+IF(H6>='Допущения'!$D$9,'Допущения'!$C$104*(1-'Допущения'!$D$107),0)+MIN('Допущения'!$D$104,'Допущения'!$D$108)+MAX(0,'Допущения'!$D$104-'Допущения'!$D$108)*MIN(MAX(H6-1,0),3)/3)/'Допущения'!$D$7 | I56: =I51+('Допущения'!$C$104*'Допущения'!$D$107+IF(I6>='Допущения'!$D$9,'Допущения'!$C$104*(1-'Допущения'!$D$107),0)+MIN('Допущения'!$D$104,'Допущения'!$D$108)+MAX(0,'Допущения'!$D$104-'Допущения'!$D$108)*MIN(MAX(I6-1,0),3)/3)/'Допущения'!$D$7 | J56: =J51+('Допущения'!$C$104*'Допущения'!$D$107+IF(J6>='Допущения'!$D$9,'Допущения'!$C$104*(1-'Допущения'!$D$107),0)+MIN('Допущения'!$D$104,'Допущения'!$D$108)+MAX(0,'Допущения'!$D$104-'Допущения'!$D$108)*MIN(MAX(J6-1,0),3)/3)/'Допущения'!$D$7 | ... AL56: =AL51+('Допущения'!$C$104*'Допущения'!$D$107+IF(AL6>='Допущения'!$D$9,'Допущения'!$C$104*(1-'Допущения'!$D$107),0)+MIN('Допущения'!$D$104,'Допущения'!$D$108)+MAX(0,'Допущения'!$D$104-'Допущения'!$D$108)*MIN(MAX(AL6-1,0),3)/3)/'Допущения'!$D$7
A57: Касса при варианте 2 «Средний» | B57: =MIN(C57:AL57) | C57: =C51+('Допущения'!$C$105*'Допущения'!$D$107+IF(C6>='Допущения'!$D$9,'Допущения'!$C$105*(1-'Допущения'!$D$107),0)+MIN('Допущения'!$D$105,'Допущения'!$D$108)+MAX(0,'Допущения'!$D$105-'Допущения'!$D$108)*MIN(MAX(C6-1,0),3)/3)/'Допущения'!$D$7 | D57: =D51+('Допущения'!$C$105*'Допущения'!$D$107+IF(D6>='Допущения'!$D$9,'Допущения'!$C$105*(1-'Допущения'!$D$107),0)+MIN('Допущения'!$D$105,'Допущения'!$D$108)+MAX(0,'Допущения'!$D$105-'Допущения'!$D$108)*MIN(MAX(D6-1,0),3)/3)/'Допущения'!$D$7 | E57: =E51+('Допущения'!$C$105*'Допущения'!$D$107+IF(E6>='Допущения'!$D$9,'Допущения'!$C$105*(1-'Допущения'!$D$107),0)+MIN('Допущения'!$D$105,'Допущения'!$D$108)+MAX(0,'Допущения'!$D$105-'Допущения'!$D$108)*MIN(MAX(E6-1,0),3)/3)/'Допущения'!$D$7 | F57: =F51+('Допущения'!$C$105*'Допущения'!$D$107+IF(F6>='Допущения'!$D$9,'Допущения'!$C$105*(1-'Допущения'!$D$107),0)+MIN('Допущения'!$D$105,'Допущения'!$D$108)+MAX(0,'Допущения'!$D$105-'Допущения'!$D$108)*MIN(MAX(F6-1,0),3)/3)/'Допущения'!$D$7 | G57: =G51+('Допущения'!$C$105*'Допущения'!$D$107+IF(G6>='Допущения'!$D$9,'Допущения'!$C$105*(1-'Допущения'!$D$107),0)+MIN('Допущения'!$D$105,'Допущения'!$D$108)+MAX(0,'Допущения'!$D$105-'Допущения'!$D$108)*MIN(MAX(G6-1,0),3)/3)/'Допущения'!$D$7 | H57: =H51+('Допущения'!$C$105*'Допущения'!$D$107+IF(H6>='Допущения'!$D$9,'Допущения'!$C$105*(1-'Допущения'!$D$107),0)+MIN('Допущения'!$D$105,'Допущения'!$D$108)+MAX(0,'Допущения'!$D$105-'Допущения'!$D$108)*MIN(MAX(H6-1,0),3)/3)/'Допущения'!$D$7 | I57: =I51+('Допущения'!$C$105*'Допущения'!$D$107+IF(I6>='Допущения'!$D$9,'Допущения'!$C$105*(1-'Допущения'!$D$107),0)+MIN('Допущения'!$D$105,'Допущения'!$D$108)+MAX(0,'Допущения'!$D$105-'Допущения'!$D$108)*MIN(MAX(I6-1,0),3)/3)/'Допущения'!$D$7 | J57: =J51+('Допущения'!$C$105*'Допущения'!$D$107+IF(J6>='Допущения'!$D$9,'Допущения'!$C$105*(1-'Допущения'!$D$107),0)+MIN('Допущения'!$D$105,'Допущения'!$D$108)+MAX(0,'Допущения'!$D$105-'Допущения'!$D$108)*MIN(MAX(J6-1,0),3)/3)/'Допущения'!$D$7 | ... AL57: =AL51+('Допущения'!$C$105*'Допущения'!$D$107+IF(AL6>='Допущения'!$D$9,'Допущения'!$C$105*(1-'Допущения'!$D$107),0)+MIN('Допущения'!$D$105,'Допущения'!$D$108)+MAX(0,'Допущения'!$D$105-'Допущения'!$D$108)*MIN(MAX(AL6-1,0),3)/3)/'Допущения'!$D$7
A58: Касса при варианте 3 «Максимум» | B58: =MIN(C58:AL58) | C58: =C51+('Допущения'!$C$106*'Допущения'!$D$107+IF(C6>='Допущения'!$D$9,'Допущения'!$C$106*(1-'Допущения'!$D$107),0)+MIN('Допущения'!$D$106,'Допущения'!$D$108)+MAX(0,'Допущения'!$D$106-'Допущения'!$D$108)*MIN(MAX(C6-1,0),3)/3)/'Допущения'!$D$7 | D58: =D51+('Допущения'!$C$106*'Допущения'!$D$107+IF(D6>='Допущения'!$D$9,'Допущения'!$C$106*(1-'Допущения'!$D$107),0)+MIN('Допущения'!$D$106,'Допущения'!$D$108)+MAX(0,'Допущения'!$D$106-'Допущения'!$D$108)*MIN(MAX(D6-1,0),3)/3)/'Допущения'!$D$7 | E58: =E51+('Допущения'!$C$106*'Допущения'!$D$107+IF(E6>='Допущения'!$D$9,'Допущения'!$C$106*(1-'Допущения'!$D$107),0)+MIN('Допущения'!$D$106,'Допущения'!$D$108)+MAX(0,'Допущения'!$D$106-'Допущения'!$D$108)*MIN(MAX(E6-1,0),3)/3)/'Допущения'!$D$7 | F58: =F51+('Допущения'!$C$106*'Допущения'!$D$107+IF(F6>='Допущения'!$D$9,'Допущения'!$C$106*(1-'Допущения'!$D$107),0)+MIN('Допущения'!$D$106,'Допущения'!$D$108)+MAX(0,'Допущения'!$D$106-'Допущения'!$D$108)*MIN(MAX(F6-1,0),3)/3)/'Допущения'!$D$7 | G58: =G51+('Допущения'!$C$106*'Допущения'!$D$107+IF(G6>='Допущения'!$D$9,'Допущения'!$C$106*(1-'Допущения'!$D$107),0)+MIN('Допущения'!$D$106,'Допущения'!$D$108)+MAX(0,'Допущения'!$D$106-'Допущения'!$D$108)*MIN(MAX(G6-1,0),3)/3)/'Допущения'!$D$7 | H58: =H51+('Допущения'!$C$106*'Допущения'!$D$107+IF(H6>='Допущения'!$D$9,'Допущения'!$C$106*(1-'Допущения'!$D$107),0)+MIN('Допущения'!$D$106,'Допущения'!$D$108)+MAX(0,'Допущения'!$D$106-'Допущения'!$D$108)*MIN(MAX(H6-1,0),3)/3)/'Допущения'!$D$7 | I58: =I51+('Допущения'!$C$106*'Допущения'!$D$107+IF(I6>='Допущения'!$D$9,'Допущения'!$C$106*(1-'Допущения'!$D$107),0)+MIN('Допущения'!$D$106,'Допущения'!$D$108)+MAX(0,'Допущения'!$D$106-'Допущения'!$D$108)*MIN(MAX(I6-1,0),3)/3)/'Допущения'!$D$7 | J58: =J51+('Допущения'!$C$106*'Допущения'!$D$107+IF(J6>='Допущения'!$D$9,'Допущения'!$C$106*(1-'Допущения'!$D$107),0)+MIN('Допущения'!$D$106,'Допущения'!$D$108)+MAX(0,'Допущения'!$D$106-'Допущения'!$D$108)*MIN(MAX(J6-1,0),3)/3)/'Допущения'!$D$7 | ... AL58: =AL51+('Допущения'!$C$106*'Допущения'!$D$107+IF(AL6>='Допущения'!$D$9,'Допущения'!$C$106*(1-'Допущения'!$D$107),0)+MIN('Допущения'!$D$106,'Допущения'!$D$108)+MAX(0,'Допущения'!$D$106-'Допущения'!$D$108)*MIN(MAX(AL6-1,0),3)/3)/'Допущения'!$D$7
A59: МЕТРИКИ
A60: MRR (брутто), $ | C60: =C24 | D60: =D24 | E60: =E24 | F60: =F24 | G60: =G24 | H60: =H24 | I60: =I24 | J60: =J24 | ... AL60: =AL24
A61: CAC на нового платящего, $ | B61: =IFERROR(B11/B19,0) | C61: =IFERROR(IF(C9=1,C11/C19,0),0) | D61: =IFERROR(IF(D9=1,D11/D19,0),0) | E61: =IFERROR(IF(E9=1,E11/E19,0),0) | F61: =IFERROR(IF(F9=1,F11/F19,0),0) | G61: =IFERROR(IF(G9=1,G11/G19,0),0) | H61: =IFERROR(IF(H9=1,H11/H19,0),0) | I61: =IFERROR(IF(I9=1,I11/I19,0),0) | J61: =IFERROR(IF(J9=1,J11/J19,0),0) | ... AL61: =IFERROR(IF(AL9=1,AL11/AL19,0),0)
A62: Флаг: EBITDA ≥ 0 после выхода | C62: =IF(AND(C9=1,C48>=0),1,0) | D62: =IF(AND(D9=1,D48>=0),1,0) | E62: =IF(AND(E9=1,E48>=0),1,0) | F62: =IF(AND(F9=1,F48>=0),1,0) | G62: =IF(AND(G9=1,G48>=0),1,0) | H62: =IF(AND(H9=1,H48>=0),1,0) | I62: =IF(AND(I9=1,I48>=0),1,0) | J62: =IF(AND(J9=1,J48>=0),1,0) | ... AL62: =IF(AND(AL9=1,AL48>=0),1,0)
A63: Флаг: EBITDA ≥ 0 в этом и всех следующих месяцах | C63: =IF(AND(C9=1,MIN(C48:$AL$48)>=0),1,0) | D63: =IF(AND(D9=1,MIN(D48:$AL$48)>=0),1,0) | E63: =IF(AND(E9=1,MIN(E48:$AL$48)>=0),1,0) | F63: =IF(AND(F9=1,MIN(F48:$AL$48)>=0),1,0) | G63: =IF(AND(G9=1,MIN(G48:$AL$48)>=0),1,0) | H63: =IF(AND(H9=1,MIN(H48:$AL$48)>=0),1,0) | I63: =IF(AND(I9=1,MIN(I48:$AL$48)>=0),1,0) | J63: =IF(AND(J9=1,MIN(J48:$AL$48)>=0),1,0) | ... AL63: =IF(AND(AL9=1,MIN(AL48:$AL$48)>=0),1,0)
A64: Флаг: накопленный поток ≥ 0 | C64: =IF(C51>=0,1,0) | D64: =IF(D51>=0,1,0) | E64: =IF(E51>=0,1,0) | F64: =IF(F51>=0,1,0) | G64: =IF(G51>=0,1,0) | H64: =IF(H51>=0,1,0) | I64: =IF(I51>=0,1,0) | J64: =IF(J51>=0,1,0) | ... AL64: =IF(AL51>=0,1,0)
A65: Поток для IRR (с терминальной стоимостью) | C65: =C50+0 | D65: =D50+0 | E65: =E50+0 | F65: =F50+0 | G65: =G50+0 | H65: =H50+0 | I65: =I50+0 | J65: =J50+0 | ... AK65: =AK50+0 | AL65: =AL50+AL60*12*'Допущения'!$D$100
A67: СВОДКА
A68: Первый месяц с EBITDA ≥ 0 (№) | B68: =IFERROR(MATCH(1,$C$62:$AL$62,0),"не достигнут")
A69: Устойчивая безубыточность: EBITDA ≥ 0 и дальше (№ мес.) | B69: =IFERROR(MATCH(1,$C$63:$AL$63,0),"не достигнута")
A70: Устойчивая безубыточность (дата) | B70: =IFERROR(INDEX($C$7:$AL$7,MATCH(1,$C$63:$AL$63,0)),"—")
A71: Окупаемость: накопленный поток ≥ 0 (№ мес.) | B71: =IFERROR(MATCH(1,$C$64:$AL$64,0),"> 36 мес.")
A72: Пиковая потребность в финансировании, $ | B72: =-MIN($C$51:$AL$51)
A73: То же, ₽ | B73: =-MIN($C$51:$AL$51)*'Допущения'!$D$7
A74: Чистая выручка, год 1, $ | B74: =SUMIF($C$8:$AL$8,1,$C$28:$AL$28)
A75: Чистая выручка, год 2, $ | B75: =SUMIF($C$8:$AL$8,2,$C$28:$AL$28)
A76: Чистая выручка, год 3, $ | B76: =SUMIF($C$8:$AL$8,3,$C$28:$AL$28)
A77: EBITDA, год 1, $ | B77: =SUMIF($C$8:$AL$8,1,$C$48:$AL$48)
A78: EBITDA, год 2, $ | B78: =SUMIF($C$8:$AL$8,2,$C$48:$AL$48)
A79: EBITDA, год 3, $ | B79: =SUMIF($C$8:$AL$8,3,$C$48:$AL$48)
A80: Платящие, мес. 12 | B80: =$N$21
A81: Платящие, мес. 24 | B81: =$Z$21
A82: Платящие, мес. 36 | B82: =$AL$21
A83: Активные, мес. 12 | B83: =$N$22
A84: Активные, мес. 36 | B84: =$AL$22
A85: MRR, мес. 12, $ | B85: =$N$60
A86: MRR, мес. 24, $ | B86: =$Z$60
A87: MRR, мес. 36, $ | B87: =$AL$60
A88: ARR, мес. 36, $ | B88: =$AL$60*12
A89: CAC средний (маркетинг / новые платящие после выхода), $ | B89: =IFERROR(SUMIF($C$9:$AL$9,1,$C$11:$AL$11)/SUM($C$19:$AL$19),0)
A90: LTV платящего (чистая выручка × маржа / отток), $ | B90: ='Себестоимость'!$D$13*'Себестоимость'!$D$15/'Допущения'!$D$69
A91: LTV / CAC | B91: =IFERROR(B90/B89,0)
A92: Валовая маржа за 36 мес. | B92: =B36
A93: NPV операционного потока + терминальная стоимость, $ | B93: =NPV((1+'Допущения'!$D$99)^(1/12)-1,$C$65:$AL$65)
A94: IRR годовая | B94: =IFERROR((1+IRR($C$65:$AL$65,0.05))^12-1,"н/д")
A95: Мин. касса при выбранном варианте вложений, $ | B95: =B55
A96: Мин. касса: вариант 1, $ | B96: =B56
A97: Мин. касса: вариант 2, $ | B97: =B57
A98: Мин. касса: вариант 3, $ | B98: =B58
A99: Расходы мес. 1 … выход включительно, $ | B99: =SUMIF($C$6:$AL$6,"<="&'Допущения'!$D$9,$C$34:$AL$34)+SUMIF($C$6:$AL$6,"<="&'Допущения'!$D$9,$C$47:$AL$47)

Sheet Модель_П
A1: Финмодель на 36 месяцев — сценарий: Пессимистичный
A2: Все значения считаются формулами из листов «Допущения», «Себестоимость», «Старт».
B5: Итого / знач.
A6: Месяц № | C6: 1 | D6: 2 | E6: 3 | F6: 4 | G6: 5 | H6: 6 | I6: 7 | J6: 8 | K6: 9 | L6: 10 | M6: 11 | N6: 12 | O6: 13 | P6: 14 | Q6: 15 | R6: 16 | S6: 17 | T6: 18 | U6: 19 | V6: 20 | W6: 21 | X6: 22 | Y6: 23 | Z6: 24 | AA6: 25 | AB6: 26 | AC6: 27 | AD6: 28 | AE6: 29 | AF6: 30 | AG6: 31 | AH6: 32 | AI6: 33 | AJ6: 34 | AK6: 35 | AL6: 36
A7: Месяц | C7: ноя 2026 | D7: дек 2026 | E7: янв 2027 | F7: фев 2027 | G7: мар 2027 | H7: апр 2027 | I7: май 2027 | J7: июн 2027 | K7: июл 2027 | L7: авг 2027 | M7: сен 2027 | N7: окт 2027 | O7: ноя 2027 | P7: дек 2027 | Q7: янв 2028 | R7: фев 2028 | S7: мар 2028 | T7: апр 2028 | U7: май 2028 | V7: июн 2028 | W7: июл 2028 | X7: авг 2028 | Y7: сен 2028 | Z7: окт 2028 | AA7: ноя 2028 | AB7: дек 2028 | AC7: янв 2029 | AD7: фев 2029 | AE7: мар 2029 | AF7: апр 2029 | AG7: май 2029 | AH7: июн 2029 | AI7: июл 2029 | AJ7: авг 2029 | AK7: сен 2029 | AL7: окт 2029
A8: Год проекта | C8: 1 | D8: 1 | E8: 1 | F8: 1 | G8: 1 | H8: 1 | I8: 1 | J8: 1 | K8: 1 | L8: 1 | M8: 1 | N8: 1 | O8: 2 | P8: 2 | Q8: 2 | R8: 2 | S8: 2 | T8: 2 | U8: 2 | V8: 2 | W8: 2 | X8: 2 | Y8: 2 | Z8: 2 | AA8: 3 | AB8: 3 | AC8: 3 | AD8: 3 | AE8: 3 | AF8: 3 | AG8: 3 | AH8: 3 | AI8: 3 | AJ8: 3 | AK8: 3 | AL8: 3
A9: Рынок (1 = MVP вышел) | C9: =IF(C6>='Допущения'!$C$9,1,0) | D9: =IF(D6>='Допущения'!$C$9,1,0) | E9: =IF(E6>='Допущения'!$C$9,1,0) | F9: =IF(F6>='Допущения'!$C$9,1,0) | G9: =IF(G6>='Допущения'!$C$9,1,0) | H9: =IF(H6>='Допущения'!$C$9,1,0) | I9: =IF(I6>='Допущения'!$C$9,1,0) | J9: =IF(J6>='Допущения'!$C$9,1,0) | ... AL9: =IF(AL6>='Допущения'!$C$9,1,0)
A10: ВОРОНКА
A11: Маркетинг, $ | B11: =SUM(C11:AL11) | C11: =IF(C9=1,MAX('Допущения'!$C$83,'Допущения'!$C$84*0)+IF(C6='Допущения'!$C$9,'Допущения'!$C$82,0),'Допущения'!$C$81) | D11: =IF(D9=1,MAX('Допущения'!$C$83,'Допущения'!$C$84*C28)+IF(D6='Допущения'!$C$9,'Допущения'!$C$82,0),'Допущения'!$C$81) | E11: =IF(E9=1,MAX('Допущения'!$C$83,'Допущения'!$C$84*D28)+IF(E6='Допущения'!$C$9,'Допущения'!$C$82,0),'Допущения'!$C$81) | F11: =IF(F9=1,MAX('Допущения'!$C$83,'Допущения'!$C$84*E28)+IF(F6='Допущения'!$C$9,'Допущения'!$C$82,0),'Допущения'!$C$81) | G11: =IF(G9=1,MAX('Допущения'!$C$83,'Допущения'!$C$84*F28)+IF(G6='Допущения'!$C$9,'Допущения'!$C$82,0),'Допущения'!$C$81) | H11: =IF(H9=1,MAX('Допущения'!$C$83,'Допущения'!$C$84*G28)+IF(H6='Допущения'!$C$9,'Допущения'!$C$82,0),'Допущения'!$C$81) | I11: =IF(I9=1,MAX('Допущения'!$C$83,'Допущения'!$C$84*H28)+IF(I6='Допущения'!$C$9,'Допущения'!$C$82,0),'Допущения'!$C$81) | J11: =IF(J9=1,MAX('Допущения'!$C$83,'Допущения'!$C$84*I28)+IF(J6='Допущения'!$C$9,'Допущения'!$C$82,0),'Допущения'!$C$81) | K11: =IF(K9=1,MAX('Допущения'!$C$83,'Допущения'!$C$84*J28)+IF(K6='Допущения'!$C$9,'Допущения'!$C$82,0),'Допущения'!$C$81) | ... AL11: =IF(AL9=1,MAX('Допущения'!$C$83,'Допущения'!$C$84*AK28)+IF(AL6='Допущения'!$C$9,'Допущения'!$C$82,0),'Допущения'!$C$81)
A12: Платные установки | B12: =SUM(C12:AL12) | C12: =IF(C9=1,C11/'Допущения'!$C$60,0) | D12: =IF(D9=1,D11/'Допущения'!$C$60,0) | E12: =IF(E9=1,E11/'Допущения'!$C$60,0) | F12: =IF(F9=1,F11/'Допущения'!$C$60,0) | G12: =IF(G9=1,G11/'Допущения'!$C$60,0) | H12: =IF(H9=1,H11/'Допущения'!$C$60,0) | I12: =IF(I9=1,I11/'Допущения'!$C$60,0) | J12: =IF(J9=1,J11/'Допущения'!$C$60,0) | ... AL12: =IF(AL9=1,AL11/'Допущения'!$C$60,0)
A13: Органические установки | B13: =SUM(C13:AL13) | C13: =IF(C9=1,MIN('Допущения'!$C$63,'Допущения'!$C$61*(1+'Допущения'!$C$62)^(C6-'Допущения'!$C$9)),0) | D13: =IF(D9=1,MIN('Допущения'!$C$63,'Допущения'!$C$61*(1+'Допущения'!$C$62)^(D6-'Допущения'!$C$9)),0) | E13: =IF(E9=1,MIN('Допущения'!$C$63,'Допущения'!$C$61*(1+'Допущения'!$C$62)^(E6-'Допущения'!$C$9)),0) | F13: =IF(F9=1,MIN('Допущения'!$C$63,'Допущения'!$C$61*(1+'Допущения'!$C$62)^(F6-'Допущения'!$C$9)),0) | G13: =IF(G9=1,MIN('Допущения'!$C$63,'Допущения'!$C$61*(1+'Допущения'!$C$62)^(G6-'Допущения'!$C$9)),0) | H13: =IF(H9=1,MIN('Допущения'!$C$63,'Допущения'!$C$61*(1+'Допущения'!$C$62)^(H6-'Допущения'!$C$9)),0) | I13: =IF(I9=1,MIN('Допущения'!$C$63,'Допущения'!$C$61*(1+'Допущения'!$C$62)^(I6-'Допущения'!$C$9)),0) | J13: =IF(J9=1,MIN('Допущения'!$C$63,'Допущения'!$C$61*(1+'Допущения'!$C$62)^(J6-'Допущения'!$C$9)),0) | ... AL13: =IF(AL9=1,MIN('Допущения'!$C$63,'Допущения'!$C$61*(1+'Допущения'!$C$62)^(AL6-'Допущения'!$C$9)),0)
A14: Вирусные установки | B14: =SUM(C14:AL14) | C14: =(C12+C13)*'Допущения'!$C$64 | D14: =(D12+D13)*'Допущения'!$C$64 | E14: =(E12+E13)*'Допущения'!$C$64 | F14: =(F12+F13)*'Допущения'!$C$64 | G14: =(G12+G13)*'Допущения'!$C$64 | H14: =(H12+H13)*'Допущения'!$C$64 | I14: =(I12+I13)*'Допущения'!$C$64 | J14: =(J12+J13)*'Допущения'!$C$64 | ... AL14: =(AL12+AL13)*'Допущения'!$C$64
A15: Всего установок | B15: =SUM(C15:AL15) | C15: =C12+C13+C14 | D15: =D12+D13+D14 | E15: =E12+E13+E14 | F15: =F12+F13+F14 | G15: =G12+G13+G14 | H15: =H12+H13+H14 | I15: =I12+I13+I14 | J15: =J12+J13+J14 | ... AL15: =AL12+AL13+AL14
A16: Новые активированные | B16: =SUM(C16:AL16) | C16: =C15*'Допущения'!$C$65+IF(C6='Допущения'!$C$9,0*'Допущения'!$C$78,0) | D16: =D15*'Допущения'!$C$65+IF(D6='Допущения'!$C$9,C17*'Допущения'!$C$78,0) | E16: =E15*'Допущения'!$C$65+IF(E6='Допущения'!$C$9,D17*'Допущения'!$C$78,0) | F16: =F15*'Допущения'!$C$65+IF(F6='Допущения'!$C$9,E17*'Допущения'!$C$78,0) | G16: =G15*'Допущения'!$C$65+IF(G6='Допущения'!$C$9,F17*'Допущения'!$C$78,0) | H16: =H15*'Допущения'!$C$65+IF(H6='Допущения'!$C$9,G17*'Допущения'!$C$78,0) | I16: =I15*'Допущения'!$C$65+IF(I6='Допущения'!$C$9,H17*'Допущения'!$C$78,0) | J16: =J15*'Допущения'!$C$65+IF(J6='Допущения'!$C$9,I17*'Допущения'!$C$78,0) | K16: =K15*'Допущения'!$C$65+IF(K6='Допущения'!$C$9,J17*'Допущения'!$C$78,0) | ... AL16: =AL15*'Допущения'!$C$65+IF(AL6='Допущения'!$C$9,AK17*'Допущения'!$C$78,0)
A17: Игроки прототипа (до выхода) | C17: =IF(C9=1,0,'Допущения'!$C$72*(1+'Допущения'!$C$73)^(C6-1)) | D17: =IF(D9=1,0,'Допущения'!$C$72*(1+'Допущения'!$C$73)^(D6-1)) | E17: =IF(E9=1,0,'Допущения'!$C$72*(1+'Допущения'!$C$73)^(E6-1)) | F17: =IF(F9=1,0,'Допущения'!$C$72*(1+'Допущения'!$C$73)^(F6-1)) | G17: =IF(G9=1,0,'Допущения'!$C$72*(1+'Допущения'!$C$73)^(G6-1)) | H17: =IF(H9=1,0,'Допущения'!$C$72*(1+'Допущения'!$C$73)^(H6-1)) | I17: =IF(I9=1,0,'Допущения'!$C$72*(1+'Допущения'!$C$73)^(I6-1)) | J17: =IF(J9=1,0,'Допущения'!$C$72*(1+'Допущения'!$C$73)^(J6-1)) | ... AL17: =IF(AL9=1,0,'Допущения'!$C$72*(1+'Допущения'!$C$73)^(AL6-1))
A18: Активные free (на конец мес.) | C18: =IF(C9=1,0*(1-'Допущения'!$C$68)*'Допущения'!$C$66+C16*(1-'Допущения'!$C$67),0) | D18: =IF(D9=1,C18*(1-'Допущения'!$C$68)*'Допущения'!$C$66+D16*(1-'Допущения'!$C$67),0) | E18: =IF(E9=1,D18*(1-'Допущения'!$C$68)*'Допущения'!$C$66+E16*(1-'Допущения'!$C$67),0) | F18: =IF(F9=1,E18*(1-'Допущения'!$C$68)*'Допущения'!$C$66+F16*(1-'Допущения'!$C$67),0) | G18: =IF(G9=1,F18*(1-'Допущения'!$C$68)*'Допущения'!$C$66+G16*(1-'Допущения'!$C$67),0) | H18: =IF(H9=1,G18*(1-'Допущения'!$C$68)*'Допущения'!$C$66+H16*(1-'Допущения'!$C$67),0) | I18: =IF(I9=1,H18*(1-'Допущения'!$C$68)*'Допущения'!$C$66+I16*(1-'Допущения'!$C$67),0) | J18: =IF(J9=1,I18*(1-'Допущения'!$C$68)*'Допущения'!$C$66+J16*(1-'Допущения'!$C$67),0) | K18: =IF(K9=1,J18*(1-'Допущения'!$C$68)*'Допущения'!$C$66+K16*(1-'Допущения'!$C$67),0) | ... AL18: =IF(AL9=1,AK18*(1-'Допущения'!$C$68)*'Допущения'!$C$66+AL16*(1-'Допущения'!$C$67),0)
A19: Новые платящие | B19: =SUM(C19:AL19) | C19: =IF(C9=1,C16*'Допущения'!$C$67+0*'Допущения'!$C$68,0) | D19: =IF(D9=1,D16*'Допущения'!$C$67+C18*'Допущения'!$C$68,0) | E19: =IF(E9=1,E16*'Допущения'!$C$67+D18*'Допущения'!$C$68,0) | F19: =IF(F9=1,F16*'Допущения'!$C$67+E18*'Допущения'!$C$68,0) | G19: =IF(G9=1,G16*'Допущения'!$C$67+F18*'Допущения'!$C$68,0) | H19: =IF(H9=1,H16*'Допущения'!$C$67+G18*'Допущения'!$C$68,0) | I19: =IF(I9=1,I16*'Допущения'!$C$67+H18*'Допущения'!$C$68,0) | J19: =IF(J9=1,J16*'Допущения'!$C$67+I18*'Допущения'!$C$68,0) | K19: =IF(K9=1,K16*'Допущения'!$C$67+J18*'Допущения'!$C$68,0) | ... AL19: =IF(AL9=1,AL16*'Допущения'!$C$67+AK18*'Допущения'!$C$68,0)
A20: Ушедшие платящие | B20: =SUM(C20:AL20) | C20: =0*'Допущения'!$C$69 | D20: =C21*'Допущения'!$C$69 | E20: =D21*'Допущения'!$C$69 | F20: =E21*'Допущения'!$C$69 | G20: =F21*'Допущения'!$C$69 | H20: =G21*'Допущения'!$C$69 | I20: =H21*'Допущения'!$C$69 | J20: =I21*'Допущения'!$C$69 | K20: =J21*'Допущения'!$C$69 | ... AL20: =AK21*'Допущения'!$C$69
A21: Платящие (на конец мес.) | C21: =0+C19-C20 | D21: =C21+D19-D20 | E21: =D21+E19-E20 | F21: =E21+F19-F20 | G21: =F21+G19-G20 | H21: =G21+H19-H20 | I21: =H21+I19-I20 | J21: =I21+J19-J20 | K21: =J21+K19-K20 | ... AL21: =AK21+AL19-AL20
A22: Активные пользователи всего | C22: =C17+C18+C21 | D22: =D17+D18+D21 | E22: =E17+E18+E21 | F22: =F17+F18+F21 | G22: =G17+G18+G21 | H22: =H17+H18+H21 | I22: =I17+I18+I21 | J22: =J17+J18+J21 | ... AL22: =AL17+AL18+AL21
A23: ВЫРУЧКА, $
A24: Оплаты подписок (брутто) | B24: =SUM(C24:AL24) | C24: =C21*'Себестоимость'!$C$12 | D24: =D21*'Себестоимость'!$C$12 | E24: =E21*'Себестоимость'!$C$12 | F24: =F21*'Себестоимость'!$C$12 | G24: =G21*'Себестоимость'!$C$12 | H24: =H21*'Себестоимость'!$C$12 | I24: =I21*'Себестоимость'!$C$12 | J24: =J21*'Себестоимость'!$C$12 | ... AL24: =AL21*'Себестоимость'!$C$12
A25: Комиссии магазинов/Paddle и НДС | B25: =SUM(C25:AL25) | C25: =C24-C26 | D25: =D24-D26 | E25: =E24-E26 | F25: =F24-F26 | G25: =G24-G26 | H25: =H24-H26 | I25: =I24-I26 | J25: =J24-J26 | ... AL25: =AL24-AL26
A26: Чистая выручка подписок | B26: =SUM(C26:AL26) | C26: =C21*'Себестоимость'!$C$13 | D26: =D21*'Себестоимость'!$C$13 | E26: =E21*'Себестоимость'!$C$13 | F26: =F21*'Себестоимость'!$C$13 | G26: =G21*'Себестоимость'!$C$13 | H26: =H21*'Себестоимость'!$C$13 | I26: =I21*'Себестоимость'!$C$13 | J26: =J21*'Себестоимость'!$C$13 | ... AL26: =AL21*'Себестоимость'!$C$13
A27: Донаты (чистые) | B27: =SUM(C27:AL27) | C27: =C17*'Допущения'!$C$75*'Допущения'!$C$76*(1-'Допущения'!$C$77) | D27: =D17*'Допущения'!$C$75*'Допущения'!$C$76*(1-'Допущения'!$C$77) | E27: =E17*'Допущения'!$C$75*'Допущения'!$C$76*(1-'Допущения'!$C$77) | F27: =F17*'Допущения'!$C$75*'Допущения'!$C$76*(1-'Допущения'!$C$77) | G27: =G17*'Допущения'!$C$75*'Допущения'!$C$76*(1-'Допущения'!$C$77) | H27: =H17*'Допущения'!$C$75*'Допущения'!$C$76*(1-'Допущения'!$C$77) | I27: =I17*'Допущения'!$C$75*'Допущения'!$C$76*(1-'Допущения'!$C$77) | J27: =J17*'Допущения'!$C$75*'Допущения'!$C$76*(1-'Допущения'!$C$77) | ... AL27: =AL17*'Допущения'!$C$75*'Допущения'!$C$76*(1-'Допущения'!$C$77)
A28: Итого чистая выручка | B28: =SUM(C28:AL28) | C28: =C26+C27 | D28: =D26+D27 | E28: =E26+E27 | F28: =F26+F27 | G28: =G26+G27 | H28: =H26+H27 | I28: =I26+I27 | J28: =J26+J27 | ... AL28: =AL26+AL27
A29: ПЕРЕМЕННЫЕ ЗАТРАТЫ, $
A30: LLM: платящие | B30: =SUM(C30:AL30) | C30: =C21*'Себестоимость'!$C$14 | D30: =D21*'Себестоимость'!$C$14 | E30: =E21*'Себестоимость'!$C$14 | F30: =F21*'Себестоимость'!$C$14 | G30: =G21*'Себестоимость'!$C$14 | H30: =H21*'Себестоимость'!$C$14 | I30: =I21*'Себестоимость'!$C$14 | J30: =J21*'Себестоимость'!$C$14 | ... AL30: =AL21*'Себестоимость'!$C$14
A31: LLM: free и прототип | B31: =SUM(C31:AL31) | C31: =C18*'Себестоимость'!$C$16+C17*'Допущения'!$C$74*'Себестоимость'!$C$7 | D31: =D18*'Себестоимость'!$C$16+D17*'Допущения'!$C$74*'Себестоимость'!$C$7 | E31: =E18*'Себестоимость'!$C$16+E17*'Допущения'!$C$74*'Себестоимость'!$C$7 | F31: =F18*'Себестоимость'!$C$16+F17*'Допущения'!$C$74*'Себестоимость'!$C$7 | G31: =G18*'Себестоимость'!$C$16+G17*'Допущения'!$C$74*'Себестоимость'!$C$7 | H31: =H18*'Себестоимость'!$C$16+H17*'Допущения'!$C$74*'Себестоимость'!$C$7 | I31: =I18*'Себестоимость'!$C$16+I17*'Допущения'!$C$74*'Себестоимость'!$C$7 | J31: =J18*'Себестоимость'!$C$16+J17*'Допущения'!$C$74*'Себестоимость'!$C$7 | ... AL31: =AL18*'Себестоимость'!$C$16+AL17*'Допущения'!$C$74*'Себестоимость'!$C$7
A32: Проверка возраста | B32: =SUM(C32:AL32) | C32: =C19*'Допущения'!$C$44*'Допущения'!$C$93 | D32: =D19*'Допущения'!$C$44*'Допущения'!$C$93 | E32: =E19*'Допущения'!$C$44*'Допущения'!$C$93 | F32: =F19*'Допущения'!$C$44*'Допущения'!$C$93 | G32: =G19*'Допущения'!$C$44*'Допущения'!$C$93 | H32: =H19*'Допущения'!$C$44*'Допущения'!$C$93 | I32: =I19*'Допущения'!$C$44*'Допущения'!$C$93 | J32: =J19*'Допущения'!$C$44*'Допущения'!$C$93 | ... AL32: =AL19*'Допущения'!$C$44*'Допущения'!$C$93
A33: Инфраструктура (на пользователя) | B33: =SUM(C33:AL33) | C33: =C22*'Допущения'!$C$86 | D33: =D22*'Допущения'!$C$86 | E33: =E22*'Допущения'!$C$86 | F33: =F22*'Допущения'!$C$86 | G33: =G22*'Допущения'!$C$86 | H33: =H22*'Допущения'!$C$86 | I33: =I22*'Допущения'!$C$86 | J33: =J22*'Допущения'!$C$86 | ... AL33: =AL22*'Допущения'!$C$86
A34: Итого переменные | B34: =SUM(C34:AL34) | C34: =SUM(C30:C33) | D34: =SUM(D30:D33) | E34: =SUM(E30:E33) | F34: =SUM(F30:F33) | G34: =SUM(G30:G33) | H34: =SUM(H30:H33) | I34: =SUM(I30:I33) | J34: =SUM(J30:J33) | ... AL34: =SUM(AL30:AL33)
A35: Валовая прибыль | B35: =SUM(C35:AL35) | C35: =C28-C34 | D35: =D28-D34 | E35: =E28-E34 | F35: =F28-F34 | G35: =G28-G34 | H35: =H28-H34 | I35: =I28-I34 | J35: =J28-J34 | ... AL35: =AL28-AL34
A36: Валовая маржа | B36: =IFERROR(B35/B28,0) | C36: =IFERROR(C35/C28,0) | D36: =IFERROR(D35/D28,0) | E36: =IFERROR(E35/E28,0) | F36: =IFERROR(F35/F28,0) | G36: =IFERROR(G35/G28,0) | H36: =IFERROR(H35/H28,0) | I36: =IFERROR(I35/I28,0) | ... AL36: =IFERROR(AL35/AL28,0)
A37: ПОСТОЯННЫЕ ЗАТРАТЫ И МАРКЕТИНГ, $
A38: Инфраструктура (база) | B38: =SUM(C38:AL38) | C38: ='Допущения'!$C$85 | D38: ='Допущения'!$C$85 | E38: ='Допущения'!$C$85 | F38: ='Допущения'!$C$85 | G38: ='Допущения'!$C$85 | H38: ='Допущения'!$C$85 | I38: ='Допущения'!$C$85 | J38: ='Допущения'!$C$85 | ... AL38: ='Допущения'!$C$85
A39: SaaS-инструменты | B39: =SUM(C39:AL39) | C39: ='Допущения'!$C$87 | D39: ='Допущения'!$C$87 | E39: ='Допущения'!$C$87 | F39: ='Допущения'!$C$87 | G39: ='Допущения'!$C$87 | H39: ='Допущения'!$C$87 | I39: ='Допущения'!$C$87 | J39: ='Допущения'!$C$87 | ... AL39: ='Допущения'!$C$87
A40: Бухгалтерия | B40: =SUM(C40:AL40) | C40: =IF(C6>='Допущения'!$C$10,'Допущения'!$C$88,0) | D40: =IF(D6>='Допущения'!$C$10,'Допущения'!$C$88,0) | E40: =IF(E6>='Допущения'!$C$10,'Допущения'!$C$88,0) | F40: =IF(F6>='Допущения'!$C$10,'Допущения'!$C$88,0) | G40: =IF(G6>='Допущения'!$C$10,'Допущения'!$C$88,0) | H40: =IF(H6>='Допущения'!$C$10,'Допущения'!$C$88,0) | I40: =IF(I6>='Допущения'!$C$10,'Допущения'!$C$88,0) | J40: =IF(J6>='Допущения'!$C$10,'Допущения'!$C$88,0) | ... AL40: =IF(AL6>='Допущения'!$C$10,'Допущения'!$C$88,0)
A41: Юр. сопровождение | B41: =SUM(C41:AL41) | C41: =IF(C9=1,'Допущения'!$C$89,0) | D41: =IF(D9=1,'Допущения'!$C$89,0) | E41: =IF(E9=1,'Допущения'!$C$89,0) | F41: =IF(F9=1,'Допущения'!$C$89,0) | G41: =IF(G9=1,'Допущения'!$C$89,0) | H41: =IF(H9=1,'Допущения'!$C$89,0) | I41: =IF(I9=1,'Допущения'!$C$89,0) | J41: =IF(J9=1,'Допущения'!$C$89,0) | ... AL41: =IF(AL9=1,'Допущения'!$C$89,0)
A42: Магазины приложений | B42: =SUM(C42:AL42) | C42: =IF(C6='Допущения'!$C$9-1,'Допущения'!$C$90+'Допущения'!$C$91,0)+IF(AND(C6>'Допущения'!$C$9-1,MOD(C6-('Допущения'!$C$9-1),12)=0),'Допущения'!$C$90,0) | D42: =IF(D6='Допущения'!$C$9-1,'Допущения'!$C$90+'Допущения'!$C$91,0)+IF(AND(D6>'Допущения'!$C$9-1,MOD(D6-('Допущения'!$C$9-1),12)=0),'Допущения'!$C$90,0) | E42: =IF(E6='Допущения'!$C$9-1,'Допущения'!$C$90+'Допущения'!$C$91,0)+IF(AND(E6>'Допущения'!$C$9-1,MOD(E6-('Допущения'!$C$9-1),12)=0),'Допущения'!$C$90,0) | F42: =IF(F6='Допущения'!$C$9-1,'Допущения'!$C$90+'Допущения'!$C$91,0)+IF(AND(F6>'Допущения'!$C$9-1,MOD(F6-('Допущения'!$C$9-1),12)=0),'Допущения'!$C$90,0) | G42: =IF(G6='Допущения'!$C$9-1,'Допущения'!$C$90+'Допущения'!$C$91,0)+IF(AND(G6>'Допущения'!$C$9-1,MOD(G6-('Допущения'!$C$9-1),12)=0),'Допущения'!$C$90,0) | H42: =IF(H6='Допущения'!$C$9-1,'Допущения'!$C$90+'Допущения'!$C$91,0)+IF(AND(H6>'Допущения'!$C$9-1,MOD(H6-('Допущения'!$C$9-1),12)=0),'Допущения'!$C$90,0) | I42: =IF(I6='Допущения'!$C$9-1,'Допущения'!$C$90+'Допущения'!$C$91,0)+IF(AND(I6>'Допущения'!$C$9-1,MOD(I6-('Допущения'!$C$9-1),12)=0),'Допущения'!$C$90,0) | J42: =IF(J6='Допущения'!$C$9-1,'Допущения'!$C$90+'Допущения'!$C$91,0)+IF(AND(J6>'Допущения'!$C$9-1,MOD(J6-('Допущения'!$C$9-1),12)=0),'Допущения'!$C$90,0) | ... AL42: =IF(AL6='Допущения'!$C$9-1,'Допущения'!$C$90+'Допущения'!$C$91,0)+IF(AND(AL6>'Допущения'!$C$9-1,MOD(AL6-('Допущения'!$C$9-1),12)=0),'Допущения'!$C$90,0)
A43: Разовые стартовые (лист «Старт») | B43: =SUM(C43:AL43) | C43: =SUMIF('Старт'!$C$5:$C$17,C6,'Старт'!$D$5:$D$17) | D43: =SUMIF('Старт'!$C$5:$C$17,D6,'Старт'!$D$5:$D$17) | E43: =SUMIF('Старт'!$C$5:$C$17,E6,'Старт'!$D$5:$D$17) | F43: =SUMIF('Старт'!$C$5:$C$17,F6,'Старт'!$D$5:$D$17) | G43: =SUMIF('Старт'!$C$5:$C$17,G6,'Старт'!$D$5:$D$17) | H43: =SUMIF('Старт'!$C$5:$C$17,H6,'Старт'!$D$5:$D$17) | I43: =SUMIF('Старт'!$C$5:$C$17,I6,'Старт'!$D$5:$D$17) | J43: =SUMIF('Старт'!$C$5:$C$17,J6,'Старт'!$D$5:$D$17) | ... AL43: =SUMIF('Старт'!$C$5:$C$17,AL6,'Старт'!$D$5:$D$17)
A44: Контент / SMM | B44: =SUM(C44:AL44) | C44: =IF(C6>'Допущения'!$C$9,'Допущения'!$C$92,0) | D44: =IF(D6>'Допущения'!$C$9,'Допущения'!$C$92,0) | E44: =IF(E6>'Допущения'!$C$9,'Допущения'!$C$92,0) | F44: =IF(F6>'Допущения'!$C$9,'Допущения'!$C$92,0) | G44: =IF(G6>'Допущения'!$C$9,'Допущения'!$C$92,0) | H44: =IF(H6>'Допущения'!$C$9,'Допущения'!$C$92,0) | I44: =IF(I6>'Допущения'!$C$9,'Допущения'!$C$92,0) | J44: =IF(J6>'Допущения'!$C$9,'Допущения'!$C$92,0) | ... AL44: =IF(AL6>'Допущения'!$C$9,'Допущения'!$C$92,0)
A45: Маркетинг | B45: =SUM(C45:AL45) | C45: =C11 | D45: =D11 | E45: =E11 | F45: =F11 | G45: =G11 | H45: =H11 | I45: =I11 | J45: =J11 | ... AL45: =AL11
A46: Выплаты основателям | B46: =SUM(C46:AL46) | C46: =IF(C6>='Допущения'!$C$94,MIN('Допущения'!$C$95,MAX(0,'Допущения'!$C$96*(0+0))),0) | D46: =IF(D6>='Допущения'!$C$94,MIN('Допущения'!$C$95,MAX(0,'Допущения'!$C$96*(C48+C46))),0) | E46: =IF(E6>='Допущения'!$C$94,MIN('Допущения'!$C$95,MAX(0,'Допущения'!$C$96*(D48+D46))),0) | F46: =IF(F6>='Допущения'!$C$94,MIN('Допущения'!$C$95,MAX(0,'Допущения'!$C$96*(E48+E46))),0) | G46: =IF(G6>='Допущения'!$C$94,MIN('Допущения'!$C$95,MAX(0,'Допущения'!$C$96*(F48+F46))),0) | H46: =IF(H6>='Допущения'!$C$94,MIN('Допущения'!$C$95,MAX(0,'Допущения'!$C$96*(G48+G46))),0) | I46: =IF(I6>='Допущения'!$C$94,MIN('Допущения'!$C$95,MAX(0,'Допущения'!$C$96*(H48+H46))),0) | J46: =IF(J6>='Допущения'!$C$94,MIN('Допущения'!$C$95,MAX(0,'Допущения'!$C$96*(I48+I46))),0) | K46: =IF(K6>='Допущения'!$C$94,MIN('Допущения'!$C$95,MAX(0,'Допущения'!$C$96*(J48+J46))),0) | ... AL46: =IF(AL6>='Допущения'!$C$94,MIN('Допущения'!$C$95,MAX(0,'Допущения'!$C$96*(AK48+AK46))),0)
A47: Итого постоянные + маркетинг | B47: =SUM(C47:AL47) | C47: =SUM(C38:C46) | D47: =SUM(D38:D46) | E47: =SUM(E38:E46) | F47: =SUM(F38:F46) | G47: =SUM(G38:G46) | H47: =SUM(H38:H46) | I47: =SUM(I38:I46) | J47: =SUM(J38:J46) | ... AL47: =SUM(AL38:AL46)
A48: EBITDA | B48: =SUM(C48:AL48) | C48: =C35-C47 | D48: =D35-D47 | E48: =E35-E47 | F48: =F35-F47 | G48: =G35-G47 | H48: =H35-H47 | I48: =I35-I47 | J48: =J35-J47 | ... AL48: =AL35-AL47
A49: Налог на прибыль | B49: =SUM(C49:AL49) | C49: =MAX(0,C48)*'Допущения'!$C$57 | D49: =MAX(0,D48)*'Допущения'!$C$57 | E49: =MAX(0,E48)*'Допущения'!$C$57 | F49: =MAX(0,F48)*'Допущения'!$C$57 | G49: =MAX(0,G48)*'Допущения'!$C$57 | H49: =MAX(0,H48)*'Допущения'!$C$57 | I49: =MAX(0,I48)*'Допущения'!$C$57 | J49: =MAX(0,J48)*'Допущения'!$C$57 | ... AL49: =MAX(0,AL48)*'Допущения'!$C$57
A50: Операционный денежный поток | B50: =SUM(C50:AL50) | C50: =C48-C49 | D50: =D48-D49 | E50: =E48-E49 | F50: =F48-F49 | G50: =G48-G49 | H50: =H48-H49 | I50: =I48-I49 | J50: =J48-J49 | ... AL50: =AL48-AL49
A51: Накопленный операционный поток | B51: =MIN(C51:AL51) | C51: =0+C50 | D51: =C51+D50 | E51: =D51+E50 | F51: =E51+F50 | G51: =F51+G50 | H51: =G51+H50 | I51: =H51+I50 | J51: =I51+J50 | K51: =J51+K50 | ... AL51: =AK51+AL50
A52: ВЛОЖЕНИЯ И КАССА, $
A53: Вложения партнёра (выбранный вариант) | B53: =SUM(C53:AL53) | C53: =(IF(C6=1,INDEX('Допущения'!$C$104:$C$106,'Допущения'!$D$103)*'Допущения'!$C$107,0)+IF(C6='Допущения'!$C$9,INDEX('Допущения'!$C$104:$C$106,'Допущения'!$D$103)*(1-'Допущения'!$C$107),0))/'Допущения'!$C$7 | D53: =(IF(D6=1,INDEX('Допущения'!$C$104:$C$106,'Допущения'!$D$103)*'Допущения'!$C$107,0)+IF(D6='Допущения'!$C$9,INDEX('Допущения'!$C$104:$C$106,'Допущения'!$D$103)*(1-'Допущения'!$C$107),0))/'Допущения'!$C$7 | E53: =(IF(E6=1,INDEX('Допущения'!$C$104:$C$106,'Допущения'!$D$103)*'Допущения'!$C$107,0)+IF(E6='Допущения'!$C$9,INDEX('Допущения'!$C$104:$C$106,'Допущения'!$D$103)*(1-'Допущения'!$C$107),0))/'Допущения'!$C$7 | F53: =(IF(F6=1,INDEX('Допущения'!$C$104:$C$106,'Допущения'!$D$103)*'Допущения'!$C$107,0)+IF(F6='Допущения'!$C$9,INDEX('Допущения'!$C$104:$C$106,'Допущения'!$D$103)*(1-'Допущения'!$C$107),0))/'Допущения'!$C$7 | G53: =(IF(G6=1,INDEX('Допущения'!$C$104:$C$106,'Допущения'!$D$103)*'Допущения'!$C$107,0)+IF(G6='Допущения'!$C$9,INDEX('Допущения'!$C$104:$C$106,'Допущения'!$D$103)*(1-'Допущения'!$C$107),0))/'Допущения'!$C$7 | H53: =(IF(H6=1,INDEX('Допущения'!$C$104:$C$106,'Допущения'!$D$103)*'Допущения'!$C$107,0)+IF(H6='Допущения'!$C$9,INDEX('Допущения'!$C$104:$C$106,'Допущения'!$D$103)*(1-'Допущения'!$C$107),0))/'Допущения'!$C$7 | I53: =(IF(I6=1,INDEX('Допущения'!$C$104:$C$106,'Допущения'!$D$103)*'Допущения'!$C$107,0)+IF(I6='Допущения'!$C$9,INDEX('Допущения'!$C$104:$C$106,'Допущения'!$D$103)*(1-'Допущения'!$C$107),0))/'Допущения'!$C$7 | J53: =(IF(J6=1,INDEX('Допущения'!$C$104:$C$106,'Допущения'!$D$103)*'Допущения'!$C$107,0)+IF(J6='Допущения'!$C$9,INDEX('Допущения'!$C$104:$C$106,'Допущения'!$D$103)*(1-'Допущения'!$C$107),0))/'Допущения'!$C$7 | ... AL53: =(IF(AL6=1,INDEX('Допущения'!$C$104:$C$106,'Допущения'!$D$103)*'Допущения'!$C$107,0)+IF(AL6='Допущения'!$C$9,INDEX('Допущения'!$C$104:$C$106,'Допущения'!$D$103)*(1-'Допущения'!$C$107),0))/'Допущения'!$C$7
A54: Мои вложения (выбранный вариант) | B54: =SUM(C54:AL54) | C54: =(IF(C6=1,MIN(INDEX('Допущения'!$D$104:$D$106,'Допущения'!$D$103),'Допущения'!$C$108),0)+IF(AND(C6>=2,C6<=4),MAX(0,INDEX('Допущения'!$D$104:$D$106,'Допущения'!$D$103)-'Допущения'!$C$108)/3,0))/'Допущения'!$C$7 | D54: =(IF(D6=1,MIN(INDEX('Допущения'!$D$104:$D$106,'Допущения'!$D$103),'Допущения'!$C$108),0)+IF(AND(D6>=2,D6<=4),MAX(0,INDEX('Допущения'!$D$104:$D$106,'Допущения'!$D$103)-'Допущения'!$C$108)/3,0))/'Допущения'!$C$7 | E54: =(IF(E6=1,MIN(INDEX('Допущения'!$D$104:$D$106,'Допущения'!$D$103),'Допущения'!$C$108),0)+IF(AND(E6>=2,E6<=4),MAX(0,INDEX('Допущения'!$D$104:$D$106,'Допущения'!$D$103)-'Допущения'!$C$108)/3,0))/'Допущения'!$C$7 | F54: =(IF(F6=1,MIN(INDEX('Допущения'!$D$104:$D$106,'Допущения'!$D$103),'Допущения'!$C$108),0)+IF(AND(F6>=2,F6<=4),MAX(0,INDEX('Допущения'!$D$104:$D$106,'Допущения'!$D$103)-'Допущения'!$C$108)/3,0))/'Допущения'!$C$7 | G54: =(IF(G6=1,MIN(INDEX('Допущения'!$D$104:$D$106,'Допущения'!$D$103),'Допущения'!$C$108),0)+IF(AND(G6>=2,G6<=4),MAX(0,INDEX('Допущения'!$D$104:$D$106,'Допущения'!$D$103)-'Допущения'!$C$108)/3,0))/'Допущения'!$C$7 | H54: =(IF(H6=1,MIN(INDEX('Допущения'!$D$104:$D$106,'Допущения'!$D$103),'Допущения'!$C$108),0)+IF(AND(H6>=2,H6<=4),MAX(0,INDEX('Допущения'!$D$104:$D$106,'Допущения'!$D$103)-'Допущения'!$C$108)/3,0))/'Допущения'!$C$7 | I54: =(IF(I6=1,MIN(INDEX('Допущения'!$D$104:$D$106,'Допущения'!$D$103),'Допущения'!$C$108),0)+IF(AND(I6>=2,I6<=4),MAX(0,INDEX('Допущения'!$D$104:$D$106,'Допущения'!$D$103)-'Допущения'!$C$108)/3,0))/'Допущения'!$C$7 | J54: =(IF(J6=1,MIN(INDEX('Допущения'!$D$104:$D$106,'Допущения'!$D$103),'Допущения'!$C$108),0)+IF(AND(J6>=2,J6<=4),MAX(0,INDEX('Допущения'!$D$104:$D$106,'Допущения'!$D$103)-'Допущения'!$C$108)/3,0))/'Допущения'!$C$7 | ... AL54: =(IF(AL6=1,MIN(INDEX('Допущения'!$D$104:$D$106,'Допущения'!$D$103),'Допущения'!$C$108),0)+IF(AND(AL6>=2,AL6<=4),MAX(0,INDEX('Допущения'!$D$104:$D$106,'Допущения'!$D$103)-'Допущения'!$C$108)/3,0))/'Допущения'!$C$7
A55: Касса на конец месяца | B55: =MIN(C55:AL55) | C55: =0+C50+C53+C54 | D55: =C55+D50+D53+D54 | E55: =D55+E50+E53+E54 | F55: =E55+F50+F53+F54 | G55: =F55+G50+G53+G54 | H55: =G55+H50+H53+H54 | I55: =H55+I50+I53+I54 | J55: =I55+J50+J53+J54 | K55: =J55+K50+K53+K54 | ... AL55: =AK55+AL50+AL53+AL54
A56: Касса при варианте 1 «Минимум» | B56: =MIN(C56:AL56) | C56: =C51+('Допущения'!$C$104*'Допущения'!$C$107+IF(C6>='Допущения'!$C$9,'Допущения'!$C$104*(1-'Допущения'!$C$107),0)+MIN('Допущения'!$D$104,'Допущения'!$C$108)+MAX(0,'Допущения'!$D$104-'Допущения'!$C$108)*MIN(MAX(C6-1,0),3)/3)/'Допущения'!$C$7 | D56: =D51+('Допущения'!$C$104*'Допущения'!$C$107+IF(D6>='Допущения'!$C$9,'Допущения'!$C$104*(1-'Допущения'!$C$107),0)+MIN('Допущения'!$D$104,'Допущения'!$C$108)+MAX(0,'Допущения'!$D$104-'Допущения'!$C$108)*MIN(MAX(D6-1,0),3)/3)/'Допущения'!$C$7 | E56: =E51+('Допущения'!$C$104*'Допущения'!$C$107+IF(E6>='Допущения'!$C$9,'Допущения'!$C$104*(1-'Допущения'!$C$107),0)+MIN('Допущения'!$D$104,'Допущения'!$C$108)+MAX(0,'Допущения'!$D$104-'Допущения'!$C$108)*MIN(MAX(E6-1,0),3)/3)/'Допущения'!$C$7 | F56: =F51+('Допущения'!$C$104*'Допущения'!$C$107+IF(F6>='Допущения'!$C$9,'Допущения'!$C$104*(1-'Допущения'!$C$107),0)+MIN('Допущения'!$D$104,'Допущения'!$C$108)+MAX(0,'Допущения'!$D$104-'Допущения'!$C$108)*MIN(MAX(F6-1,0),3)/3)/'Допущения'!$C$7 | G56: =G51+('Допущения'!$C$104*'Допущения'!$C$107+IF(G6>='Допущения'!$C$9,'Допущения'!$C$104*(1-'Допущения'!$C$107),0)+MIN('Допущения'!$D$104,'Допущения'!$C$108)+MAX(0,'Допущения'!$D$104-'Допущения'!$C$108)*MIN(MAX(G6-1,0),3)/3)/'Допущения'!$C$7 | H56: =H51+('Допущения'!$C$104*'Допущения'!$C$107+IF(H6>='Допущения'!$C$9,'Допущения'!$C$104*(1-'Допущения'!$C$107),0)+MIN('Допущения'!$D$104,'Допущения'!$C$108)+MAX(0,'Допущения'!$D$104-'Допущения'!$C$108)*MIN(MAX(H6-1,0),3)/3)/'Допущения'!$C$7 | I56: =I51+('Допущения'!$C$104*'Допущения'!$C$107+IF(I6>='Допущения'!$C$9,'Допущения'!$C$104*(1-'Допущения'!$C$107),0)+MIN('Допущения'!$D$104,'Допущения'!$C$108)+MAX(0,'Допущения'!$D$104-'Допущения'!$C$108)*MIN(MAX(I6-1,0),3)/3)/'Допущения'!$C$7 | J56: =J51+('Допущения'!$C$104*'Допущения'!$C$107+IF(J6>='Допущения'!$C$9,'Допущения'!$C$104*(1-'Допущения'!$C$107),0)+MIN('Допущения'!$D$104,'Допущения'!$C$108)+MAX(0,'Допущения'!$D$104-'Допущения'!$C$108)*MIN(MAX(J6-1,0),3)/3)/'Допущения'!$C$7 | ... AL56: =AL51+('Допущения'!$C$104*'Допущения'!$C$107+IF(AL6>='Допущения'!$C$9,'Допущения'!$C$104*(1-'Допущения'!$C$107),0)+MIN('Допущения'!$D$104,'Допущения'!$C$108)+MAX(0,'Допущения'!$D$104-'Допущения'!$C$108)*MIN(MAX(AL6-1,0),3)/3)/'Допущения'!$C$7
A57: Касса при варианте 2 «Средний» | B57: =MIN(C57:AL57) | C57: =C51+('Допущения'!$C$105*'Допущения'!$C$107+IF(C6>='Допущения'!$C$9,'Допущения'!$C$105*(1-'Допущения'!$C$107),0)+MIN('Допущения'!$D$105,'Допущения'!$C$108)+MAX(0,'Допущения'!$D$105-'Допущения'!$C$108)*MIN(MAX(C6-1,0),3)/3)/'Допущения'!$C$7 | D57: =D51+('Допущения'!$C$105*'Допущения'!$C$107+IF(D6>='Допущения'!$C$9,'Допущения'!$C$105*(1-'Допущения'!$C$107),0)+MIN('Допущения'!$D$105,'Допущения'!$C$108)+MAX(0,'Допущения'!$D$105-'Допущения'!$C$108)*MIN(MAX(D6-1,0),3)/3)/'Допущения'!$C$7 | E57: =E51+('Допущения'!$C$105*'Допущения'!$C$107+IF(E6>='Допущения'!$C$9,'Допущения'!$C$105*(1-'Допущения'!$C$107),0)+MIN('Допущения'!$D$105,'Допущения'!$C$108)+MAX(0,'Допущения'!$D$105-'Допущения'!$C$108)*MIN(MAX(E6-1,0),3)/3)/'Допущения'!$C$7 | F57: =F51+('Допущения'!$C$105*'Допущения'!$C$107+IF(F6>='Допущения'!$C$9,'Допущения'!$C$105*(1-'Допущения'!$C$107),0)+MIN('Допущения'!$D$105,'Допущения'!$C$108)+MAX(0,'Допущения'!$D$105-'Допущения'!$C$108)*MIN(MAX(F6-1,0),3)/3)/'Допущения'!$C$7 | G57: =G51+('Допущения'!$C$105*'Допущения'!$C$107+IF(G6>='Допущения'!$C$9,'Допущения'!$C$105*(1-'Допущения'!$C$107),0)+MIN('Допущения'!$D$105,'Допущения'!$C$108)+MAX(0,'Допущения'!$D$105-'Допущения'!$C$108)*MIN(MAX(G6-1,0),3)/3)/'Допущения'!$C$7 | H57: =H51+('Допущения'!$C$105*'Допущения'!$C$107+IF(H6>='Допущения'!$C$9,'Допущения'!$C$105*(1-'Допущения'!$C$107),0)+MIN('Допущения'!$D$105,'Допущения'!$C$108)+MAX(0,'Допущения'!$D$105-'Допущения'!$C$108)*MIN(MAX(H6-1,0),3)/3)/'Допущения'!$C$7 | I57: =I51+('Допущения'!$C$105*'Допущения'!$C$107+IF(I6>='Допущения'!$C$9,'Допущения'!$C$105*(1-'Допущения'!$C$107),0)+MIN('Допущения'!$D$105,'Допущения'!$C$108)+MAX(0,'Допущения'!$D$105-'Допущения'!$C$108)*MIN(MAX(I6-1,0),3)/3)/'Допущения'!$C$7 | J57: =J51+('Допущения'!$C$105*'Допущения'!$C$107+IF(J6>='Допущения'!$C$9,'Допущения'!$C$105*(1-'Допущения'!$C$107),0)+MIN('Допущения'!$D$105,'Допущения'!$C$108)+MAX(0,'Допущения'!$D$105-'Допущения'!$C$108)*MIN(MAX(J6-1,0),3)/3)/'Допущения'!$C$7 | ... AL57: =AL51+('Допущения'!$C$105*'Допущения'!$C$107+IF(AL6>='Допущения'!$C$9,'Допущения'!$C$105*(1-'Допущения'!$C$107),0)+MIN('Допущения'!$D$105,'Допущения'!$C$108)+MAX(0,'Допущения'!$D$105-'Допущения'!$C$108)*MIN(MAX(AL6-1,0),3)/3)/'Допущения'!$C$7
A58: Касса при варианте 3 «Максимум» | B58: =MIN(C58:AL58) | C58: =C51+('Допущения'!$C$106*'Допущения'!$C$107+IF(C6>='Допущения'!$C$9,'Допущения'!$C$106*(1-'Допущения'!$C$107),0)+MIN('Допущения'!$D$106,'Допущения'!$C$108)+MAX(0,'Допущения'!$D$106-'Допущения'!$C$108)*MIN(MAX(C6-1,0),3)/3)/'Допущения'!$C$7 | D58: =D51+('Допущения'!$C$106*'Допущения'!$C$107+IF(D6>='Допущения'!$C$9,'Допущения'!$C$106*(1-'Допущения'!$C$107),0)+MIN('Допущения'!$D$106,'Допущения'!$C$108)+MAX(0,'Допущения'!$D$106-'Допущения'!$C$108)*MIN(MAX(D6-1,0),3)/3)/'Допущения'!$C$7 | E58: =E51+('Допущения'!$C$106*'Допущения'!$C$107+IF(E6>='Допущения'!$C$9,'Допущения'!$C$106*(1-'Допущения'!$C$107),0)+MIN('Допущения'!$D$106,'Допущения'!$C$108)+MAX(0,'Допущения'!$D$106-'Допущения'!$C$108)*MIN(MAX(E6-1,0),3)/3)/'Допущения'!$C$7 | F58: =F51+('Допущения'!$C$106*'Допущения'!$C$107+IF(F6>='Допущения'!$C$9,'Допущения'!$C$106*(1-'Допущения'!$C$107),0)+MIN('Допущения'!$D$106,'Допущения'!$C$108)+MAX(0,'Допущения'!$D$106-'Допущения'!$C$108)*MIN(MAX(F6-1,0),3)/3)/'Допущения'!$C$7 | G58: =G51+('Допущения'!$C$106*'Допущения'!$C$107+IF(G6>='Допущения'!$C$9,'Допущения'!$C$106*(1-'Допущения'!$C$107),0)+MIN('Допущения'!$D$106,'Допущения'!$C$108)+MAX(0,'Допущения'!$D$106-'Допущения'!$C$108)*MIN(MAX(G6-1,0),3)/3)/'Допущения'!$C$7 | H58: =H51+('Допущения'!$C$106*'Допущения'!$C$107+IF(H6>='Допущения'!$C$9,'Допущения'!$C$106*(1-'Допущения'!$C$107),0)+MIN('Допущения'!$D$106,'Допущения'!$C$108)+MAX(0,'Допущения'!$D$106-'Допущения'!$C$108)*MIN(MAX(H6-1,0),3)/3)/'Допущения'!$C$7 | I58: =I51+('Допущения'!$C$106*'Допущения'!$C$107+IF(I6>='Допущения'!$C$9,'Допущения'!$C$106*(1-'Допущения'!$C$107),0)+MIN('Допущения'!$D$106,'Допущения'!$C$108)+MAX(0,'Допущения'!$D$106-'Допущения'!$C$108)*MIN(MAX(I6-1,0),3)/3)/'Допущения'!$C$7 | J58: =J51+('Допущения'!$C$106*'Допущения'!$C$107+IF(J6>='Допущения'!$C$9,'Допущения'!$C$106*(1-'Допущения'!$C$107),0)+MIN('Допущения'!$D$106,'Допущения'!$C$108)+MAX(0,'Допущения'!$D$106-'Допущения'!$C$108)*MIN(MAX(J6-1,0),3)/3)/'Допущения'!$C$7 | ... AL58: =AL51+('Допущения'!$C$106*'Допущения'!$C$107+IF(AL6>='Допущения'!$C$9,'Допущения'!$C$106*(1-'Допущения'!$C$107),0)+MIN('Допущения'!$D$106,'Допущения'!$C$108)+MAX(0,'Допущения'!$D$106-'Допущения'!$C$108)*MIN(MAX(AL6-1,0),3)/3)/'Допущения'!$C$7
A59: МЕТРИКИ
A60: MRR (брутто), $ | C60: =C24 | D60: =D24 | E60: =E24 | F60: =F24 | G60: =G24 | H60: =H24 | I60: =I24 | J60: =J24 | ... AL60: =AL24
A61: CAC на нового платящего, $ | B61: =IFERROR(B11/B19,0) | C61: =IFERROR(IF(C9=1,C11/C19,0),0) | D61: =IFERROR(IF(D9=1,D11/D19,0),0) | E61: =IFERROR(IF(E9=1,E11/E19,0),0) | F61: =IFERROR(IF(F9=1,F11/F19,0),0) | G61: =IFERROR(IF(G9=1,G11/G19,0),0) | H61: =IFERROR(IF(H9=1,H11/H19,0),0) | I61: =IFERROR(IF(I9=1,I11/I19,0),0) | J61: =IFERROR(IF(J9=1,J11/J19,0),0) | ... AL61: =IFERROR(IF(AL9=1,AL11/AL19,0),0)
A62: Флаг: EBITDA ≥ 0 после выхода | C62: =IF(AND(C9=1,C48>=0),1,0) | D62: =IF(AND(D9=1,D48>=0),1,0) | E62: =IF(AND(E9=1,E48>=0),1,0) | F62: =IF(AND(F9=1,F48>=0),1,0) | G62: =IF(AND(G9=1,G48>=0),1,0) | H62: =IF(AND(H9=1,H48>=0),1,0) | I62: =IF(AND(I9=1,I48>=0),1,0) | J62: =IF(AND(J9=1,J48>=0),1,0) | ... AL62: =IF(AND(AL9=1,AL48>=0),1,0)
A63: Флаг: EBITDA ≥ 0 в этом и всех следующих месяцах | C63: =IF(AND(C9=1,MIN(C48:$AL$48)>=0),1,0) | D63: =IF(AND(D9=1,MIN(D48:$AL$48)>=0),1,0) | E63: =IF(AND(E9=1,MIN(E48:$AL$48)>=0),1,0) | F63: =IF(AND(F9=1,MIN(F48:$AL$48)>=0),1,0) | G63: =IF(AND(G9=1,MIN(G48:$AL$48)>=0),1,0) | H63: =IF(AND(H9=1,MIN(H48:$AL$48)>=0),1,0) | I63: =IF(AND(I9=1,MIN(I48:$AL$48)>=0),1,0) | J63: =IF(AND(J9=1,MIN(J48:$AL$48)>=0),1,0) | ... AL63: =IF(AND(AL9=1,MIN(AL48:$AL$48)>=0),1,0)
A64: Флаг: накопленный поток ≥ 0 | C64: =IF(C51>=0,1,0) | D64: =IF(D51>=0,1,0) | E64: =IF(E51>=0,1,0) | F64: =IF(F51>=0,1,0) | G64: =IF(G51>=0,1,0) | H64: =IF(H51>=0,1,0) | I64: =IF(I51>=0,1,0) | J64: =IF(J51>=0,1,0) | ... AL64: =IF(AL51>=0,1,0)
A65: Поток для IRR (с терминальной стоимостью) | C65: =C50+0 | D65: =D50+0 | E65: =E50+0 | F65: =F50+0 | G65: =G50+0 | H65: =H50+0 | I65: =I50+0 | J65: =J50+0 | ... AK65: =AK50+0 | AL65: =AL50+AL60*12*'Допущения'!$C$100
A67: СВОДКА
A68: Первый месяц с EBITDA ≥ 0 (№) | B68: =IFERROR(MATCH(1,$C$62:$AL$62,0),"не достигнут")
A69: Устойчивая безубыточность: EBITDA ≥ 0 и дальше (№ мес.) | B69: =IFERROR(MATCH(1,$C$63:$AL$63,0),"не достигнута")
A70: Устойчивая безубыточность (дата) | B70: =IFERROR(INDEX($C$7:$AL$7,MATCH(1,$C$63:$AL$63,0)),"—")
A71: Окупаемость: накопленный поток ≥ 0 (№ мес.) | B71: =IFERROR(MATCH(1,$C$64:$AL$64,0),"> 36 мес.")
A72: Пиковая потребность в финансировании, $ | B72: =-MIN($C$51:$AL$51)
A73: То же, ₽ | B73: =-MIN($C$51:$AL$51)*'Допущения'!$C$7
A74: Чистая выручка, год 1, $ | B74: =SUMIF($C$8:$AL$8,1,$C$28:$AL$28)
A75: Чистая выручка, год 2, $ | B75: =SUMIF($C$8:$AL$8,2,$C$28:$AL$28)
A76: Чистая выручка, год 3, $ | B76: =SUMIF($C$8:$AL$8,3,$C$28:$AL$28)
A77: EBITDA, год 1, $ | B77: =SUMIF($C$8:$AL$8,1,$C$48:$AL$48)
A78: EBITDA, год 2, $ | B78: =SUMIF($C$8:$AL$8,2,$C$48:$AL$48)
A79: EBITDA, год 3, $ | B79: =SUMIF($C$8:$AL$8,3,$C$48:$AL$48)
A80: Платящие, мес. 12 | B80: =$N$21
A81: Платящие, мес. 24 | B81: =$Z$21
A82: Платящие, мес. 36 | B82: =$AL$21
A83: Активные, мес. 12 | B83: =$N$22
A84: Активные, мес. 36 | B84: =$AL$22
A85: MRR, мес. 12, $ | B85: =$N$60
A86: MRR, мес. 24, $ | B86: =$Z$60
A87: MRR, мес. 36, $ | B87: =$AL$60
A88: ARR, мес. 36, $ | B88: =$AL$60*12
A89: CAC средний (маркетинг / новые платящие после выхода), $ | B89: =IFERROR(SUMIF($C$9:$AL$9,1,$C$11:$AL$11)/SUM($C$19:$AL$19),0)
A90: LTV платящего (чистая выручка × маржа / отток), $ | B90: ='Себестоимость'!$C$13*'Себестоимость'!$C$15/'Допущения'!$C$69
A91: LTV / CAC | B91: =IFERROR(B90/B89,0)
A92: Валовая маржа за 36 мес. | B92: =B36
A93: NPV операционного потока + терминальная стоимость, $ | B93: =NPV((1+'Допущения'!$C$99)^(1/12)-1,$C$65:$AL$65)
A94: IRR годовая | B94: =IFERROR((1+IRR($C$65:$AL$65,0.05))^12-1,"н/д")
A95: Мин. касса при выбранном варианте вложений, $ | B95: =B55
A96: Мин. касса: вариант 1, $ | B96: =B56
A97: Мин. касса: вариант 2, $ | B97: =B57
A98: Мин. касса: вариант 3, $ | B98: =B58
A99: Расходы мес. 1 … выход включительно, $ | B99: =SUMIF($C$6:$AL$6,"<="&'Допущения'!$C$9,$C$34:$AL$34)+SUMIF($C$6:$AL$6,"<="&'Допущения'!$C$9,$C$47:$AL$47)

Sheet Модель_О
A1: Финмодель на 36 месяцев — сценарий: Оптимистичный
A2: Все значения считаются формулами из листов «Допущения», «Себестоимость», «Старт».
B5: Итого / знач.
A6: Месяц № | C6: 1 | D6: 2 | E6: 3 | F6: 4 | G6: 5 | H6: 6 | I6: 7 | J6: 8 | K6: 9 | L6: 10 | M6: 11 | N6: 12 | O6: 13 | P6: 14 | Q6: 15 | R6: 16 | S6: 17 | T6: 18 | U6: 19 | V6: 20 | W6: 21 | X6: 22 | Y6: 23 | Z6: 24 | AA6: 25 | AB6: 26 | AC6: 27 | AD6: 28 | AE6: 29 | AF6: 30 | AG6: 31 | AH6: 32 | AI6: 33 | AJ6: 34 | AK6: 35 | AL6: 36
A7: Месяц | C7: ноя 2026 | D7: дек 2026 | E7: янв 2027 | F7: фев 2027 | G7: мар 2027 | H7: апр 2027 | I7: май 2027 | J7: июн 2027 | K7: июл 2027 | L7: авг 2027 | M7: сен 2027 | N7: окт 2027 | O7: ноя 2027 | P7: дек 2027 | Q7: янв 2028 | R7: фев 2028 | S7: мар 2028 | T7: апр 2028 | U7: май 2028 | V7: июн 2028 | W7: июл 2028 | X7: авг 2028 | Y7: сен 2028 | Z7: окт 2028 | AA7: ноя 2028 | AB7: дек 2028 | AC7: янв 2029 | AD7: фев 2029 | AE7: мар 2029 | AF7: апр 2029 | AG7: май 2029 | AH7: июн 2029 | AI7: июл 2029 | AJ7: авг 2029 | AK7: сен 2029 | AL7: окт 2029
A8: Год проекта | C8: 1 | D8: 1 | E8: 1 | F8: 1 | G8: 1 | H8: 1 | I8: 1 | J8: 1 | K8: 1 | L8: 1 | M8: 1 | N8: 1 | O8: 2 | P8: 2 | Q8: 2 | R8: 2 | S8: 2 | T8: 2 | U8: 2 | V8: 2 | W8: 2 | X8: 2 | Y8: 2 | Z8: 2 | AA8: 3 | AB8: 3 | AC8: 3 | AD8: 3 | AE8: 3 | AF8: 3 | AG8: 3 | AH8: 3 | AI8: 3 | AJ8: 3 | AK8: 3 | AL8: 3
A9: Рынок (1 = MVP вышел) | C9: =IF(C6>='Допущения'!$E$9,1,0) | D9: =IF(D6>='Допущения'!$E$9,1,0) | E9: =IF(E6>='Допущения'!$E$9,1,0) | F9: =IF(F6>='Допущения'!$E$9,1,0) | G9: =IF(G6>='Допущения'!$E$9,1,0) | H9: =IF(H6>='Допущения'!$E$9,1,0) | I9: =IF(I6>='Допущения'!$E$9,1,0) | J9: =IF(J6>='Допущения'!$E$9,1,0) | ... AL9: =IF(AL6>='Допущения'!$E$9,1,0)
A10: ВОРОНКА
A11: Маркетинг, $ | B11: =SUM(C11:AL11) | C11: =IF(C9=1,MAX('Допущения'!$E$83,'Допущения'!$E$84*0)+IF(C6='Допущения'!$E$9,'Допущения'!$E$82,0),'Допущения'!$E$81) | D11: =IF(D9=1,MAX('Допущения'!$E$83,'Допущения'!$E$84*C28)+IF(D6='Допущения'!$E$9,'Допущения'!$E$82,0),'Допущения'!$E$81) | E11: =IF(E9=1,MAX('Допущения'!$E$83,'Допущения'!$E$84*D28)+IF(E6='Допущения'!$E$9,'Допущения'!$E$82,0),'Допущения'!$E$81) | F11: =IF(F9=1,MAX('Допущения'!$E$83,'Допущения'!$E$84*E28)+IF(F6='Допущения'!$E$9,'Допущения'!$E$82,0),'Допущения'!$E$81) | G11: =IF(G9=1,MAX('Допущения'!$E$83,'Допущения'!$E$84*F28)+IF(G6='Допущения'!$E$9,'Допущения'!$E$82,0),'Допущения'!$E$81) | H11: =IF(H9=1,MAX('Допущения'!$E$83,'Допущения'!$E$84*G28)+IF(H6='Допущения'!$E$9,'Допущения'!$E$82,0),'Допущения'!$E$81) | I11: =IF(I9=1,MAX('Допущения'!$E$83,'Допущения'!$E$84*H28)+IF(I6='Допущения'!$E$9,'Допущения'!$E$82,0),'Допущения'!$E$81) | J11: =IF(J9=1,MAX('Допущения'!$E$83,'Допущения'!$E$84*I28)+IF(J6='Допущения'!$E$9,'Допущения'!$E$82,0),'Допущения'!$E$81) | K11: =IF(K9=1,MAX('Допущения'!$E$83,'Допущения'!$E$84*J28)+IF(K6='Допущения'!$E$9,'Допущения'!$E$82,0),'Допущения'!$E$81) | ... AL11: =IF(AL9=1,MAX('Допущения'!$E$83,'Допущения'!$E$84*AK28)+IF(AL6='Допущения'!$E$9,'Допущения'!$E$82,0),'Допущения'!$E$81)
A12: Платные установки | B12: =SUM(C12:AL12) | C12: =IF(C9=1,C11/'Допущения'!$E$60,0) | D12: =IF(D9=1,D11/'Допущения'!$E$60,0) | E12: =IF(E9=1,E11/'Допущения'!$E$60,0) | F12: =IF(F9=1,F11/'Допущения'!$E$60,0) | G12: =IF(G9=1,G11/'Допущения'!$E$60,0) | H12: =IF(H9=1,H11/'Допущения'!$E$60,0) | I12: =IF(I9=1,I11/'Допущения'!$E$60,0) | J12: =IF(J9=1,J11/'Допущения'!$E$60,0) | ... AL12: =IF(AL9=1,AL11/'Допущения'!$E$60,0)
A13: Органические установки | B13: =SUM(C13:AL13) | C13: =IF(C9=1,MIN('Допущения'!$E$63,'Допущения'!$E$61*(1+'Допущения'!$E$62)^(C6-'Допущения'!$E$9)),0) | D13: =IF(D9=1,MIN('Допущения'!$E$63,'Допущения'!$E$61*(1+'Допущения'!$E$62)^(D6-'Допущения'!$E$9)),0) | E13: =IF(E9=1,MIN('Допущения'!$E$63,'Допущения'!$E$61*(1+'Допущения'!$E$62)^(E6-'Допущения'!$E$9)),0) | F13: =IF(F9=1,MIN('Допущения'!$E$63,'Допущения'!$E$61*(1+'Допущения'!$E$62)^(F6-'Допущения'!$E$9)),0) | G13: =IF(G9=1,MIN('Допущения'!$E$63,'Допущения'!$E$61*(1+'Допущения'!$E$62)^(G6-'Допущения'!$E$9)),0) | H13: =IF(H9=1,MIN('Допущения'!$E$63,'Допущения'!$E$61*(1+'Допущения'!$E$62)^(H6-'Допущения'!$E$9)),0) | I13: =IF(I9=1,MIN('Допущения'!$E$63,'Допущения'!$E$61*(1+'Допущения'!$E$62)^(I6-'Допущения'!$E$9)),0) | J13: =IF(J9=1,MIN('Допущения'!$E$63,'Допущения'!$E$61*(1+'Допущения'!$E$62)^(J6-'Допущения'!$E$9)),0) | ... AL13: =IF(AL9=1,MIN('Допущения'!$E$63,'Допущения'!$E$61*(1+'Допущения'!$E$62)^(AL6-'Допущения'!$E$9)),0)
A14: Вирусные установки | B14: =SUM(C14:AL14) | C14: =(C12+C13)*'Допущения'!$E$64 | D14: =(D12+D13)*'Допущения'!$E$64 | E14: =(E12+E13)*'Допущения'!$E$64 | F14: =(F12+F13)*'Допущения'!$E$64 | G14: =(G12+G13)*'Допущения'!$E$64 | H14: =(H12+H13)*'Допущения'!$E$64 | I14: =(I12+I13)*'Допущения'!$E$64 | J14: =(J12+J13)*'Допущения'!$E$64 | ... AL14: =(AL12+AL13)*'Допущения'!$E$64
A15: Всего установок | B15: =SUM(C15:AL15) | C15: =C12+C13+C14 | D15: =D12+D13+D14 | E15: =E12+E13+E14 | F15: =F12+F13+F14 | G15: =G12+G13+G14 | H15: =H12+H13+H14 | I15: =I12+I13+I14 | J15: =J12+J13+J14 | ... AL15: =AL12+AL13+AL14
A16: Новые активированные | B16: =SUM(C16:AL16) | C16: =C15*'Допущения'!$E$65+IF(C6='Допущения'!$E$9,0*'Допущения'!$E$78,0) | D16: =D15*'Допущения'!$E$65+IF(D6='Допущения'!$E$9,C17*'Допущения'!$E$78,0) | E16: =E15*'Допущения'!$E$65+IF(E6='Допущения'!$E$9,D17*'Допущения'!$E$78,0) | F16: =F15*'Допущения'!$E$65+IF(F6='Допущения'!$E$9,E17*'Допущения'!$E$78,0) | G16: =G15*'Допущения'!$E$65+IF(G6='Допущения'!$E$9,F17*'Допущения'!$E$78,0) | H16: =H15*'Допущения'!$E$65+IF(H6='Допущения'!$E$9,G17*'Допущения'!$E$78,0) | I16: =I15*'Допущения'!$E$65+IF(I6='Допущения'!$E$9,H17*'Допущения'!$E$78,0) | J16: =J15*'Допущения'!$E$65+IF(J6='Допущения'!$E$9,I17*'Допущения'!$E$78,0) | K16: =K15*'Допущения'!$E$65+IF(K6='Допущения'!$E$9,J17*'Допущения'!$E$78,0) | ... AL16: =AL15*'Допущения'!$E$65+IF(AL6='Допущения'!$E$9,AK17*'Допущения'!$E$78,0)
A17: Игроки прототипа (до выхода) | C17: =IF(C9=1,0,'Допущения'!$E$72*(1+'Допущения'!$E$73)^(C6-1)) | D17: =IF(D9=1,0,'Допущения'!$E$72*(1+'Допущения'!$E$73)^(D6-1)) | E17: =IF(E9=1,0,'Допущения'!$E$72*(1+'Допущения'!$E$73)^(E6-1)) | F17: =IF(F9=1,0,'Допущения'!$E$72*(1+'Допущения'!$E$73)^(F6-1)) | G17: =IF(G9=1,0,'Допущения'!$E$72*(1+'Допущения'!$E$73)^(G6-1)) | H17: =IF(H9=1,0,'Допущения'!$E$72*(1+'Допущения'!$E$73)^(H6-1)) | I17: =IF(I9=1,0,'Допущения'!$E$72*(1+'Допущения'!$E$73)^(I6-1)) | J17: =IF(J9=1,0,'Допущения'!$E$72*(1+'Допущения'!$E$73)^(J6-1)) | ... AL17: =IF(AL9=1,0,'Допущения'!$E$72*(1+'Допущения'!$E$73)^(AL6-1))
A18: Активные free (на конец мес.) | C18: =IF(C9=1,0*(1-'Допущения'!$E$68)*'Допущения'!$E$66+C16*(1-'Допущения'!$E$67),0) | D18: =IF(D9=1,C18*(1-'Допущения'!$E$68)*'Допущения'!$E$66+D16*(1-'Допущения'!$E$67),0) | E18: =IF(E9=1,D18*(1-'Допущения'!$E$68)*'Допущения'!$E$66+E16*(1-'Допущения'!$E$67),0) | F18: =IF(F9=1,E18*(1-'Допущения'!$E$68)*'Допущения'!$E$66+F16*(1-'Допущения'!$E$67),0) | G18: =IF(G9=1,F18*(1-'Допущения'!$E$68)*'Допущения'!$E$66+G16*(1-'Допущения'!$E$67),0) | H18: =IF(H9=1,G18*(1-'Допущения'!$E$68)*'Допущения'!$E$66+H16*(1-'Допущения'!$E$67),0) | I18: =IF(I9=1,H18*(1-'Допущения'!$E$68)*'Допущения'!$E$66+I16*(1-'Допущения'!$E$67),0) | J18: =IF(J9=1,I18*(1-'Допущения'!$E$68)*'Допущения'!$E$66+J16*(1-'Допущения'!$E$67),0) | K18: =IF(K9=1,J18*(1-'Допущения'!$E$68)*'Допущения'!$E$66+K16*(1-'Допущения'!$E$67),0) | ... AL18: =IF(AL9=1,AK18*(1-'Допущения'!$E$68)*'Допущения'!$E$66+AL16*(1-'Допущения'!$E$67),0)
A19: Новые платящие | B19: =SUM(C19:AL19) | C19: =IF(C9=1,C16*'Допущения'!$E$67+0*'Допущения'!$E$68,0) | D19: =IF(D9=1,D16*'Допущения'!$E$67+C18*'Допущения'!$E$68,0) | E19: =IF(E9=1,E16*'Допущения'!$E$67+D18*'Допущения'!$E$68,0) | F19: =IF(F9=1,F16*'Допущения'!$E$67+E18*'Допущения'!$E$68,0) | G19: =IF(G9=1,G16*'Допущения'!$E$67+F18*'Допущения'!$E$68,0) | H19: =IF(H9=1,H16*'Допущения'!$E$67+G18*'Допущения'!$E$68,0) | I19: =IF(I9=1,I16*'Допущения'!$E$67+H18*'Допущения'!$E$68,0) | J19: =IF(J9=1,J16*'Допущения'!$E$67+I18*'Допущения'!$E$68,0) | K19: =IF(K9=1,K16*'Допущения'!$E$67+J18*'Допущения'!$E$68,0) | ... AL19: =IF(AL9=1,AL16*'Допущения'!$E$67+AK18*'Допущения'!$E$68,0)
A20: Ушедшие платящие | B20: =SUM(C20:AL20) | C20: =0*'Допущения'!$E$69 | D20: =C21*'Допущения'!$E$69 | E20: =D21*'Допущения'!$E$69 | F20: =E21*'Допущения'!$E$69 | G20: =F21*'Допущения'!$E$69 | H20: =G21*'Допущения'!$E$69 | I20: =H21*'Допущения'!$E$69 | J20: =I21*'Допущения'!$E$69 | K20: =J21*'Допущения'!$E$69 | ... AL20: =AK21*'Допущения'!$E$69
A21: Платящие (на конец мес.) | C21: =0+C19-C20 | D21: =C21+D19-D20 | E21: =D21+E19-E20 | F21: =E21+F19-F20 | G21: =F21+G19-G20 | H21: =G21+H19-H20 | I21: =H21+I19-I20 | J21: =I21+J19-J20 | K21: =J21+K19-K20 | ... AL21: =AK21+AL19-AL20
A22: Активные пользователи всего | C22: =C17+C18+C21 | D22: =D17+D18+D21 | E22: =E17+E18+E21 | F22: =F17+F18+F21 | G22: =G17+G18+G21 | H22: =H17+H18+H21 | I22: =I17+I18+I21 | J22: =J17+J18+J21 | ... AL22: =AL17+AL18+AL21
A23: ВЫРУЧКА, $
A24: Оплаты подписок (брутто) | B24: =SUM(C24:AL24) | C24: =C21*'Себестоимость'!$E$12 | D24: =D21*'Себестоимость'!$E$12 | E24: =E21*'Себестоимость'!$E$12 | F24: =F21*'Себестоимость'!$E$12 | G24: =G21*'Себестоимость'!$E$12 | H24: =H21*'Себестоимость'!$E$12 | I24: =I21*'Себестоимость'!$E$12 | J24: =J21*'Себестоимость'!$E$12 | ... AL24: =AL21*'Себестоимость'!$E$12
A25: Комиссии магазинов/Paddle и НДС | B25: =SUM(C25:AL25) | C25: =C24-C26 | D25: =D24-D26 | E25: =E24-E26 | F25: =F24-F26 | G25: =G24-G26 | H25: =H24-H26 | I25: =I24-I26 | J25: =J24-J26 | ... AL25: =AL24-AL26
A26: Чистая выручка подписок | B26: =SUM(C26:AL26) | C26: =C21*'Себестоимость'!$E$13 | D26: =D21*'Себестоимость'!$E$13 | E26: =E21*'Себестоимость'!$E$13 | F26: =F21*'Себестоимость'!$E$13 | G26: =G21*'Себестоимость'!$E$13 | H26: =H21*'Себестоимость'!$E$13 | I26: =I21*'Себестоимость'!$E$13 | J26: =J21*'Себестоимость'!$E$13 | ... AL26: =AL21*'Себестоимость'!$E$13
A27: Донаты (чистые) | B27: =SUM(C27:AL27) | C27: =C17*'Допущения'!$E$75*'Допущения'!$E$76*(1-'Допущения'!$E$77) | D27: =D17*'Допущения'!$E$75*'Допущения'!$E$76*(1-'Допущения'!$E$77) | E27: =E17*'Допущения'!$E$75*'Допущения'!$E$76*(1-'Допущения'!$E$77) | F27: =F17*'Допущения'!$E$75*'Допущения'!$E$76*(1-'Допущения'!$E$77) | G27: =G17*'Допущения'!$E$75*'Допущения'!$E$76*(1-'Допущения'!$E$77) | H27: =H17*'Допущения'!$E$75*'Допущения'!$E$76*(1-'Допущения'!$E$77) | I27: =I17*'Допущения'!$E$75*'Допущения'!$E$76*(1-'Допущения'!$E$77) | J27: =J17*'Допущения'!$E$75*'Допущения'!$E$76*(1-'Допущения'!$E$77) | ... AL27: =AL17*'Допущения'!$E$75*'Допущения'!$E$76*(1-'Допущения'!$E$77)
A28: Итого чистая выручка | B28: =SUM(C28:AL28) | C28: =C26+C27 | D28: =D26+D27 | E28: =E26+E27 | F28: =F26+F27 | G28: =G26+G27 | H28: =H26+H27 | I28: =I26+I27 | J28: =J26+J27 | ... AL28: =AL26+AL27
A29: ПЕРЕМЕННЫЕ ЗАТРАТЫ, $
A30: LLM: платящие | B30: =SUM(C30:AL30) | C30: =C21*'Себестоимость'!$E$14 | D30: =D21*'Себестоимость'!$E$14 | E30: =E21*'Себестоимость'!$E$14 | F30: =F21*'Себестоимость'!$E$14 | G30: =G21*'Себестоимость'!$E$14 | H30: =H21*'Себестоимость'!$E$14 | I30: =I21*'Себестоимость'!$E$14 | J30: =J21*'Себестоимость'!$E$14 | ... AL30: =AL21*'Себестоимость'!$E$14
A31: LLM: free и прототип | B31: =SUM(C31:AL31) | C31: =C18*'Себестоимость'!$E$16+C17*'Допущения'!$E$74*'Себестоимость'!$E$7 | D31: =D18*'Себестоимость'!$E$16+D17*'Допущения'!$E$74*'Себестоимость'!$E$7 | E31: =E18*'Себестоимость'!$E$16+E17*'Допущения'!$E$74*'Себестоимость'!$E$7 | F31: =F18*'Себестоимость'!$E$16+F17*'Допущения'!$E$74*'Себестоимость'!$E$7 | G31: =G18*'Себестоимость'!$E$16+G17*'Допущения'!$E$74*'Себестоимость'!$E$7 | H31: =H18*'Себестоимость'!$E$16+H17*'Допущения'!$E$74*'Себестоимость'!$E$7 | I31: =I18*'Себестоимость'!$E$16+I17*'Допущения'!$E$74*'Себестоимость'!$E$7 | J31: =J18*'Себестоимость'!$E$16+J17*'Допущения'!$E$74*'Себестоимость'!$E$7 | ... AL31: =AL18*'Себестоимость'!$E$16+AL17*'Допущения'!$E$74*'Себестоимость'!$E$7
A32: Проверка возраста | B32: =SUM(C32:AL32) | C32: =C19*'Допущения'!$E$44*'Допущения'!$E$93 | D32: =D19*'Допущения'!$E$44*'Допущения'!$E$93 | E32: =E19*'Допущения'!$E$44*'Допущения'!$E$93 | F32: =F19*'Допущения'!$E$44*'Допущения'!$E$93 | G32: =G19*'Допущения'!$E$44*'Допущения'!$E$93 | H32: =H19*'Допущения'!$E$44*'Допущения'!$E$93 | I32: =I19*'Допущения'!$E$44*'Допущения'!$E$93 | J32: =J19*'Допущения'!$E$44*'Допущения'!$E$93 | ... AL32: =AL19*'Допущения'!$E$44*'Допущения'!$E$93
A33: Инфраструктура (на пользователя) | B33: =SUM(C33:AL33) | C33: =C22*'Допущения'!$E$86 | D33: =D22*'Допущения'!$E$86 | E33: =E22*'Допущения'!$E$86 | F33: =F22*'Допущения'!$E$86 | G33: =G22*'Допущения'!$E$86 | H33: =H22*'Допущения'!$E$86 | I33: =I22*'Допущения'!$E$86 | J33: =J22*'Допущения'!$E$86 | ... AL33: =AL22*'Допущения'!$E$86
A34: Итого переменные | B34: =SUM(C34:AL34) | C34: =SUM(C30:C33) | D34: =SUM(D30:D33) | E34: =SUM(E30:E33) | F34: =SUM(F30:F33) | G34: =SUM(G30:G33) | H34: =SUM(H30:H33) | I34: =SUM(I30:I33) | J34: =SUM(J30:J33) | ... AL34: =SUM(AL30:AL33)
A35: Валовая прибыль | B35: =SUM(C35:AL35) | C35: =C28-C34 | D35: =D28-D34 | E35: =E28-E34 | F35: =F28-F34 | G35: =G28-G34 | H35: =H28-H34 | I35: =I28-I34 | J35: =J28-J34 | ... AL35: =AL28-AL34
A36: Валовая маржа | B36: =IFERROR(B35/B28,0) | C36: =IFERROR(C35/C28,0) | D36: =IFERROR(D35/D28,0) | E36: =IFERROR(E35/E28,0) | F36: =IFERROR(F35/F28,0) | G36: =IFERROR(G35/G28,0) | H36: =IFERROR(H35/H28,0) | I36: =IFERROR(I35/I28,0) | ... AL36: =IFERROR(AL35/AL28,0)
A37: ПОСТОЯННЫЕ ЗАТРАТЫ И МАРКЕТИНГ, $
A38: Инфраструктура (база) | B38: =SUM(C38:AL38) | C38: ='Допущения'!$E$85 | D38: ='Допущения'!$E$85 | E38: ='Допущения'!$E$85 | F38: ='Допущения'!$E$85 | G38: ='Допущения'!$E$85 | H38: ='Допущения'!$E$85 | I38: ='Допущения'!$E$85 | J38: ='Допущения'!$E$85 | ... AL38: ='Допущения'!$E$85
A39: SaaS-инструменты | B39: =SUM(C39:AL39) | C39: ='Допущения'!$E$87 | D39: ='Допущения'!$E$87 | E39: ='Допущения'!$E$87 | F39: ='Допущения'!$E$87 | G39: ='Допущения'!$E$87 | H39: ='Допущения'!$E$87 | I39: ='Допущения'!$E$87 | J39: ='Допущения'!$E$87 | ... AL39: ='Допущения'!$E$87
A40: Бухгалтерия | B40: =SUM(C40:AL40) | C40: =IF(C6>='Допущения'!$E$10,'Допущения'!$E$88,0) | D40: =IF(D6>='Допущения'!$E$10,'Допущения'!$E$88,0) | E40: =IF(E6>='Допущения'!$E$10,'Допущения'!$E$88,0) | F40: =IF(F6>='Допущения'!$E$10,'Допущения'!$E$88,0) | G40: =IF(G6>='Допущения'!$E$10,'Допущения'!$E$88,0) | H40: =IF(H6>='Допущения'!$E$10,'Допущения'!$E$88,0) | I40: =IF(I6>='Допущения'!$E$10,'Допущения'!$E$88,0) | J40: =IF(J6>='Допущения'!$E$10,'Допущения'!$E$88,0) | ... AL40: =IF(AL6>='Допущения'!$E$10,'Допущения'!$E$88,0)
A41: Юр. сопровождение | B41: =SUM(C41:AL41) | C41: =IF(C9=1,'Допущения'!$E$89,0) | D41: =IF(D9=1,'Допущения'!$E$89,0) | E41: =IF(E9=1,'Допущения'!$E$89,0) | F41: =IF(F9=1,'Допущения'!$E$89,0) | G41: =IF(G9=1,'Допущения'!$E$89,0) | H41: =IF(H9=1,'Допущения'!$E$89,0) | I41: =IF(I9=1,'Допущения'!$E$89,0) | J41: =IF(J9=1,'Допущения'!$E$89,0) | ... AL41: =IF(AL9=1,'Допущения'!$E$89,0)
A42: Магазины приложений | B42: =SUM(C42:AL42) | C42: =IF(C6='Допущения'!$E$9-1,'Допущения'!$E$90+'Допущения'!$E$91,0)+IF(AND(C6>'Допущения'!$E$9-1,MOD(C6-('Допущения'!$E$9-1),12)=0),'Допущения'!$E$90,0) | D42: =IF(D6='Допущения'!$E$9-1,'Допущения'!$E$90+'Допущения'!$E$91,0)+IF(AND(D6>'Допущения'!$E$9-1,MOD(D6-('Допущения'!$E$9-1),12)=0),'Допущения'!$E$90,0) | E42: =IF(E6='Допущения'!$E$9-1,'Допущения'!$E$90+'Допущения'!$E$91,0)+IF(AND(E6>'Допущения'!$E$9-1,MOD(E6-('Допущения'!$E$9-1),12)=0),'Допущения'!$E$90,0) | F42: =IF(F6='Допущения'!$E$9-1,'Допущения'!$E$90+'Допущения'!$E$91,0)+IF(AND(F6>'Допущения'!$E$9-1,MOD(F6-('Допущения'!$E$9-1),12)=0),'Допущения'!$E$90,0) | G42: =IF(G6='Допущения'!$E$9-1,'Допущения'!$E$90+'Допущения'!$E$91,0)+IF(AND(G6>'Допущения'!$E$9-1,MOD(G6-('Допущения'!$E$9-1),12)=0),'Допущения'!$E$90,0) | H42: =IF(H6='Допущения'!$E$9-1,'Допущения'!$E$90+'Допущения'!$E$91,0)+IF(AND(H6>'Допущения'!$E$9-1,MOD(H6-('Допущения'!$E$9-1),12)=0),'Допущения'!$E$90,0) | I42: =IF(I6='Допущения'!$E$9-1,'Допущения'!$E$90+'Допущения'!$E$91,0)+IF(AND(I6>'Допущения'!$E$9-1,MOD(I6-('Допущения'!$E$9-1),12)=0),'Допущения'!$E$90,0) | J42: =IF(J6='Допущения'!$E$9-1,'Допущения'!$E$90+'Допущения'!$E$91,0)+IF(AND(J6>'Допущения'!$E$9-1,MOD(J6-('Допущения'!$E$9-1),12)=0),'Допущения'!$E$90,0) | ... AL42: =IF(AL6='Допущения'!$E$9-1,'Допущения'!$E$90+'Допущения'!$E$91,0)+IF(AND(AL6>'Допущения'!$E$9-1,MOD(AL6-('Допущения'!$E$9-1),12)=0),'Допущения'!$E$90,0)
A43: Разовые стартовые (лист «Старт») | B43: =SUM(C43:AL43) | C43: =SUMIF('Старт'!$C$5:$C$17,C6,'Старт'!$D$5:$D$17) | D43: =SUMIF('Старт'!$C$5:$C$17,D6,'Старт'!$D$5:$D$17) | E43: =SUMIF('Старт'!$C$5:$C$17,E6,'Старт'!$D$5:$D$17) | F43: =SUMIF('Старт'!$C$5:$C$17,F6,'Старт'!$D$5:$D$17) | G43: =SUMIF('Старт'!$C$5:$C$17,G6,'Старт'!$D$5:$D$17) | H43: =SUMIF('Старт'!$C$5:$C$17,H6,'Старт'!$D$5:$D$17) | I43: =SUMIF('Старт'!$C$5:$C$17,I6,'Старт'!$D$5:$D$17) | J43: =SUMIF('Старт'!$C$5:$C$17,J6,'Старт'!$D$5:$D$17) | ... AL43: =SUMIF('Старт'!$C$5:$C$17,AL6,'Старт'!$D$5:$D$17)
A44: Контент / SMM | B44: =SUM(C44:AL44) | C44: =IF(C6>'Допущения'!$E$9,'Допущения'!$E$92,0) | D44: =IF(D6>'Допущения'!$E$9,'Допущения'!$E$92,0) | E44: =IF(E6>'Допущения'!$E$9,'Допущения'!$E$92,0) | F44: =IF(F6>'Допущения'!$E$9,'Допущения'!$E$92,0) | G44: =IF(G6>'Допущения'!$E$9,'Допущения'!$E$92,0) | H44: =IF(H6>'Допущения'!$E$9,'Допущения'!$E$92,0) | I44: =IF(I6>'Допущения'!$E$9,'Допущения'!$E$92,0) | J44: =IF(J6>'Допущения'!$E$9,'Допущения'!$E$92,0) | ... AL44: =IF(AL6>'Допущения'!$E$9,'Допущения'!$E$92,0)
A45: Маркетинг | B45: =SUM(C45:AL45) | C45: =C11 | D45: =D11 | E45: =E11 | F45: =F11 | G45: =G11 | H45: =H11 | I45: =I11 | J45: =J11 | ... AL45: =AL11
A46: Выплаты основателям | B46: =SUM(C46:AL46) | C46: =IF(C6>='Допущения'!$E$94,MIN('Допущения'!$E$95,MAX(0,'Допущения'!$E$96*(0+0))),0) | D46: =IF(D6>='Допущения'!$E$94,MIN('Допущения'!$E$95,MAX(0,'Допущения'!$E$96*(C48+C46))),0) | E46: =IF(E6>='Допущения'!$E$94,MIN('Допущения'!$E$95,MAX(0,'Допущения'!$E$96*(D48+D46))),0) | F46: =IF(F6>='Допущения'!$E$94,MIN('Допущения'!$E$95,MAX(0,'Допущения'!$E$96*(E48+E46))),0) | G46: =IF(G6>='Допущения'!$E$94,MIN('Допущения'!$E$95,MAX(0,'Допущения'!$E$96*(F48+F46))),0) | H46: =IF(H6>='Допущения'!$E$94,MIN('Допущения'!$E$95,MAX(0,'Допущения'!$E$96*(G48+G46))),0) | I46: =IF(I6>='Допущения'!$E$94,MIN('Допущения'!$E$95,MAX(0,'Допущения'!$E$96*(H48+H46))),0) | J46: =IF(J6>='Допущения'!$E$94,MIN('Допущения'!$E$95,MAX(0,'Допущения'!$E$96*(I48+I46))),0) | K46: =IF(K6>='Допущения'!$E$94,MIN('Допущения'!$E$95,MAX(0,'Допущения'!$E$96*(J48+J46))),0) | ... AL46: =IF(AL6>='Допущения'!$E$94,MIN('Допущения'!$E$95,MAX(0,'Допущения'!$E$96*(AK48+AK46))),0)
A47: Итого постоянные + маркетинг | B47: =SUM(C47:AL47) | C47: =SUM(C38:C46) | D47: =SUM(D38:D46) | E47: =SUM(E38:E46) | F47: =SUM(F38:F46) | G47: =SUM(G38:G46) | H47: =SUM(H38:H46) | I47: =SUM(I38:I46) | J47: =SUM(J38:J46) | ... AL47: =SUM(AL38:AL46)
A48: EBITDA | B48: =SUM(C48:AL48) | C48: =C35-C47 | D48: =D35-D47 | E48: =E35-E47 | F48: =F35-F47 | G48: =G35-G47 | H48: =H35-H47 | I48: =I35-I47 | J48: =J35-J47 | ... AL48: =AL35-AL47
A49: Налог на прибыль | B49: =SUM(C49:AL49) | C49: =MAX(0,C48)*'Допущения'!$E$57 | D49: =MAX(0,D48)*'Допущения'!$E$57 | E49: =MAX(0,E48)*'Допущения'!$E$57 | F49: =MAX(0,F48)*'Допущения'!$E$57 | G49: =MAX(0,G48)*'Допущения'!$E$57 | H49: =MAX(0,H48)*'Допущения'!$E$57 | I49: =MAX(0,I48)*'Допущения'!$E$57 | J49: =MAX(0,J48)*'Допущения'!$E$57 | ... AL49: =MAX(0,AL48)*'Допущения'!$E$57
A50: Операционный денежный поток | B50: =SUM(C50:AL50) | C50: =C48-C49 | D50: =D48-D49 | E50: =E48-E49 | F50: =F48-F49 | G50: =G48-G49 | H50: =H48-H49 | I50: =I48-I49 | J50: =J48-J49 | ... AL50: =AL48-AL49
A51: Накопленный операционный поток | B51: =MIN(C51:AL51) | C51: =0+C50 | D51: =C51+D50 | E51: =D51+E50 | F51: =E51+F50 | G51: =F51+G50 | H51: =G51+H50 | I51: =H51+I50 | J51: =I51+J50 | K51: =J51+K50 | ... AL51: =AK51+AL50
A52: ВЛОЖЕНИЯ И КАССА, $
A53: Вложения партнёра (выбранный вариант) | B53: =SUM(C53:AL53) | C53: =(IF(C6=1,INDEX('Допущения'!$C$104:$C$106,'Допущения'!$D$103)*'Допущения'!$E$107,0)+IF(C6='Допущения'!$E$9,INDEX('Допущения'!$C$104:$C$106,'Допущения'!$D$103)*(1-'Допущения'!$E$107),0))/'Допущения'!$E$7 | D53: =(IF(D6=1,INDEX('Допущения'!$C$104:$C$106,'Допущения'!$D$103)*'Допущения'!$E$107,0)+IF(D6='Допущения'!$E$9,INDEX('Допущения'!$C$104:$C$106,'Допущения'!$D$103)*(1-'Допущения'!$E$107),0))/'Допущения'!$E$7 | E53: =(IF(E6=1,INDEX('Допущения'!$C$104:$C$106,'Допущения'!$D$103)*'Допущения'!$E$107,0)+IF(E6='Допущения'!$E$9,INDEX('Допущения'!$C$104:$C$106,'Допущения'!$D$103)*(1-'Допущения'!$E$107),0))/'Допущения'!$E$7 | F53: =(IF(F6=1,INDEX('Допущения'!$C$104:$C$106,'Допущения'!$D$103)*'Допущения'!$E$107,0)+IF(F6='Допущения'!$E$9,INDEX('Допущения'!$C$104:$C$106,'Допущения'!$D$103)*(1-'Допущения'!$E$107),0))/'Допущения'!$E$7 | G53: =(IF(G6=1,INDEX('Допущения'!$C$104:$C$106,'Допущения'!$D$103)*'Допущения'!$E$107,0)+IF(G6='Допущения'!$E$9,INDEX('Допущения'!$C$104:$C$106,'Допущения'!$D$103)*(1-'Допущения'!$E$107),0))/'Допущения'!$E$7 | H53: =(IF(H6=1,INDEX('Допущения'!$C$104:$C$106,'Допущения'!$D$103)*'Допущения'!$E$107,0)+IF(H6='Допущения'!$E$9,INDEX('Допущения'!$C$104:$C$106,'Допущения'!$D$103)*(1-'Допущения'!$E$107),0))/'Допущения'!$E$7 | I53: =(IF(I6=1,INDEX('Допущения'!$C$104:$C$106,'Допущения'!$D$103)*'Допущения'!$E$107,0)+IF(I6='Допущения'!$E$9,INDEX('Допущения'!$C$104:$C$106,'Допущения'!$D$103)*(1-'Допущения'!$E$107),0))/'Допущения'!$E$7 | J53: =(IF(J6=1,INDEX('Допущения'!$C$104:$C$106,'Допущения'!$D$103)*'Допущения'!$E$107,0)+IF(J6='Допущения'!$E$9,INDEX('Допущения'!$C$104:$C$106,'Допущения'!$D$103)*(1-'Допущения'!$E$107),0))/'Допущения'!$E$7 | ... AL53: =(IF(AL6=1,INDEX('Допущения'!$C$104:$C$106,'Допущения'!$D$103)*'Допущения'!$E$107,0)+IF(AL6='Допущения'!$E$9,INDEX('Допущения'!$C$104:$C$106,'Допущения'!$D$103)*(1-'Допущения'!$E$107),0))/'Допущения'!$E$7
A54: Мои вложения (выбранный вариант) | B54: =SUM(C54:AL54) | C54: =(IF(C6=1,MIN(INDEX('Допущения'!$D$104:$D$106,'Допущения'!$D$103),'Допущения'!$E$108),0)+IF(AND(C6>=2,C6<=4),MAX(0,INDEX('Допущения'!$D$104:$D$106,'Допущения'!$D$103)-'Допущения'!$E$108)/3,0))/'Допущения'!$E$7 | D54: =(IF(D6=1,MIN(INDEX('Допущения'!$D$104:$D$106,'Допущения'!$D$103),'Допущения'!$E$108),0)+IF(AND(D6>=2,D6<=4),MAX(0,INDEX('Допущения'!$D$104:$D$106,'Допущения'!$D$103)-'Допущения'!$E$108)/3,0))/'Допущения'!$E$7 | E54: =(IF(E6=1,MIN(INDEX('Допущения'!$D$104:$D$106,'Допущения'!$D$103),'Допущения'!$E$108),0)+IF(AND(E6>=2,E6<=4),MAX(0,INDEX('Допущения'!$D$104:$D$106,'Допущения'!$D$103)-'Допущения'!$E$108)/3,0))/'Допущения'!$E$7 | F54: =(IF(F6=1,MIN(INDEX('Допущения'!$D$104:$D$106,'Допущения'!$D$103),'Допущения'!$E$108),0)+IF(AND(F6>=2,F6<=4),MAX(0,INDEX('Допущения'!$D$104:$D$106,'Допущения'!$D$103)-'Допущения'!$E$108)/3,0))/'Допущения'!$E$7 | G54: =(IF(G6=1,MIN(INDEX('Допущения'!$D$104:$D$106,'Допущения'!$D$103),'Допущения'!$E$108),0)+IF(AND(G6>=2,G6<=4),MAX(0,INDEX('Допущения'!$D$104:$D$106,'Допущения'!$D$103)-'Допущения'!$E$108)/3,0))/'Допущения'!$E$7 | H54: =(IF(H6=1,MIN(INDEX('Допущения'!$D$104:$D$106,'Допущения'!$D$103),'Допущения'!$E$108),0)+IF(AND(H6>=2,H6<=4),MAX(0,INDEX('Допущения'!$D$104:$D$106,'Допущения'!$D$103)-'Допущения'!$E$108)/3,0))/'Допущения'!$E$7 | I54: =(IF(I6=1,MIN(INDEX('Допущения'!$D$104:$D$106,'Допущения'!$D$103),'Допущения'!$E$108),0)+IF(AND(I6>=2,I6<=4),MAX(0,INDEX('Допущения'!$D$104:$D$106,'Допущения'!$D$103)-'Допущения'!$E$108)/3,0))/'Допущения'!$E$7 | J54: =(IF(J6=1,MIN(INDEX('Допущения'!$D$104:$D$106,'Допущения'!$D$103),'Допущения'!$E$108),0)+IF(AND(J6>=2,J6<=4),MAX(0,INDEX('Допущения'!$D$104:$D$106,'Допущения'!$D$103)-'Допущения'!$E$108)/3,0))/'Допущения'!$E$7 | ... AL54: =(IF(AL6=1,MIN(INDEX('Допущения'!$D$104:$D$106,'Допущения'!$D$103),'Допущения'!$E$108),0)+IF(AND(AL6>=2,AL6<=4),MAX(0,INDEX('Допущения'!$D$104:$D$106,'Допущения'!$D$103)-'Допущения'!$E$108)/3,0))/'Допущения'!$E$7
A55: Касса на конец месяца | B55: =MIN(C55:AL55) | C55: =0+C50+C53+C54 | D55: =C55+D50+D53+D54 | E55: =D55+E50+E53+E54 | F55: =E55+F50+F53+F54 | G55: =F55+G50+G53+G54 | H55: =G55+H50+H53+H54 | I55: =H55+I50+I53+I54 | J55: =I55+J50+J53+J54 | K55: =J55+K50+K53+K54 | ... AL55: =AK55+AL50+AL53+AL54
A56: Касса при варианте 1 «Минимум» | B56: =MIN(C56:AL56) | C56: =C51+('Допущения'!$C$104*'Допущения'!$E$107+IF(C6>='Допущения'!$E$9,'Допущения'!$C$104*(1-'Допущения'!$E$107),0)+MIN('Допущения'!$D$104,'Допущения'!$E$108)+MAX(0,'Допущения'!$D$104-'Допущения'!$E$108)*MIN(MAX(C6-1,0),3)/3)/'Допущения'!$E$7 | D56: =D51+('Допущения'!$C$104*'Допущения'!$E$107+IF(D6>='Допущения'!$E$9,'Допущения'!$C$104*(1-'Допущения'!$E$107),0)+MIN('Допущения'!$D$104,'Допущения'!$E$108)+MAX(0,'Допущения'!$D$104-'Допущения'!$E$108)*MIN(MAX(D6-1,0),3)/3)/'Допущения'!$E$7 | E56: =E51+('Допущения'!$C$104*'Допущения'!$E$107+IF(E6>='Допущения'!$E$9,'Допущения'!$C$104*(1-'Допущения'!$E$107),0)+MIN('Допущения'!$D$104,'Допущения'!$E$108)+MAX(0,'Допущения'!$D$104-'Допущения'!$E$108)*MIN(MAX(E6-1,0),3)/3)/'Допущения'!$E$7 | F56: =F51+('Допущения'!$C$104*'Допущения'!$E$107+IF(F6>='Допущения'!$E$9,'Допущения'!$C$104*(1-'Допущения'!$E$107),0)+MIN('Допущения'!$D$104,'Допущения'!$E$108)+MAX(0,'Допущения'!$D$104-'Допущения'!$E$108)*MIN(MAX(F6-1,0),3)/3)/'Допущения'!$E$7 | G56: =G51+('Допущения'!$C$104*'Допущения'!$E$107+IF(G6>='Допущения'!$E$9,'Допущения'!$C$104*(1-'Допущения'!$E$107),0)+MIN('Допущения'!$D$104,'Допущения'!$E$108)+MAX(0,'Допущения'!$D$104-'Допущения'!$E$108)*MIN(MAX(G6-1,0),3)/3)/'Допущения'!$E$7 | H56: =H51+('Допущения'!$C$104*'Допущения'!$E$107+IF(H6>='Допущения'!$E$9,'Допущения'!$C$104*(1-'Допущения'!$E$107),0)+MIN('Допущения'!$D$104,'Допущения'!$E$108)+MAX(0,'Допущения'!$D$104-'Допущения'!$E$108)*MIN(MAX(H6-1,0),3)/3)/'Допущения'!$E$7 | I56: =I51+('Допущения'!$C$104*'Допущения'!$E$107+IF(I6>='Допущения'!$E$9,'Допущения'!$C$104*(1-'Допущения'!$E$107),0)+MIN('Допущения'!$D$104,'Допущения'!$E$108)+MAX(0,'Допущения'!$D$104-'Допущения'!$E$108)*MIN(MAX(I6-1,0),3)/3)/'Допущения'!$E$7 | J56: =J51+('Допущения'!$C$104*'Допущения'!$E$107+IF(J6>='Допущения'!$E$9,'Допущения'!$C$104*(1-'Допущения'!$E$107),0)+MIN('Допущения'!$D$104,'Допущения'!$E$108)+MAX(0,'Допущения'!$D$104-'Допущения'!$E$108)*MIN(MAX(J6-1,0),3)/3)/'Допущения'!$E$7 | ... AL56: =AL51+('Допущения'!$C$104*'Допущения'!$E$107+IF(AL6>='Допущения'!$E$9,'Допущения'!$C$104*(1-'Допущения'!$E$107),0)+MIN('Допущения'!$D$104,'Допущения'!$E$108)+MAX(0,'Допущения'!$D$104-'Допущения'!$E$108)*MIN(MAX(AL6-1,0),3)/3)/'Допущения'!$E$7
A57: Касса при варианте 2 «Средний» | B57: =MIN(C57:AL57) | C57: =C51+('Допущения'!$C$105*'Допущения'!$E$107+IF(C6>='Допущения'!$E$9,'Допущения'!$C$105*(1-'Допущения'!$E$107),0)+MIN('Допущения'!$D$105,'Допущения'!$E$108)+MAX(0,'Допущения'!$D$105-'Допущения'!$E$108)*MIN(MAX(C6-1,0),3)/3)/'Допущения'!$E$7 | D57: =D51+('Допущения'!$C$105*'Допущения'!$E$107+IF(D6>='Допущения'!$E$9,'Допущения'!$C$105*(1-'Допущения'!$E$107),0)+MIN('Допущения'!$D$105,'Допущения'!$E$108)+MAX(0,'Допущения'!$D$105-'Допущения'!$E$108)*MIN(MAX(D6-1,0),3)/3)/'Допущения'!$E$7 | E57: =E51+('Допущения'!$C$105*'Допущения'!$E$107+IF(E6>='Допущения'!$E$9,'Допущения'!$C$105*(1-'Допущения'!$E$107),0)+MIN('Допущения'!$D$105,'Допущения'!$E$108)+MAX(0,'Допущения'!$D$105-'Допущения'!$E$108)*MIN(MAX(E6-1,0),3)/3)/'Допущения'!$E$7 | F57: =F51+('Допущения'!$C$105*'Допущения'!$E$107+IF(F6>='Допущения'!$E$9,'Допущения'!$C$105*(1-'Допущения'!$E$107),0)+MIN('Допущения'!$D$105,'Допущения'!$E$108)+MAX(0,'Допущения'!$D$105-'Допущения'!$E$108)*MIN(MAX(F6-1,0),3)/3)/'Допущения'!$E$7 | G57: =G51+('Допущения'!$C$105*'Допущения'!$E$107+IF(G6>='Допущения'!$E$9,'Допущения'!$C$105*(1-'Допущения'!$E$107),0)+MIN('Допущения'!$D$105,'Допущения'!$E$108)+MAX(0,'Допущения'!$D$105-'Допущения'!$E$108)*MIN(MAX(G6-1,0),3)/3)/'Допущения'!$E$7 | H57: =H51+('Допущения'!$C$105*'Допущения'!$E$107+IF(H6>='Допущения'!$E$9,'Допущения'!$C$105*(1-'Допущения'!$E$107),0)+MIN('Допущения'!$D$105,'Допущения'!$E$108)+MAX(0,'Допущения'!$D$105-'Допущения'!$E$108)*MIN(MAX(H6-1,0),3)/3)/'Допущения'!$E$7 | I57: =I51+('Допущения'!$C$105*'Допущения'!$E$107+IF(I6>='Допущения'!$E$9,'Допущения'!$C$105*(1-'Допущения'!$E$107),0)+MIN('Допущения'!$D$105,'Допущения'!$E$108)+MAX(0,'Допущения'!$D$105-'Допущения'!$E$108)*MIN(MAX(I6-1,0),3)/3)/'Допущения'!$E$7 | J57: =J51+('Допущения'!$C$105*'Допущения'!$E$107+IF(J6>='Допущения'!$E$9,'Допущения'!$C$105*(1-'Допущения'!$E$107),0)+MIN('Допущения'!$D$105,'Допущения'!$E$108)+MAX(0,'Допущения'!$D$105-'Допущения'!$E$108)*MIN(MAX(J6-1,0),3)/3)/'Допущения'!$E$7 | ... AL57: =AL51+('Допущения'!$C$105*'Допущения'!$E$107+IF(AL6>='Допущения'!$E$9,'Допущения'!$C$105*(1-'Допущения'!$E$107),0)+MIN('Допущения'!$D$105,'Допущения'!$E$108)+MAX(0,'Допущения'!$D$105-'Допущения'!$E$108)*MIN(MAX(AL6-1,0),3)/3)/'Допущения'!$E$7
A58: Касса при варианте 3 «Максимум» | B58: =MIN(C58:AL58) | C58: =C51+('Допущения'!$C$106*'Допущения'!$E$107+IF(C6>='Допущения'!$E$9,'Допущения'!$C$106*(1-'Допущения'!$E$107),0)+MIN('Допущения'!$D$106,'Допущения'!$E$108)+MAX(0,'Допущения'!$D$106-'Допущения'!$E$108)*MIN(MAX(C6-1,0),3)/3)/'Допущения'!$E$7 | D58: =D51+('Допущения'!$C$106*'Допущения'!$E$107+IF(D6>='Допущения'!$E$9,'Допущения'!$C$106*(1-'Допущения'!$E$107),0)+MIN('Допущения'!$D$106,'Допущения'!$E$108)+MAX(0,'Допущения'!$D$106-'Допущения'!$E$108)*MIN(MAX(D6-1,0),3)/3)/'Допущения'!$E$7 | E58: =E51+('Допущения'!$C$106*'Допущения'!$E$107+IF(E6>='Допущения'!$E$9,'Допущения'!$C$106*(1-'Допущения'!$E$107),0)+MIN('Допущения'!$D$106,'Допущения'!$E$108)+MAX(0,'Допущения'!$D$106-'Допущения'!$E$108)*MIN(MAX(E6-1,0),3)/3)/'Допущения'!$E$7 | F58: =F51+('Допущения'!$C$106*'Допущения'!$E$107+IF(F6>='Допущения'!$E$9,'Допущения'!$C$106*(1-'Допущения'!$E$107),0)+MIN('Допущения'!$D$106,'Допущения'!$E$108)+MAX(0,'Допущения'!$D$106-'Допущения'!$E$108)*MIN(MAX(F6-1,0),3)/3)/'Допущения'!$E$7 | G58: =G51+('Допущения'!$C$106*'Допущения'!$E$107+IF(G6>='Допущения'!$E$9,'Допущения'!$C$106*(1-'Допущения'!$E$107),0)+MIN('Допущения'!$D$106,'Допущения'!$E$108)+MAX(0,'Допущения'!$D$106-'Допущения'!$E$108)*MIN(MAX(G6-1,0),3)/3)/'Допущения'!$E$7 | H58: =H51+('Допущения'!$C$106*'Допущения'!$E$107+IF(H6>='Допущения'!$E$9,'Допущения'!$C$106*(1-'Допущения'!$E$107),0)+MIN('Допущения'!$D$106,'Допущения'!$E$108)+MAX(0,'Допущения'!$D$106-'Допущения'!$E$108)*MIN(MAX(H6-1,0),3)/3)/'Допущения'!$E$7 | I58: =I51+('Допущения'!$C$106*'Допущения'!$E$107+IF(I6>='Допущения'!$E$9,'Допущения'!$C$106*(1-'Допущения'!$E$107),0)+MIN('Допущения'!$D$106,'Допущения'!$E$108)+MAX(0,'Допущения'!$D$106-'Допущения'!$E$108)*MIN(MAX(I6-1,0),3)/3)/'Допущения'!$E$7 | J58: =J51+('Допущения'!$C$106*'Допущения'!$E$107+IF(J6>='Допущения'!$E$9,'Допущения'!$C$106*(1-'Допущения'!$E$107),0)+MIN('Допущения'!$D$106,'Допущения'!$E$108)+MAX(0,'Допущения'!$D$106-'Допущения'!$E$108)*MIN(MAX(J6-1,0),3)/3)/'Допущения'!$E$7 | ... AL58: =AL51+('Допущения'!$C$106*'Допущения'!$E$107+IF(AL6>='Допущения'!$E$9,'Допущения'!$C$106*(1-'Допущения'!$E$107),0)+MIN('Допущения'!$D$106,'Допущения'!$E$108)+MAX(0,'Допущения'!$D$106-'Допущения'!$E$108)*MIN(MAX(AL6-1,0),3)/3)/'Допущения'!$E$7
A59: МЕТРИКИ
A60: MRR (брутто), $ | C60: =C24 | D60: =D24 | E60: =E24 | F60: =F24 | G60: =G24 | H60: =H24 | I60: =I24 | J60: =J24 | ... AL60: =AL24
A61: CAC на нового платящего, $ | B61: =IFERROR(B11/B19,0) | C61: =IFERROR(IF(C9=1,C11/C19,0),0) | D61: =IFERROR(IF(D9=1,D11/D19,0),0) | E61: =IFERROR(IF(E9=1,E11/E19,0),0) | F61: =IFERROR(IF(F9=1,F11/F19,0),0) | G61: =IFERROR(IF(G9=1,G11/G19,0),0) | H61: =IFERROR(IF(H9=1,H11/H19,0),0) | I61: =IFERROR(IF(I9=1,I11/I19,0),0) | J61: =IFERROR(IF(J9=1,J11/J19,0),0) | ... AL61: =IFERROR(IF(AL9=1,AL11/AL19,0),0)
A62: Флаг: EBITDA ≥ 0 после выхода | C62: =IF(AND(C9=1,C48>=0),1,0) | D62: =IF(AND(D9=1,D48>=0),1,0) | E62: =IF(AND(E9=1,E48>=0),1,0) | F62: =IF(AND(F9=1,F48>=0),1,0) | G62: =IF(AND(G9=1,G48>=0),1,0) | H62: =IF(AND(H9=1,H48>=0),1,0) | I62: =IF(AND(I9=1,I48>=0),1,0) | J62: =IF(AND(J9=1,J48>=0),1,0) | ... AL62: =IF(AND(AL9=1,AL48>=0),1,0)
A63: Флаг: EBITDA ≥ 0 в этом и всех следующих месяцах | C63: =IF(AND(C9=1,MIN(C48:$AL$48)>=0),1,0) | D63: =IF(AND(D9=1,MIN(D48:$AL$48)>=0),1,0) | E63: =IF(AND(E9=1,MIN(E48:$AL$48)>=0),1,0) | F63: =IF(AND(F9=1,MIN(F48:$AL$48)>=0),1,0) | G63: =IF(AND(G9=1,MIN(G48:$AL$48)>=0),1,0) | H63: =IF(AND(H9=1,MIN(H48:$AL$48)>=0),1,0) | I63: =IF(AND(I9=1,MIN(I48:$AL$48)>=0),1,0) | J63: =IF(AND(J9=1,MIN(J48:$AL$48)>=0),1,0) | ... AL63: =IF(AND(AL9=1,MIN(AL48:$AL$48)>=0),1,0)
A64: Флаг: накопленный поток ≥ 0 | C64: =IF(C51>=0,1,0) | D64: =IF(D51>=0,1,0) | E64: =IF(E51>=0,1,0) | F64: =IF(F51>=0,1,0) | G64: =IF(G51>=0,1,0) | H64: =IF(H51>=0,1,0) | I64: =IF(I51>=0,1,0) | J64: =IF(J51>=0,1,0) | ... AL64: =IF(AL51>=0,1,0)
A65: Поток для IRR (с терминальной стоимостью) | C65: =C50+0 | D65: =D50+0 | E65: =E50+0 | F65: =F50+0 | G65: =G50+0 | H65: =H50+0 | I65: =I50+0 | J65: =J50+0 | ... AK65: =AK50+0 | AL65: =AL50+AL60*12*'Допущения'!$E$100
A67: СВОДКА
A68: Первый месяц с EBITDA ≥ 0 (№) | B68: =IFERROR(MATCH(1,$C$62:$AL$62,0),"не достигнут")
A69: Устойчивая безубыточность: EBITDA ≥ 0 и дальше (№ мес.) | B69: =IFERROR(MATCH(1,$C$63:$AL$63,0),"не достигнута")
A70: Устойчивая безубыточность (дата) | B70: =IFERROR(INDEX($C$7:$AL$7,MATCH(1,$C$63:$AL$63,0)),"—")
A71: Окупаемость: накопленный поток ≥ 0 (№ мес.) | B71: =IFERROR(MATCH(1,$C$64:$AL$64,0),"> 36 мес.")
A72: Пиковая потребность в финансировании, $ | B72: =-MIN($C$51:$AL$51)
A73: То же, ₽ | B73: =-MIN($C$51:$AL$51)*'Допущения'!$E$7
A74: Чистая выручка, год 1, $ | B74: =SUMIF($C$8:$AL$8,1,$C$28:$AL$28)
A75: Чистая выручка, год 2, $ | B75: =SUMIF($C$8:$AL$8,2,$C$28:$AL$28)
A76: Чистая выручка, год 3, $ | B76: =SUMIF($C$8:$AL$8,3,$C$28:$AL$28)
A77: EBITDA, год 1, $ | B77: =SUMIF($C$8:$AL$8,1,$C$48:$AL$48)
A78: EBITDA, год 2, $ | B78: =SUMIF($C$8:$AL$8,2,$C$48:$AL$48)
A79: EBITDA, год 3, $ | B79: =SUMIF($C$8:$AL$8,3,$C$48:$AL$48)
A80: Платящие, мес. 12 | B80: =$N$21
A81: Платящие, мес. 24 | B81: =$Z$21
A82: Платящие, мес. 36 | B82: =$AL$21
A83: Активные, мес. 12 | B83: =$N$22
A84: Активные, мес. 36 | B84: =$AL$22
A85: MRR, мес. 12, $ | B85: =$N$60
A86: MRR, мес. 24, $ | B86: =$Z$60
A87: MRR, мес. 36, $ | B87: =$AL$60
A88: ARR, мес. 36, $ | B88: =$AL$60*12
A89: CAC средний (маркетинг / новые платящие после выхода), $ | B89: =IFERROR(SUMIF($C$9:$AL$9,1,$C$11:$AL$11)/SUM($C$19:$AL$19),0)
A90: LTV платящего (чистая выручка × маржа / отток), $ | B90: ='Себестоимость'!$E$13*'Себестоимость'!$E$15/'Допущения'!$E$69
A91: LTV / CAC | B91: =IFERROR(B90/B89,0)
A92: Валовая маржа за 36 мес. | B92: =B36
A93: NPV операционного потока + терминальная стоимость, $ | B93: =NPV((1+'Допущения'!$E$99)^(1/12)-1,$C$65:$AL$65)
A94: IRR годовая | B94: =IFERROR((1+IRR($C$65:$AL$65,0.05))^12-1,"н/д")
A95: Мин. касса при выбранном варианте вложений, $ | B95: =B55
A96: Мин. касса: вариант 1, $ | B96: =B56
A97: Мин. касса: вариант 2, $ | B97: =B57
A98: Мин. касса: вариант 3, $ | B98: =B58
A99: Расходы мес. 1 … выход включительно, $ | B99: =SUMIF($C$6:$AL$6,"<="&'Допущения'!$E$9,$C$34:$AL$34)+SUMIF($C$6:$AL$6,"<="&'Допущения'!$E$9,$C$47:$AL$47)

Sheet Чувствительность
A1: Анализ чувствительности (базовый сценарий): параметр ±Δ, остальное без изменений
A3: Δ, изменение параметра | B3: 0.2
A5: Параметр | B5: NPV при −Δ, $ | C5: NPV при +Δ, $ | D5: Размах NPV, $ | E5: Мин. касса (вар. 2) при −Δ | F5: Мин. касса (вар. 2) при +Δ | G5: Безубыточность при −Δ (мес.) | H5: Безубыточность при +Δ (мес.)
A6: CPI | B6: ='S_cpim'!$B$93 | C6: ='S_cpip'!$B$93 | D6: =ABS(C6-B6) | E6: ='S_cpim'!$B$97 | F6: ='S_cpip'!$B$97 | G6: ='S_cpim'!$B$69 | H6: ='S_cpip'!$B$69
A7: Конверсия в платящего | B7: ='S_conv_newm'!$B$93 | C7: ='S_conv_newp'!$B$93 | D7: =ABS(C7-B7) | E7: ='S_conv_newm'!$B$97 | F7: ='S_conv_newp'!$B$97 | G7: ='S_conv_newm'!$B$69 | H7: ='S_conv_newp'!$B$69
A8: Отток платящих | B8: ='S_churnm'!$B$93 | C8: ='S_churnp'!$B$93 | D8: =ABS(C8-B8) | E8: ='S_churnm'!$B$97 | F8: ='S_churnp'!$B$97 | G8: ='S_churnm'!$B$69 | H8: ='S_churnp'!$B$69
A9: Цена подписок (ARPPU) | B9: ='S_arppum'!$B$93 | C9: ='S_arppup'!$B$93 | D9: =ABS(C9-B9) | E9: ='S_arppum'!$B$97 | F9: ='S_arppup'!$B$97 | G9: ='S_arppum'!$B$69 | H9: ='S_arppup'!$B$69
A10: Себестоимость хода | B10: ='S_c_hm'!$B$93 | C10: ='S_c_hp'!$B$93 | D10: =ABS(C10-B10) | E10: ='S_c_hm'!$B$97 | F10: ='S_c_hp'!$B$97 | G10: ='S_c_hm'!$B$69 | H10: ='S_c_hp'!$B$69
A11: Органика на старте | B11: ='S_org0m'!$B$93 | C11: ='S_org0p'!$B$93 | D11: =ABS(C11-B11) | E11: ='S_org0m'!$B$97 | F11: ='S_org0p'!$B$97 | G11: ='S_org0m'!$B$69 | H11: ='S_org0p'!$B$69
A13: Базовый NPV, $ | B13: ='Модель_Б'!$B$93
A14: Размах показывает, какие допущения сильнее всего двигают оценку: их проверяем первыми на прототипе (конверсия, отток) и в первых рекламных тестах (CPI).

Sheet S_cpim
A1: Финмодель на 36 месяцев — сценарий: Базовый
A2: Все значения считаются формулами из листов «Допущения», «Себестоимость», «Старт».
B5: Итого / знач.
A6: Месяц № | C6: 1 | D6: 2 | E6: 3 | F6: 4 | G6: 5 | H6: 6 | I6: 7 | J6: 8 | K6: 9 | L6: 10 | M6: 11 | N6: 12 | O6: 13 | P6: 14 | Q6: 15 | R6: 16 | S6: 17 | T6: 18 | U6: 19 | V6: 20 | W6: 21 | X6: 22 | Y6: 23 | Z6: 24 | AA6: 25 | AB6: 26 | AC6: 27 | AD6: 28 | AE6: 29 | AF6: 30 | AG6: 31 | AH6: 32 | AI6: 33 | AJ6: 34 | AK6: 35 | AL6: 36
A7: Месяц | C7: ноя 2026 | D7: дек 2026 | E7: янв 2027 | F7: фев 2027 | G7: мар 2027 | H7: апр 2027 | I7: май 2027 | J7: июн 2027 | K7: июл 2027 | L7: авг 2027 | M7: сен 2027 | N7: окт 2027 | O7: ноя 2027 | P7: дек 2027 | Q7: янв 2028 | R7: фев 2028 | S7: мар 2028 | T7: апр 2028 | U7: май 2028 | V7: июн 2028 | W7: июл 2028 | X7: авг 2028 | Y7: сен 2028 | Z7: окт 2028 | AA7: ноя 2028 | AB7: дек 2028 | AC7: янв 2029 | AD7: фев 2029 | AE7: мар 2029 | AF7: апр 2029 | AG7: май 2029 | AH7: июн 2029 | AI7: июл 2029 | AJ7: авг 2029 | AK7: сен 2029 | AL7: окт 2029
A8: Год проекта | C8: 1 | D8: 1 | E8: 1 | F8: 1 | G8: 1 | H8: 1 | I8: 1 | J8: 1 | K8: 1 | L8: 1 | M8: 1 | N8: 1 | O8: 2 | P8: 2 | Q8: 2 | R8: 2 | S8: 2 | T8: 2 | U8: 2 | V8: 2 | W8: 2 | X8: 2 | Y8: 2 | Z8: 2 | AA8: 3 | AB8: 3 | AC8: 3 | AD8: 3 | AE8: 3 | AF8: 3 | AG8: 3 | AH8: 3 | AI8: 3 | AJ8: 3 | AK8: 3 | AL8: 3
A9: Рынок (1 = MVP вышел) | C9: =IF(C6>='Допущения'!$D$9,1,0) | D9: =IF(D6>='Допущения'!$D$9,1,0) | E9: =IF(E6>='Допущения'!$D$9,1,0) | F9: =IF(F6>='Допущения'!$D$9,1,0) | G9: =IF(G6>='Допущения'!$D$9,1,0) | H9: =IF(H6>='Допущения'!$D$9,1,0) | I9: =IF(I6>='Допущения'!$D$9,1,0) | J9: =IF(J6>='Допущения'!$D$9,1,0) | ... AL9: =IF(AL6>='Допущения'!$D$9,1,0)
A10: ВОРОНКА
A11: Маркетинг, $ | B11: =SUM(C11:AL11) | C11: =IF(C9=1,MAX('Допущения'!$D$83,'Допущения'!$D$84*0)+IF(C6='Допущения'!$D$9,'Допущения'!$D$82,0),'Допущения'!$D$81) | D11: =IF(D9=1,MAX('Допущения'!$D$83,'Допущения'!$D$84*C28)+IF(D6='Допущения'!$D$9,'Допущения'!$D$82,0),'Допущения'!$D$81) | E11: =IF(E9=1,MAX('Допущения'!$D$83,'Допущения'!$D$84*D28)+IF(E6='Допущения'!$D$9,'Допущения'!$D$82,0),'Допущения'!$D$81) | F11: =IF(F9=1,MAX('Допущения'!$D$83,'Допущения'!$D$84*E28)+IF(F6='Допущения'!$D$9,'Допущения'!$D$82,0),'Допущения'!$D$81) | G11: =IF(G9=1,MAX('Допущения'!$D$83,'Допущения'!$D$84*F28)+IF(G6='Допущения'!$D$9,'Допущения'!$D$82,0),'Допущения'!$D$81) | H11: =IF(H9=1,MAX('Допущения'!$D$83,'Допущения'!$D$84*G28)+IF(H6='Допущения'!$D$9,'Допущения'!$D$82,0),'Допущения'!$D$81) | I11: =IF(I9=1,MAX('Допущения'!$D$83,'Допущения'!$D$84*H28)+IF(I6='Допущения'!$D$9,'Допущения'!$D$82,0),'Допущения'!$D$81) | J11: =IF(J9=1,MAX('Допущения'!$D$83,'Допущения'!$D$84*I28)+IF(J6='Допущения'!$D$9,'Допущения'!$D$82,0),'Допущения'!$D$81) | K11: =IF(K9=1,MAX('Допущения'!$D$83,'Допущения'!$D$84*J28)+IF(K6='Допущения'!$D$9,'Допущения'!$D$82,0),'Допущения'!$D$81) | ... AL11: =IF(AL9=1,MAX('Допущения'!$D$83,'Допущения'!$D$84*AK28)+IF(AL6='Допущения'!$D$9,'Допущения'!$D$82,0),'Допущения'!$D$81)
A12: Платные установки | B12: =SUM(C12:AL12) | C12: =IF(C9=1,C11/('Допущения'!$D$60*(1-'Чувствительность'!$B$3)),0) | D12: =IF(D9=1,D11/('Допущения'!$D$60*(1-'Чувствительность'!$B$3)),0) | E12: =IF(E9=1,E11/('Допущения'!$D$60*(1-'Чувствительность'!$B$3)),0) | F12: =IF(F9=1,F11/('Допущения'!$D$60*(1-'Чувствительность'!$B$3)),0) | G12: =IF(G9=1,G11/('Допущения'!$D$60*(1-'Чувствительность'!$B$3)),0) | H12: =IF(H9=1,H11/('Допущения'!$D$60*(1-'Чувствительность'!$B$3)),0) | I12: =IF(I9=1,I11/('Допущения'!$D$60*(1-'Чувствительность'!$B$3)),0) | J12: =IF(J9=1,J11/('Допущения'!$D$60*(1-'Чувствительность'!$B$3)),0) | ... AL12: =IF(AL9=1,AL11/('Допущения'!$D$60*(1-'Чувствительность'!$B$3)),0)
A13: Органические установки | B13: =SUM(C13:AL13) | C13: =IF(C9=1,MIN('Допущения'!$D$63,'Допущения'!$D$61*(1+'Допущения'!$D$62)^(C6-'Допущения'!$D$9)),0) | D13: =IF(D9=1,MIN('Допущения'!$D$63,'Допущения'!$D$61*(1+'Допущения'!$D$62)^(D6-'Допущения'!$D$9)),0) | E13: =IF(E9=1,MIN('Допущения'!$D$63,'Допущения'!$D$61*(1+'Допущения'!$D$62)^(E6-'Допущения'!$D$9)),0) | F13: =IF(F9=1,MIN('Допущения'!$D$63,'Допущения'!$D$61*(1+'Допущения'!$D$62)^(F6-'Допущения'!$D$9)),0) | G13: =IF(G9=1,MIN('Допущения'!$D$63,'Допущения'!$D$61*(1+'Допущения'!$D$62)^(G6-'Допущения'!$D$9)),0) | H13: =IF(H9=1,MIN('Допущения'!$D$63,'Допущения'!$D$61*(1+'Допущения'!$D$62)^(H6-'Допущения'!$D$9)),0) | I13: =IF(I9=1,MIN('Допущения'!$D$63,'Допущения'!$D$61*(1+'Допущения'!$D$62)^(I6-'Допущения'!$D$9)),0) | J13: =IF(J9=1,MIN('Допущения'!$D$63,'Допущения'!$D$61*(1+'Допущения'!$D$62)^(J6-'Допущения'!$D$9)),0) | ... AL13: =IF(AL9=1,MIN('Допущения'!$D$63,'Допущения'!$D$61*(1+'Допущения'!$D$62)^(AL6-'Допущения'!$D$9)),0)
A14: Вирусные установки | B14: =SUM(C14:AL14) | C14: =(C12+C13)*'Допущения'!$D$64 | D14: =(D12+D13)*'Допущения'!$D$64 | E14: =(E12+E13)*'Допущения'!$D$64 | F14: =(F12+F13)*'Допущения'!$D$64 | G14: =(G12+G13)*'Допущения'!$D$64 | H14: =(H12+H13)*'Допущения'!$D$64 | I14: =(I12+I13)*'Допущения'!$D$64 | J14: =(J12+J13)*'Допущения'!$D$64 | ... AL14: =(AL12+AL13)*'Допущения'!$D$64
A15: Всего установок | B15: =SUM(C15:AL15) | C15: =C12+C13+C14 | D15: =D12+D13+D14 | E15: =E12+E13+E14 | F15: =F12+F13+F14 | G15: =G12+G13+G14 | H15: =H12+H13+H14 | I15: =I12+I13+I14 | J15: =J12+J13+J14 | ... AL15: =AL12+AL13+AL14
A16: Новые активированные | B16: =SUM(C16:AL16) | C16: =C15*'Допущения'!$D$65+IF(C6='Допущения'!$D$9,0*'Допущения'!$D$78,0) | D16: =D15*'Допущения'!$D$65+IF(D6='Допущения'!$D$9,C17*'Допущения'!$D$78,0) | E16: =E15*'Допущения'!$D$65+IF(E6='Допущения'!$D$9,D17*'Допущения'!$D$78,0) | F16: =F15*'Допущения'!$D$65+IF(F6='Допущения'!$D$9,E17*'Допущения'!$D$78,0) | G16: =G15*'Допущения'!$D$65+IF(G6='Допущения'!$D$9,F17*'Допущения'!$D$78,0) | H16: =H15*'Допущения'!$D$65+IF(H6='Допущения'!$D$9,G17*'Допущения'!$D$78,0) | I16: =I15*'Допущения'!$D$65+IF(I6='Допущения'!$D$9,H17*'Допущения'!$D$78,0) | J16: =J15*'Допущения'!$D$65+IF(J6='Допущения'!$D$9,I17*'Допущения'!$D$78,0) | K16: =K15*'Допущения'!$D$65+IF(K6='Допущения'!$D$9,J17*'Допущения'!$D$78,0) | ... AL16: =AL15*'Допущения'!$D$65+IF(AL6='Допущения'!$D$9,AK17*'Допущения'!$D$78,0)
A17: Игроки прототипа (до выхода) | C17: =IF(C9=1,0,'Допущения'!$D$72*(1+'Допущения'!$D$73)^(C6-1)) | D17: =IF(D9=1,0,'Допущения'!$D$72*(1+'Допущения'!$D$73)^(D6-1)) | E17: =IF(E9=1,0,'Допущения'!$D$72*(1+'Допущения'!$D$73)^(E6-1)) | F17: =IF(F9=1,0,'Допущения'!$D$72*(1+'Допущения'!$D$73)^(F6-1)) | G17: =IF(G9=1,0,'Допущения'!$D$72*(1+'Допущения'!$D$73)^(G6-1)) | H17: =IF(H9=1,0,'Допущения'!$D$72*(1+'Допущения'!$D$73)^(H6-1)) | I17: =IF(I9=1,0,'Допущения'!$D$72*(1+'Допущения'!$D$73)^(I6-1)) | J17: =IF(J9=1,0,'Допущения'!$D$72*(1+'Допущения'!$D$73)^(J6-1)) | ... AL17: =IF(AL9=1,0,'Допущения'!$D$72*(1+'Допущения'!$D$73)^(AL6-1))
A18: Активные free (на конец мес.) | C18: =IF(C9=1,0*(1-'Допущения'!$D$68)*'Допущения'!$D$66+C16*(1-'Допущения'!$D$67),0) | D18: =IF(D9=1,C18*(1-'Допущения'!$D$68)*'Допущения'!$D$66+D16*(1-'Допущения'!$D$67),0) | E18: =IF(E9=1,D18*(1-'Допущения'!$D$68)*'Допущения'!$D$66+E16*(1-'Допущения'!$D$67),0) | F18: =IF(F9=1,E18*(1-'Допущения'!$D$68)*'Допущения'!$D$66+F16*(1-'Допущения'!$D$67),0) | G18: =IF(G9=1,F18*(1-'Допущения'!$D$68)*'Допущения'!$D$66+G16*(1-'Допущения'!$D$67),0) | H18: =IF(H9=1,G18*(1-'Допущения'!$D$68)*'Допущения'!$D$66+H16*(1-'Допущения'!$D$67),0) | I18: =IF(I9=1,H18*(1-'Допущения'!$D$68)*'Допущения'!$D$66+I16*(1-'Допущения'!$D$67),0) | J18: =IF(J9=1,I18*(1-'Допущения'!$D$68)*'Допущения'!$D$66+J16*(1-'Допущения'!$D$67),0) | K18: =IF(K9=1,J18*(1-'Допущения'!$D$68)*'Допущения'!$D$66+K16*(1-'Допущения'!$D$67),0) | ... AL18: =IF(AL9=1,AK18*(1-'Допущения'!$D$68)*'Допущения'!$D$66+AL16*(1-'Допущения'!$D$67),0)
A19: Новые платящие | B19: =SUM(C19:AL19) | C19: =IF(C9=1,C16*'Допущения'!$D$67+0*'Допущения'!$D$68,0) | D19: =IF(D9=1,D16*'Допущения'!$D$67+C18*'Допущения'!$D$68,0) | E19: =IF(E9=1,E16*'Допущения'!$D$67+D18*'Допущения'!$D$68,0) | F19: =IF(F9=1,F16*'Допущения'!$D$67+E18*'Допущения'!$D$68,0) | G19: =IF(G9=1,G16*'Допущения'!$D$67+F18*'Допущения'!$D$68,0) | H19: =IF(H9=1,H16*'Допущения'!$D$67+G18*'Допущения'!$D$68,0) | I19: =IF(I9=1,I16*'Допущения'!$D$67+H18*'Допущения'!$D$68,0) | J19: =IF(J9=1,J16*'Допущения'!$D$67+I18*'Допущения'!$D$68,0) | K19: =IF(K9=1,K16*'Допущения'!$D$67+J18*'Допущения'!$D$68,0) | ... AL19: =IF(AL9=1,AL16*'Допущения'!$D$67+AK18*'Допущения'!$D$68,0)
A20: Ушедшие платящие | B20: =SUM(C20:AL20) | C20: =0*'Допущения'!$D$69 | D20: =C21*'Допущения'!$D$69 | E20: =D21*'Допущения'!$D$69 | F20: =E21*'Допущения'!$D$69 | G20: =F21*'Допущения'!$D$69 | H20: =G21*'Допущения'!$D$69 | I20: =H21*'Допущения'!$D$69 | J20: =I21*'Допущения'!$D$69 | K20: =J21*'Допущения'!$D$69 | ... AL20: =AK21*'Допущения'!$D$69
A21: Платящие (на конец мес.) | C21: =0+C19-C20 | D21: =C21+D19-D20 | E21: =D21+E19-E20 | F21: =E21+F19-F20 | G21: =F21+G19-G20 | H21: =G21+H19-H20 | I21: =H21+I19-I20 | J21: =I21+J19-J20 | K21: =J21+K19-K20 | ... AL21: =AK21+AL19-AL20
A22: Активные пользователи всего | C22: =C17+C18+C21 | D22: =D17+D18+D21 | E22: =E17+E18+E21 | F22: =F17+F18+F21 | G22: =G17+G18+G21 | H22: =H17+H18+H21 | I22: =I17+I18+I21 | J22: =J17+J18+J21 | ... AL22: =AL17+AL18+AL21
A23: ВЫРУЧКА, $
A24: Оплаты подписок (брутто) | B24: =SUM(C24:AL24) | C24: =C21*'Себестоимость'!$D$12 | D24: =D21*'Себестоимость'!$D$12 | E24: =E21*'Себестоимость'!$D$12 | F24: =F21*'Себестоимость'!$D$12 | G24: =G21*'Себестоимость'!$D$12 | H24: =H21*'Себестоимость'!$D$12 | I24: =I21*'Себестоимость'!$D$12 | J24: =J21*'Себестоимость'!$D$12 | ... AL24: =AL21*'Себестоимость'!$D$12
A25: Комиссии магазинов/Paddle и НДС | B25: =SUM(C25:AL25) | C25: =C24-C26 | D25: =D24-D26 | E25: =E24-E26 | F25: =F24-F26 | G25: =G24-G26 | H25: =H24-H26 | I25: =I24-I26 | J25: =J24-J26 | ... AL25: =AL24-AL26
A26: Чистая выручка подписок | B26: =SUM(C26:AL26) | C26: =C21*'Себестоимость'!$D$13 | D26: =D21*'Себестоимость'!$D$13 | E26: =E21*'Себестоимость'!$D$13 | F26: =F21*'Себестоимость'!$D$13 | G26: =G21*'Себестоимость'!$D$13 | H26: =H21*'Себестоимость'!$D$13 | I26: =I21*'Себестоимость'!$D$13 | J26: =J21*'Себестоимость'!$D$13 | ... AL26: =AL21*'Себестоимость'!$D$13
A27: Донаты (чистые) | B27: =SUM(C27:AL27) | C27: =C17*'Допущения'!$D$75*'Допущения'!$D$76*(1-'Допущения'!$D$77) | D27: =D17*'Допущения'!$D$75*'Допущения'!$D$76*(1-'Допущения'!$D$77) | E27: =E17*'Допущения'!$D$75*'Допущения'!$D$76*(1-'Допущения'!$D$77) | F27: =F17*'Допущения'!$D$75*'Допущения'!$D$76*(1-'Допущения'!$D$77) | G27: =G17*'Допущения'!$D$75*'Допущения'!$D$76*(1-'Допущения'!$D$77) | H27: =H17*'Допущения'!$D$75*'Допущения'!$D$76*(1-'Допущения'!$D$77) | I27: =I17*'Допущения'!$D$75*'Допущения'!$D$76*(1-'Допущения'!$D$77) | J27: =J17*'Допущения'!$D$75*'Допущения'!$D$76*(1-'Допущения'!$D$77) | ... AL27: =AL17*'Допущения'!$D$75*'Допущения'!$D$76*(1-'Допущения'!$D$77)
A28: Итого чистая выручка | B28: =SUM(C28:AL28) | C28: =C26+C27 | D28: =D26+D27 | E28: =E26+E27 | F28: =F26+F27 | G28: =G26+G27 | H28: =H26+H27 | I28: =I26+I27 | J28: =J26+J27 | ... AL28: =AL26+AL27
A29: ПЕРЕМЕННЫЕ ЗАТРАТЫ, $
A30: LLM: платящие | B30: =SUM(C30:AL30) | C30: =C21*'Себестоимость'!$D$14 | D30: =D21*'Себестоимость'!$D$14 | E30: =E21*'Себестоимость'!$D$14 | F30: =F21*'Себестоимость'!$D$14 | G30: =G21*'Себестоимость'!$D$14 | H30: =H21*'Себестоимость'!$D$14 | I30: =I21*'Себестоимость'!$D$14 | J30: =J21*'Себестоимость'!$D$14 | ... AL30: =AL21*'Себестоимость'!$D$14
A31: LLM: free и прототип | B31: =SUM(C31:AL31) | C31: =C18*'Себестоимость'!$D$16+C17*'Допущения'!$D$74*'Себестоимость'!$D$7 | D31: =D18*'Себестоимость'!$D$16+D17*'Допущения'!$D$74*'Себестоимость'!$D$7 | E31: =E18*'Себестоимость'!$D$16+E17*'Допущения'!$D$74*'Себестоимость'!$D$7 | F31: =F18*'Себестоимость'!$D$16+F17*'Допущения'!$D$74*'Себестоимость'!$D$7 | G31: =G18*'Себестоимость'!$D$16+G17*'Допущения'!$D$74*'Себестоимость'!$D$7 | H31: =H18*'Себестоимость'!$D$16+H17*'Допущения'!$D$74*'Себестоимость'!$D$7 | I31: =I18*'Себестоимость'!$D$16+I17*'Допущения'!$D$74*'Себестоимость'!$D$7 | J31: =J18*'Себестоимость'!$D$16+J17*'Допущения'!$D$74*'Себестоимость'!$D$7 | ... AL31: =AL18*'Себестоимость'!$D$16+AL17*'Допущения'!$D$74*'Себестоимость'!$D$7
A32: Проверка возраста | B32: =SUM(C32:AL32) | C32: =C19*'Допущения'!$D$44*'Допущения'!$D$93 | D32: =D19*'Допущения'!$D$44*'Допущения'!$D$93 | E32: =E19*'Допущения'!$D$44*'Допущения'!$D$93 | F32: =F19*'Допущения'!$D$44*'Допущения'!$D$93 | G32: =G19*'Допущения'!$D$44*'Допущения'!$D$93 | H32: =H19*'Допущения'!$D$44*'Допущения'!$D$93 | I32: =I19*'Допущения'!$D$44*'Допущения'!$D$93 | J32: =J19*'Допущения'!$D$44*'Допущения'!$D$93 | ... AL32: =AL19*'Допущения'!$D$44*'Допущения'!$D$93
A33: Инфраструктура (на пользователя) | B33: =SUM(C33:AL33) | C33: =C22*'Допущения'!$D$86 | D33: =D22*'Допущения'!$D$86 | E33: =E22*'Допущения'!$D$86 | F33: =F22*'Допущения'!$D$86 | G33: =G22*'Допущения'!$D$86 | H33: =H22*'Допущения'!$D$86 | I33: =I22*'Допущения'!$D$86 | J33: =J22*'Допущения'!$D$86 | ... AL33: =AL22*'Допущения'!$D$86
A34: Итого переменные | B34: =SUM(C34:AL34) | C34: =SUM(C30:C33) | D34: =SUM(D30:D33) | E34: =SUM(E30:E33) | F34: =SUM(F30:F33) | G34: =SUM(G30:G33) | H34: =SUM(H30:H33) | I34: =SUM(I30:I33) | J34: =SUM(J30:J33) | ... AL34: =SUM(AL30:AL33)
A35: Валовая прибыль | B35: =SUM(C35:AL35) | C35: =C28-C34 | D35: =D28-D34 | E35: =E28-E34 | F35: =F28-F34 | G35: =G28-G34 | H35: =H28-H34 | I35: =I28-I34 | J35: =J28-J34 | ... AL35: =AL28-AL34
A36: Валовая маржа | B36: =IFERROR(B35/B28,0) | C36: =IFERROR(C35/C28,0) | D36: =IFERROR(D35/D28,0) | E36: =IFERROR(E35/E28,0) | F36: =IFERROR(F35/F28,0) | G36: =IFERROR(G35/G28,0) | H36: =IFERROR(H35/H28,0) | I36: =IFERROR(I35/I28,0) | ... AL36: =IFERROR(AL35/AL28,0)
A37: ПОСТОЯННЫЕ ЗАТРАТЫ И МАРКЕТИНГ, $
A38: Инфраструктура (база) | B38: =SUM(C38:AL38) | C38: ='Допущения'!$D$85 | D38: ='Допущения'!$D$85 | E38: ='Допущения'!$D$85 | F38: ='Допущения'!$D$85 | G38: ='Допущения'!$D$85 | H38: ='Допущения'!$D$85 | I38: ='Допущения'!$D$85 | J38: ='Допущения'!$D$85 | ... AL38: ='Допущения'!$D$85
A39: SaaS-инструменты | B39: =SUM(C39:AL39) | C39: ='Допущения'!$D$87 | D39: ='Допущения'!$D$87 | E39: ='Допущения'!$D$87 | F39: ='Допущения'!$D$87 | G39: ='Допущения'!$D$87 | H39: ='Допущения'!$D$87 | I39: ='Допущения'!$D$87 | J39: ='Допущения'!$D$87 | ... AL39: ='Допущения'!$D$87
A40: Бухгалтерия | B40: =SUM(C40:AL40) | C40: =IF(C6>='Допущения'!$D$10,'Допущения'!$D$88,0) | D40: =IF(D6>='Допущения'!$D$10,'Допущения'!$D$88,0) | E40: =IF(E6>='Допущения'!$D$10,'Допущения'!$D$88,0) | F40: =IF(F6>='Допущения'!$D$10,'Допущения'!$D$88,0) | G40: =IF(G6>='Допущения'!$D$10,'Допущения'!$D$88,0) | H40: =IF(H6>='Допущения'!$D$10,'Допущения'!$D$88,0) | I40: =IF(I6>='Допущения'!$D$10,'Допущения'!$D$88,0) | J40: =IF(J6>='Допущения'!$D$10,'Допущения'!$D$88,0) | ... AL40: =IF(AL6>='Допущения'!$D$10,'Допущения'!$D$88,0)
A41: Юр. сопровождение | B41: =SUM(C41:AL41) | C41: =IF(C9=1,'Допущения'!$D$89,0) | D41: =IF(D9=1,'Допущения'!$D$89,0) | E41: =IF(E9=1,'Допущения'!$D$89,0) | F41: =IF(F9=1,'Допущения'!$D$89,0) | G41: =IF(G9=1,'Допущения'!$D$89,0) | H41: =IF(H9=1,'Допущения'!$D$89,0) | I41: =IF(I9=1,'Допущения'!$D$89,0) | J41: =IF(J9=1,'Допущения'!$D$89,0) | ... AL41: =IF(AL9=1,'Допущения'!$D$89,0)
A42: Магазины приложений | B42: =SUM(C42:AL42) | C42: =IF(C6='Допущения'!$D$9-1,'Допущения'!$D$90+'Допущения'!$D$91,0)+IF(AND(C6>'Допущения'!$D$9-1,MOD(C6-('Допущения'!$D$9-1),12)=0),'Допущения'!$D$90,0) | D42: =IF(D6='Допущения'!$D$9-1,'Допущения'!$D$90+'Допущения'!$D$91,0)+IF(AND(D6>'Допущения'!$D$9-1,MOD(D6-('Допущения'!$D$9-1),12)=0),'Допущения'!$D$90,0) | E42: =IF(E6='Допущения'!$D$9-1,'Допущения'!$D$90+'Допущения'!$D$91,0)+IF(AND(E6>'Допущения'!$D$9-1,MOD(E6-('Допущения'!$D$9-1),12)=0),'Допущения'!$D$90,0) | F42: =IF(F6='Допущения'!$D$9-1,'Допущения'!$D$90+'Допущения'!$D$91,0)+IF(AND(F6>'Допущения'!$D$9-1,MOD(F6-('Допущения'!$D$9-1),12)=0),'Допущения'!$D$90,0) | G42: =IF(G6='Допущения'!$D$9-1,'Допущения'!$D$90+'Допущения'!$D$91,0)+IF(AND(G6>'Допущения'!$D$9-1,MOD(G6-('Допущения'!$D$9-1),12)=0),'Допущения'!$D$90,0) | H42: =IF(H6='Допущения'!$D$9-1,'Допущения'!$D$90+'Допущения'!$D$91,0)+IF(AND(H6>'Допущения'!$D$9-1,MOD(H6-('Допущения'!$D$9-1),12)=0),'Допущения'!$D$90,0) | I42: =IF(I6='Допущения'!$D$9-1,'Допущения'!$D$90+'Допущения'!$D$91,0)+IF(AND(I6>'Допущения'!$D$9-1,MOD(I6-('Допущения'!$D$9-1),12)=0),'Допущения'!$D$90,0) | J42: =IF(J6='Допущения'!$D$9-1,'Допущения'!$D$90+'Допущения'!$D$91,0)+IF(AND(J6>'Допущения'!$D$9-1,MOD(J6-('Допущения'!$D$9-1),12)=0),'Допущения'!$D$90,0) | ... AL42: =IF(AL6='Допущения'!$D$9-1,'Допущения'!$D$90+'Допущения'!$D$91,0)+IF(AND(AL6>'Допущения'!$D$9-1,MOD(AL6-('Допущения'!$D$9-1),12)=0),'Допущения'!$D$90,0)
A43: Разовые стартовые (лист «Старт») | B43: =SUM(C43:AL43) | C43: =SUMIF('Старт'!$C$5:$C$17,C6,'Старт'!$D$5:$D$17) | D43: =SUMIF('Старт'!$C$5:$C$17,D6,'Старт'!$D$5:$D$17) | E43: =SUMIF('Старт'!$C$5:$C$17,E6,'Старт'!$D$5:$D$17) | F43: =SUMIF('Старт'!$C$5:$C$17,F6,'Старт'!$D$5:$D$17) | G43: =SUMIF('Старт'!$C$5:$C$17,G6,'Старт'!$D$5:$D$17) | H43: =SUMIF('Старт'!$C$5:$C$17,H6,'Старт'!$D$5:$D$17) | I43: =SUMIF('Старт'!$C$5:$C$17,I6,'Старт'!$D$5:$D$17) | J43: =SUMIF('Старт'!$C$5:$C$17,J6,'Старт'!$D$5:$D$17) | ... AL43: =SUMIF('Старт'!$C$5:$C$17,AL6,'Старт'!$D$5:$D$17)
A44: Контент / SMM | B44: =SUM(C44:AL44) | C44: =IF(C6>'Допущения'!$D$9,'Допущения'!$D$92,0) | D44: =IF(D6>'Допущения'!$D$9,'Допущения'!$D$92,0) | E44: =IF(E6>'Допущения'!$D$9,'Допущения'!$D$92,0) | F44: =IF(F6>'Допущения'!$D$9,'Допущения'!$D$92,0) | G44: =IF(G6>'Допущения'!$D$9,'Допущения'!$D$92,0) | H44: =IF(H6>'Допущения'!$D$9,'Допущения'!$D$92,0) | I44: =IF(I6>'Допущения'!$D$9,'Допущения'!$D$92,0) | J44: =IF(J6>'Допущения'!$D$9,'Допущения'!$D$92,0) | ... AL44: =IF(AL6>'Допущения'!$D$9,'Допущения'!$D$92,0)
A45: Маркетинг | B45: =SUM(C45:AL45) | C45: =C11 | D45: =D11 | E45: =E11 | F45: =F11 | G45: =G11 | H45: =H11 | I45: =I11 | J45: =J11 | ... AL45: =AL11
A46: Выплаты основателям | B46: =SUM(C46:AL46) | C46: =IF(C6>='Допущения'!$D$94,MIN('Допущения'!$D$95,MAX(0,'Допущения'!$D$96*(0+0))),0) | D46: =IF(D6>='Допущения'!$D$94,MIN('Допущения'!$D$95,MAX(0,'Допущения'!$D$96*(C48+C46))),0) | E46: =IF(E6>='Допущения'!$D$94,MIN('Допущения'!$D$95,MAX(0,'Допущения'!$D$96*(D48+D46))),0) | F46: =IF(F6>='Допущения'!$D$94,MIN('Допущения'!$D$95,MAX(0,'Допущения'!$D$96*(E48+E46))),0) | G46: =IF(G6>='Допущения'!$D$94,MIN('Допущения'!$D$95,MAX(0,'Допущения'!$D$96*(F48+F46))),0) | H46: =IF(H6>='Допущения'!$D$94,MIN('Допущения'!$D$95,MAX(0,'Допущения'!$D$96*(G48+G46))),0) | I46: =IF(I6>='Допущения'!$D$94,MIN('Допущения'!$D$95,MAX(0,'Допущения'!$D$96*(H48+H46))),0) | J46: =IF(J6>='Допущения'!$D$94,MIN('Допущения'!$D$95,MAX(0,'Допущения'!$D$96*(I48+I46))),0) | K46: =IF(K6>='Допущения'!$D$94,MIN('Допущения'!$D$95,MAX(0,'Допущения'!$D$96*(J48+J46))),0) | ... AL46: =IF(AL6>='Допущения'!$D$94,MIN('Допущения'!$D$95,MAX(0,'Допущения'!$D$96*(AK48+AK46))),0)
A47: Итого постоянные + маркетинг | B47: =SUM(C47:AL47) | C47: =SUM(C38:C46) | D47: =SUM(D38:D46) | E47: =SUM(E38:E46) | F47: =SUM(F38:F46) | G47: =SUM(G38:G46) | H47: =SUM(H38:H46) | I47: =SUM(I38:I46) | J47: =SUM(J38:J46) | ... AL47: =SUM(AL38:AL46)
A48: EBITDA | B48: =SUM(C48:AL48) | C48: =C35-C47 | D48: =D35-D47 | E48: =E35-E47 | F48: =F35-F47 | G48: =G35-G47 | H48: =H35-H47 | I48: =I35-I47 | J48: =J35-J47 | ... AL48: =AL35-AL47
A49: Налог на прибыль | B49: =SUM(C49:AL49) | C49: =MAX(0,C48)*'Допущения'!$D$57 | D49: =MAX(0,D48)*'Допущения'!$D$57 | E49: =MAX(0,E48)*'Допущения'!$D$57 | F49: =MAX(0,F48)*'Допущения'!$D$57 | G49: =MAX(0,G48)*'Допущения'!$D$57 | H49: =MAX(0,H48)*'Допущения'!$D$57 | I49: =MAX(0,I48)*'Допущения'!$D$57 | J49: =MAX(0,J48)*'Допущения'!$D$57 | ... AL49: =MAX(0,AL48)*'Допущения'!$D$57
A50: Операционный денежный поток | B50: =SUM(C50:AL50) | C50: =C48-C49 | D50: =D48-D49 | E50: =E48-E49 | F50: =F48-F49 | G50: =G48-G49 | H50: =H48-H49 | I50: =I48-I49 | J50: =J48-J49 | ... AL50: =AL48-AL49
A51: Накопленный операционный поток | B51: =MIN(C51:AL51) | C51: =0+C50 | D51: =C51+D50 | E51: =D51+E50 | F51: =E51+F50 | G51: =F51+G50 | H51: =G51+H50 | I51: =H51+I50 | J51: =I51+J50 | K51: =J51+K50 | ... AL51: =AK51+AL50
A52: ВЛОЖЕНИЯ И КАССА, $
A53: Вложения партнёра (выбранный вариант) | B53: =SUM(C53:AL53) | C53: =(IF(C6=1,INDEX('Допущения'!$C$104:$C$106,'Допущения'!$D$103)*'Допущения'!$D$107,0)+IF(C6='Допущения'!$D$9,INDEX('Допущения'!$C$104:$C$106,'Допущения'!$D$103)*(1-'Допущения'!$D$107),0))/'Допущения'!$D$7 | D53: =(IF(D6=1,INDEX('Допущения'!$C$104:$C$106,'Допущения'!$D$103)*'Допущения'!$D$107,0)+IF(D6='Допущения'!$D$9,INDEX('Допущения'!$C$104:$C$106,'Допущения'!$D$103)*(1-'Допущения'!$D$107),0))/'Допущения'!$D$7 | E53: =(IF(E6=1,INDEX('Допущения'!$C$104:$C$106,'Допущения'!$D$103)*'Допущения'!$D$107,0)+IF(E6='Допущения'!$D$9,INDEX('Допущения'!$C$104:$C$106,'Допущения'!$D$103)*(1-'Допущения'!$D$107),0))/'Допущения'!$D$7 | F53: =(IF(F6=1,INDEX('Допущения'!$C$104:$C$106,'Допущения'!$D$103)*'Допущения'!$D$107,0)+IF(F6='Допущения'!$D$9,INDEX('Допущения'!$C$104:$C$106,'Допущения'!$D$103)*(1-'Допущения'!$D$107),0))/'Допущения'!$D$7 | G53: =(IF(G6=1,INDEX('Допущения'!$C$104:$C$106,'Допущения'!$D$103)*'Допущения'!$D$107,0)+IF(G6='Допущения'!$D$9,INDEX('Допущения'!$C$104:$C$106,'Допущения'!$D$103)*(1-'Допущения'!$D$107),0))/'Допущения'!$D$7 | H53: =(IF(H6=1,INDEX('Допущения'!$C$104:$C$106,'Допущения'!$D$103)*'Допущения'!$D$107,0)+IF(H6='Допущения'!$D$9,INDEX('Допущения'!$C$104:$C$106,'Допущения'!$D$103)*(1-'Допущения'!$D$107),0))/'Допущения'!$D$7 | I53: =(IF(I6=1,INDEX('Допущения'!$C$104:$C$106,'Допущения'!$D$103)*'Допущения'!$D$107,0)+IF(I6='Допущения'!$D$9,INDEX('Допущения'!$C$104:$C$106,'Допущения'!$D$103)*(1-'Допущения'!$D$107),0))/'Допущения'!$D$7 | J53: =(IF(J6=1,INDEX('Допущения'!$C$104:$C$106,'Допущения'!$D$103)*'Допущения'!$D$107,0)+IF(J6='Допущения'!$D$9,INDEX('Допущения'!$C$104:$C$106,'Допущения'!$D$103)*(1-'Допущения'!$D$107),0))/'Допущения'!$D$7 | ... AL53: =(IF(AL6=1,INDEX('Допущения'!$C$104:$C$106,'Допущения'!$D$103)*'Допущения'!$D$107,0)+IF(AL6='Допущения'!$D$9,INDEX('Допущения'!$C$104:$C$106,'Допущения'!$D$103)*(1-'Допущения'!$D$107),0))/'Допущения'!$D$7
A54: Мои вложения (выбранный вариант) | B54: =SUM(C54:AL54) | C54: =(IF(C6=1,MIN(INDEX('Допущения'!$D$104:$D$106,'Допущения'!$D$103),'Допущения'!$D$108),0)+IF(AND(C6>=2,C6<=4),MAX(0,INDEX('Допущения'!$D$104:$D$106,'Допущения'!$D$103)-'Допущения'!$D$108)/3,0))/'Допущения'!$D$7 | D54: =(IF(D6=1,MIN(INDEX('Допущения'!$D$104:$D$106,'Допущения'!$D$103),'Допущения'!$D$108),0)+IF(AND(D6>=2,D6<=4),MAX(0,INDEX('Допущения'!$D$104:$D$106,'Допущения'!$D$103)-'Допущения'!$D$108)/3,0))/'Допущения'!$D$7 | E54: =(IF(E6=1,MIN(INDEX('Допущения'!$D$104:$D$106,'Допущения'!$D$103),'Допущения'!$D$108),0)+IF(AND(E6>=2,E6<=4),MAX(0,INDEX('Допущения'!$D$104:$D$106,'Допущения'!$D$103)-'Допущения'!$D$108)/3,0))/'Допущения'!$D$7 | F54: =(IF(F6=1,MIN(INDEX('Допущения'!$D$104:$D$106,'Допущения'!$D$103),'Допущения'!$D$108),0)+IF(AND(F6>=2,F6<=4),MAX(0,INDEX('Допущения'!$D$104:$D$106,'Допущения'!$D$103)-'Допущения'!$D$108)/3,0))/'Допущения'!$D$7 | G54: =(IF(G6=1,MIN(INDEX('Допущения'!$D$104:$D$106,'Допущения'!$D$103),'Допущения'!$D$108),0)+IF(AND(G6>=2,G6<=4),MAX(0,INDEX('Допущения'!$D$104:$D$106,'Допущения'!$D$103)-'Допущения'!$D$108)/3,0))/'Допущения'!$D$7 | H54: =(IF(H6=1,MIN(INDEX('Допущения'!$D$104:$D$106,'Допущения'!$D$103),'Допущения'!$D$108),0)+IF(AND(H6>=2,H6<=4),MAX(0,INDEX('Допущения'!$D$104:$D$106,'Допущения'!$D$103)-'Допущения'!$D$108)/3,0))/'Допущения'!$D$7 | I54: =(IF(I6=1,MIN(INDEX('Допущения'!$D$104:$D$106,'Допущения'!$D$103),'Допущения'!$D$108),0)+IF(AND(I6>=2,I6<=4),MAX(0,INDEX('Допущения'!$D$104:$D$106,'Допущения'!$D$103)-'Допущения'!$D$108)/3,0))/'Допущения'!$D$7 | J54: =(IF(J6=1,MIN(INDEX('Допущения'!$D$104:$D$106,'Допущения'!$D$103),'Допущения'!$D$108),0)+IF(AND(J6>=2,J6<=4),MAX(0,INDEX('Допущения'!$D$104:$D$106,'Допущения'!$D$103)-'Допущения'!$D$108)/3,0))/'Допущения'!$D$7 | ... AL54: =(IF(AL6=1,MIN(INDEX('Допущения'!$D$104:$D$106,'Допущения'!$D$103),'Допущения'!$D$108),0)+IF(AND(AL6>=2,AL6<=4),MAX(0,INDEX('Допущения'!$D$104:$D$106,'Допущения'!$D$103)-'Допущения'!$D$108)/3,0))/'Допущения'!$D$7
A55: Касса на конец месяца | B55: =MIN(C55:AL55) | C55: =0+C50+C53+C54 | D55: =C55+D50+D53+D54 | E55: =D55+E50+E53+E54 | F55: =E55+F50+F53+F54 | G55: =F55+G50+G53+G54 | H55: =G55+H50+H53+H54 | I55: =H55+I50+I53+I54 | J55: =I55+J50+J53+J54 | K55: =J55+K50+K53+K54 | ... AL55: =AK55+AL50+AL53+AL54
A56: Касса при варианте 1 «Минимум» | B56: =MIN(C56:AL56) | C56: =C51+('Допущения'!$C$104*'Допущения'!$D$107+IF(C6>='Допущения'!$D$9,'Допущения'!$C$104*(1-'Допущения'!$D$107),0)+MIN('Допущения'!$D$104,'Допущения'!$D$108)+MAX(0,'Допущения'!$D$104-'Допущения'!$D$108)*MIN(MAX(C6-1,0),3)/3)/'Допущения'!$D$7 | D56: =D51+('Допущения'!$C$104*'Допущения'!$D$107+IF(D6>='Допущения'!$D$9,'Допущения'!$C$104*(1-'Допущения'!$D$107),0)+MIN('Допущения'!$D$104,'Допущения'!$D$108)+MAX(0,'Допущения'!$D$104-'Допущения'!$D$108)*MIN(MAX(D6-1,0),3)/3)/'Допущения'!$D$7 | E56: =E51+('Допущения'!$C$104*'Допущения'!$D$107+IF(E6>='Допущения'!$D$9,'Допущения'!$C$104*(1-'Допущения'!$D$107),0)+MIN('Допущения'!$D$104,'Допущения'!$D$108)+MAX(0,'Допущения'!$D$104-'Допущения'!$D$108)*MIN(MAX(E6-1,0),3)/3)/'Допущения'!$D$7 | F56: =F51+('Допущения'!$C$104*'Допущения'!$D$107+IF(F6>='Допущения'!$D$9,'Допущения'!$C$104*(1-'Допущения'!$D$107),0)+MIN('Допущения'!$D$104,'Допущения'!$D$108)+MAX(0,'Допущения'!$D$104-'Допущения'!$D$108)*MIN(MAX(F6-1,0),3)/3)/'Допущения'!$D$7 | G56: =G51+('Допущения'!$C$104*'Допущения'!$D$107+IF(G6>='Допущения'!$D$9,'Допущения'!$C$104*(1-'Допущения'!$D$107),0)+MIN('Допущения'!$D$104,'Допущения'!$D$108)+MAX(0,'Допущения'!$D$104-'Допущения'!$D$108)*MIN(MAX(G6-1,0),3)/3)/'Допущения'!$D$7 | H56: =H51+('Допущения'!$C$104*'Допущения'!$D$107+IF(H6>='Допущения'!$D$9,'Допущения'!$C$104*(1-'Допущения'!$D$107),0)+MIN('Допущения'!$D$104,'Допущения'!$D$108)+MAX(0,'Допущения'!$D$104-'Допущения'!$D$108)*MIN(MAX(H6-1,0),3)/3)/'Допущения'!$D$7 | I56: =I51+('Допущения'!$C$104*'Допущения'!$D$107+IF(I6>='Допущения'!$D$9,'Допущения'!$C$104*(1-'Допущения'!$D$107),0)+MIN('Допущения'!$D$104,'Допущения'!$D$108)+MAX(0,'Допущения'!$D$104-'Допущения'!$D$108)*MIN(MAX(I6-1,0),3)/3)/'Допущения'!$D$7 | J56: =J51+('Допущения'!$C$104*'Допущения'!$D$107+IF(J6>='Допущения'!$D$9,'Допущения'!$C$104*(1-'Допущения'!$D$107),0)+MIN('Допущения'!$D$104,'Допущения'!$D$108)+MAX(0,'Допущения'!$D$104-'Допущения'!$D$108)*MIN(MAX(J6-1,0),3)/3)/'Допущения'!$D$7 | ... AL56: =AL51+('Допущения'!$C$104*'Допущения'!$D$107+IF(AL6>='Допущения'!$D$9,'Допущения'!$C$104*(1-'Допущения'!$D$107),0)+MIN('Допущения'!$D$104,'Допущения'!$D$108)+MAX(0,'Допущения'!$D$104-'Допущения'!$D$108)*MIN(MAX(AL6-1,0),3)/3)/'Допущения'!$D$7
A57: Касса при варианте 2 «Средний» | B57: =MIN(C57:AL57) | C57: =C51+('Допущения'!$C$105*'Допущения'!$D$107+IF(C6>='Допущения'!$D$9,'Допущения'!$C$105*(1-'Допущения'!$D$107),0)+MIN('Допущения'!$D$105,'Допущения'!$D$108)+MAX(0,'Допущения'!$D$105-'Допущения'!$D$108)*MIN(MAX(C6-1,0),3)/3)/'Допущения'!$D$7 | D57: =D51+('Допущения'!$C$105*'Допущения'!$D$107+IF(D6>='Допущения'!$D$9,'Допущения'!$C$105*(1-'Допущения'!$D$107),0)+MIN('Допущения'!$D$105,'Допущения'!$D$108)+MAX(0,'Допущения'!$D$105-'Допущения'!$D$108)*MIN(MAX(D6-1,0),3)/3)/'Допущения'!$D$7 | E57: =E51+('Допущения'!$C$105*'Допущения'!$D$107+IF(E6>='Допущения'!$D$9,'Допущения'!$C$105*(1-'Допущения'!$D$107),0)+MIN('Допущения'!$D$105,'Допущения'!$D$108)+MAX(0,'Допущения'!$D$105-'Допущения'!$D$108)*MIN(MAX(E6-1,0),3)/3)/'Допущения'!$D$7 | F57: =F51+('Допущения'!$C$105*'Допущения'!$D$107+IF(F6>='Допущения'!$D$9,'Допущения'!$C$105*(1-'Допущения'!$D$107),0)+MIN('Допущения'!$D$105,'Допущения'!$D$108)+MAX(0,'Допущения'!$D$105-'Допущения'!$D$108)*MIN(MAX(F6-1,0),3)/3)/'Допущения'!$D$7 | G57: =G51+('Допущения'!$C$105*'Допущения'!$D$107+IF(G6>='Допущения'!$D$9,'Допущения'!$C$105*(1-'Допущения'!$D$107),0)+MIN('Допущения'!$D$105,'Допущения'!$D$108)+MAX(0,'Допущения'!$D$105-'Допущения'!$D$108)*MIN(MAX(G6-1,0),3)/3)/'Допущения'!$D$7 | H57: =H51+('Допущения'!$C$105*'Допущения'!$D$107+IF(H6>='Допущения'!$D$9,'Допущения'!$C$105*(1-'Допущения'!$D$107),0)+MIN('Допущения'!$D$105,'Допущения'!$D$108)+MAX(0,'Допущения'!$D$105-'Допущения'!$D$108)*MIN(MAX(H6-1,0),3)/3)/'Допущения'!$D$7 | I57: =I51+('Допущения'!$C$105*'Допущения'!$D$107+IF(I6>='Допущения'!$D$9,'Допущения'!$C$105*(1-'Допущения'!$D$107),0)+MIN('Допущения'!$D$105,'Допущения'!$D$108)+MAX(0,'Допущения'!$D$105-'Допущения'!$D$108)*MIN(MAX(I6-1,0),3)/3)/'Допущения'!$D$7 | J57: =J51+('Допущения'!$C$105*'Допущения'!$D$107+IF(J6>='Допущения'!$D$9,'Допущения'!$C$105*(1-'Допущения'!$D$107),0)+MIN('Допущения'!$D$105,'Допущения'!$D$108)+MAX(0,'Допущения'!$D$105-'Допущения'!$D$108)*MIN(MAX(J6-1,0),3)/3)/'Допущения'!$D$7 | ... AL57: =AL51+('Допущения'!$C$105*'Допущения'!$D$107+IF(AL6>='Допущения'!$D$9,'Допущения'!$C$105*(1-'Допущения'!$D$107),0)+MIN('Допущения'!$D$105,'Допущения'!$D$108)+MAX(0,'Допущения'!$D$105-'Допущения'!$D$108)*MIN(MAX(AL6-1,0),3)/3)/'Допущения'!$D$7
A58: Касса при варианте 3 «Максимум» | B58: =MIN(C58:AL58) | C58: =C51+('Допущения'!$C$106*'Допущения'!$D$107+IF(C6>='Допущения'!$D$9,'Допущения'!$C$106*(1-'Допущения'!$D$107),0)+MIN('Допущения'!$D$106,'Допущения'!$D$108)+MAX(0,'Допущения'!$D$106-'Допущения'!$D$108)*MIN(MAX(C6-1,0),3)/3)/'Допущения'!$D$7 | D58: =D51+('Допущения'!$C$106*'Допущения'!$D$107+IF(D6>='Допущения'!$D$9,'Допущения'!$C$106*(1-'Допущения'!$D$107),0)+MIN('Допущения'!$D$106,'Допущения'!$D$108)+MAX(0,'Допущения'!$D$106-'Допущения'!$D$108)*MIN(MAX(D6-1,0),3)/3)/'Допущения'!$D$7 | E58: =E51+('Допущения'!$C$106*'Допущения'!$D$107+IF(E6>='Допущения'!$D$9,'Допущения'!$C$106*(1-'Допущения'!$D$107),0)+MIN('Допущения'!$D$106,'Допущения'!$D$108)+MAX(0,'Допущения'!$D$106-'Допущения'!$D$108)*MIN(MAX(E6-1,0),3)/3)/'Допущения'!$D$7 | F58: =F51+('Допущения'!$C$106*'Допущения'!$D$107+IF(F6>='Допущения'!$D$9,'Допущения'!$C$106*(1-'Допущения'!$D$107),0)+MIN('Допущения'!$D$106,'Допущения'!$D$108)+MAX(0,'Допущения'!$D$106-'Допущения'!$D$108)*MIN(MAX(F6-1,0),3)/3)/'Допущения'!$D$7 | G58: =G51+('Допущения'!$C$106*'Допущения'!$D$107+IF(G6>='Допущения'!$D$9,'Допущения'!$C$106*(1-'Допущения'!$D$107),0)+MIN('Допущения'!$D$106,'Допущения'!$D$108)+MAX(0,'Допущения'!$D$106-'Допущения'!$D$108)*MIN(MAX(G6-1,0),3)/3)/'Допущения'!$D$7 | H58: =H51+('Допущения'!$C$106*'Допущения'!$D$107+IF(H6>='Допущения'!$D$9,'Допущения'!$C$106*(1-'Допущения'!$D$107),0)+MIN('Допущения'!$D$106,'Допущения'!$D$108)+MAX(0,'Допущения'!$D$106-'Допущения'!$D$108)*MIN(MAX(H6-1,0),3)/3)/'Допущения'!$D$7 | I58: =I51+('Допущения'!$C$106*'Допущения'!$D$107+IF(I6>='Допущения'!$D$9,'Допущения'!$C$106*(1-'Допущения'!$D$107),0)+MIN('Допущения'!$D$106,'Допущения'!$D$108)+MAX(0,'Допущения'!$D$106-'Допущения'!$D$108)*MIN(MAX(I6-1,0),3)/3)/'Допущения'!$D$7 | J58: =J51+('Допущения'!$C$106*'Допущения'!$D$107+IF(J6>='Допущения'!$D$9,'Допущения'!$C$106*(1-'Допущения'!$D$107),0)+MIN('Допущения'!$D$106,'Допущения'!$D$108)+MAX(0,'Допущения'!$D$106-'Допущения'!$D$108)*MIN(MAX(J6-1,0),3)/3)/'Допущения'!$D$7 | ... AL58: =AL51+('Допущения'!$C$106*'Допущения'!$D$107+IF(AL6>='Допущения'!$D$9,'Допущения'!$C$106*(1-'Допущения'!$D$107),0)+MIN('Допущения'!$D$106,'Допущения'!$D$108)+MAX(0,'Допущения'!$D$106-'Допущения'!$D$108)*MIN(MAX(AL6-1,0),3)/3)/'Допущения'!$D$7
A59: МЕТРИКИ
A60: MRR (брутто), $ | C60: =C24 | D60: =D24 | E60: =E24 | F60: =F24 | G60: =G24 | H60: =H24 | I60: =I24 | J60: =J24 | ... AL60: =AL24
A61: CAC на нового платящего, $ | B61: =IFERROR(B11/B19,0) | C61: =IFERROR(IF(C9=1,C11/C19,0),0) | D61: =IFERROR(IF(D9=1,D11/D19,0),0) | E61: =IFERROR(IF(E9=1,E11/E19,0),0) | F61: =IFERROR(IF(F9=1,F11/F19,0),0) | G61: =IFERROR(IF(G9=1,G11/G19,0),0) | H61: =IFERROR(IF(H9=1,H11/H19,0),0) | I61: =IFERROR(IF(I9=1,I11/I19,0),0) | J61: =IFERROR(IF(J9=1,J11/J19,0),0) | ... AL61: =IFERROR(IF(AL9=1,AL11/AL19,0),0)
A62: Флаг: EBITDA ≥ 0 после выхода | C62: =IF(AND(C9=1,C48>=0),1,0) | D62: =IF(AND(D9=1,D48>=0),1,0) | E62: =IF(AND(E9=1,E48>=0),1,0) | F62: =IF(AND(F9=1,F48>=0),1,0) | G62: =IF(AND(G9=1,G48>=0),1,0) | H62: =IF(AND(H9=1,H48>=0),1,0) | I62: =IF(AND(I9=1,I48>=0),1,0) | J62: =IF(AND(J9=1,J48>=0),1,0) | ... AL62: =IF(AND(AL9=1,AL48>=0),1,0)
A63: Флаг: EBITDA ≥ 0 в этом и всех следующих месяцах | C63: =IF(AND(C9=1,MIN(C48:$AL$48)>=0),1,0) | D63: =IF(AND(D9=1,MIN(D48:$AL$48)>=0),1,0) | E63: =IF(AND(E9=1,MIN(E48:$AL$48)>=0),1,0) | F63: =IF(AND(F9=1,MIN(F48:$AL$48)>=0),1,0) | G63: =IF(AND(G9=1,MIN(G48:$AL$48)>=0),1,0) | H63: =IF(AND(H9=1,MIN(H48:$AL$48)>=0),1,0) | I63: =IF(AND(I9=1,MIN(I48:$AL$48)>=0),1,0) | J63: =IF(AND(J9=1,MIN(J48:$AL$48)>=0),1,0) | ... AL63: =IF(AND(AL9=1,MIN(AL48:$AL$48)>=0),1,0)
A64: Флаг: накопленный поток ≥ 0 | C64: =IF(C51>=0,1,0) | D64: =IF(D51>=0,1,0) | E64: =IF(E51>=0,1,0) | F64: =IF(F51>=0,1,0) | G64: =IF(G51>=0,1,0) | H64: =IF(H51>=0,1,0) | I64: =IF(I51>=0,1,0) | J64: =IF(J51>=0,1,0) | ... AL64: =IF(AL51>=0,1,0)
A65: Поток для IRR (с терминальной стоимостью) | C65: =C50+0 | D65: =D50+0 | E65: =E50+0 | F65: =F50+0 | G65: =G50+0 | H65: =H50+0 | I65: =I50+0 | J65: =J50+0 | ... AK65: =AK50+0 | AL65: =AL50+AL60*12*'Допущения'!$D$100
A67: СВОДКА
A68: Первый месяц с EBITDA ≥ 0 (№) | B68: =IFERROR(MATCH(1,$C$62:$AL$62,0),"не достигнут")
A69: Устойчивая безубыточность: EBITDA ≥ 0 и дальше (№ мес.) | B69: =IFERROR(MATCH(1,$C$63:$AL$63,0),"не достигнута")
A70: Устойчивая безубыточность (дата) | B70: =IFERROR(INDEX($C$7:$AL$7,MATCH(1,$C$63:$AL$63,0)),"—")
A71: Окупаемость: накопленный поток ≥ 0 (№ мес.) | B71: =IFERROR(MATCH(1,$C$64:$AL$64,0),"> 36 мес.")
A72: Пиковая потребность в финансировании, $ | B72: =-MIN($C$51:$AL$51)
A73: То же, ₽ | B73: =-MIN($C$51:$AL$51)*'Допущения'!$D$7
A74: Чистая выручка, год 1, $ | B74: =SUMIF($C$8:$AL$8,1,$C$28:$AL$28)
A75: Чистая выручка, год 2, $ | B75: =SUMIF($C$8:$AL$8,2,$C$28:$AL$28)
A76: Чистая выручка, год 3, $ | B76: =SUMIF($C$8:$AL$8,3,$C$28:$AL$28)
A77: EBITDA, год 1, $ | B77: =SUMIF($C$8:$AL$8,1,$C$48:$AL$48)
A78: EBITDA, год 2, $ | B78: =SUMIF($C$8:$AL$8,2,$C$48:$AL$48)
A79: EBITDA, год 3, $ | B79: =SUMIF($C$8:$AL$8,3,$C$48:$AL$48)
A80: Платящие, мес. 12 | B80: =$N$21
A81: Платящие, мес. 24 | B81: =$Z$21
A82: Платящие, мес. 36 | B82: =$AL$21
A83: Активные, мес. 12 | B83: =$N$22
A84: Активные, мес. 36 | B84: =$AL$22
A85: MRR, мес. 12, $ | B85: =$N$60
A86: MRR, мес. 24, $ | B86: =$Z$60
A87: MRR, мес. 36, $ | B87: =$AL$60
A88: ARR, мес. 36, $ | B88: =$AL$60*12
A89: CAC средний (маркетинг / новые платящие после выхода), $ | B89: =IFERROR(SUMIF($C$9:$AL$9,1,$C$11:$AL$11)/SUM($C$19:$AL$19),0)
A90: LTV платящего (чистая выручка × маржа / отток), $ | B90: ='Себестоимость'!$D$13*'Себестоимость'!$D$15/'Допущения'!$D$69
A91: LTV / CAC | B91: =IFERROR(B90/B89,0)
A92: Валовая маржа за 36 мес. | B92: =B36
A93: NPV операционного потока + терминальная стоимость, $ | B93: =NPV((1+'Допущения'!$D$99)^(1/12)-1,$C$65:$AL$65)
A94: IRR годовая | B94: =IFERROR((1+IRR($C$65:$AL$65,0.05))^12-1,"н/д")
A95: Мин. касса при выбранном варианте вложений, $ | B95: =B55
A96: Мин. касса: вариант 1, $ | B96: =B56
A97: Мин. касса: вариант 2, $ | B97: =B57
A98: Мин. касса: вариант 3, $ | B98: =B58
A99: Расходы мес. 1 … выход включительно, $ | B99: =SUMIF($C$6:$AL$6,"<="&'Допущения'!$D$9,$C$34:$AL$34)+SUMIF($C$6:$AL$6,"<="&'Допущения'!$D$9,$C$47:$AL$47)

Sheet S_cpip
A1: Финмодель на 36 месяцев — сценарий: Базовый
A2: Все значения считаются формулами из листов «Допущения», «Себестоимость», «Старт».
B5: Итого / знач.
A6: Месяц № | C6: 1 | D6: 2 | E6: 3 | F6: 4 | G6: 5 | H6: 6 | I6: 7 | J6: 8 | K6: 9 | L6: 10 | M6: 11 | N6: 12 | O6: 13 | P6: 14 | Q6: 15 | R6: 16 | S6: 17 | T6: 18 | U6: 19 | V6: 20 | W6: 21 | X6: 22 | Y6: 23 | Z6: 24 | AA6: 25 | AB6: 26 | AC6: 27 | AD6: 28 | AE6: 29 | AF6: 30 | AG6: 31 | AH6: 32 | AI6: 33 | AJ6: 34 | AK6: 35 | AL6: 36
A7: Месяц | C7: ноя 2026 | D7: дек 2026 | E7: янв 2027 | F7: фев 2027 | G7: мар 2027 | H7: апр 2027 | I7: май 2027 | J7: июн 2027 | K7: июл 2027 | L7: авг 2027 | M7: сен 2027 | N7: окт 2027 | O7: ноя 2027 | P7: дек 2027 | Q7: янв 2028 | R7: фев 2028 | S7: мар 2028 | T7: апр 2028 | U7: май 2028 | V7: июн 2028 | W7: июл 2028 | X7: авг 2028 | Y7: сен 2028 | Z7: окт 2028 | AA7: ноя 2028 | AB7: дек 2028 | AC7: янв 2029 | AD7: фев 2029 | AE7: мар 2029 | AF7: апр 2029 | AG7: май 2029 | AH7: июн 2029 | AI7: июл 2029 | AJ7: авг 2029 | AK7: сен 2029 | AL7: окт 2029
A8: Год проекта | C8: 1 | D8: 1 | E8: 1 | F8: 1 | G8: 1 | H8: 1 | I8: 1 | J8: 1 | K8: 1 | L8: 1 | M8: 1 | N8: 1 | O8: 2 | P8: 2 | Q8: 2 | R8: 2 | S8: 2 | T8: 2 | U8: 2 | V8: 2 | W8: 2 | X8: 2 | Y8: 2 | Z8: 2 | AA8: 3 | AB8: 3 | AC8: 3 | AD8: 3 | AE8: 3 | AF8: 3 | AG8: 3 | AH8: 3 | AI8: 3 | AJ8: 3 | AK8: 3 | AL8: 3
A9: Рынок (1 = MVP вышел) | C9: =IF(C6>='Допущения'!$D$9,1,0) | D9: =IF(D6>='Допущения'!$D$9,1,0) | E9: =IF(E6>='Допущения'!$D$9,1,0) | F9: =IF(F6>='Допущения'!$D$9,1,0) | G9: =IF(G6>='Допущения'!$D$9,1,0) | H9: =IF(H6>='Допущения'!$D$9,1,0) | I9: =IF(I6>='Допущения'!$D$9,1,0) | J9: =IF(J6>='Допущения'!$D$9,1,0) | ... AL9: =IF(AL6>='Допущения'!$D$9,1,0)
A10: ВОРОНКА
A11: Маркетинг, $ | B11: =SUM(C11:AL11) | C11: =IF(C9=1,MAX('Допущения'!$D$83,'Допущения'!$D$84*0)+IF(C6='Допущения'!$D$9,'Допущения'!$D$82,0),'Допущения'!$D$81) | D11: =IF(D9=1,MAX('Допущения'!$D$83,'Допущения'!$D$84*C28)+IF(D6='Допущения'!$D$9,'Допущения'!$D$82,0),'Допущения'!$D$81) | E11: =IF(E9=1,MAX('Допущения'!$D$83,'Допущения'!$D$84*D28)+IF(E6='Допущения'!$D$9,'Допущения'!$D$82,0),'Допущения'!$D$81) | F11: =IF(F9=1,MAX('Допущения'!$D$83,'Допущения'!$D$84*E28)+IF(F6='Допущения'!$D$9,'Допущения'!$D$82,0),'Допущения'!$D$81) | G11: =IF(G9=1,MAX('Допущения'!$D$83,'Допущения'!$D$84*F28)+IF(G6='Допущения'!$D$9,'Допущения'!$D$82,0),'Допущения'!$D$81) | H11: =IF(H9=1,MAX('Допущения'!$D$83,'Допущения'!$D$84*G28)+IF(H6='Допущения'!$D$9,'Допущения'!$D$82,0),'Допущения'!$D$81) | I11: =IF(I9=1,MAX('Допущения'!$D$83,'Допущения'!$D$84*H28)+IF(I6='Допущения'!$D$9,'Допущения'!$D$82,0),'Допущения'!$D$81) | J11: =IF(J9=1,MAX('Допущения'!$D$83,'Допущения'!$D$84*I28)+IF(J6='Допущения'!$D$9,'Допущения'!$D$82,0),'Допущения'!$D$81) | K11: =IF(K9=1,MAX('Допущения'!$D$83,'Допущения'!$D$84*J28)+IF(K6='Допущения'!$D$9,'Допущения'!$D$82,0),'Допущения'!$D$81) | ... AL11: =IF(AL9=1,MAX('Допущения'!$D$83,'Допущения'!$D$84*AK28)+IF(AL6='Допущения'!$D$9,'Допущения'!$D$82,0),'Допущения'!$D$81)
A12: Платные установки | B12: =SUM(C12:AL12) | C12: =IF(C9=1,C11/('Допущения'!$D$60*(1+'Чувствительность'!$B$3)),0) | D12: =IF(D9=1,D11/('Допущения'!$D$60*(1+'Чувствительность'!$B$3)),0) | E12: =IF(E9=1,E11/('Допущения'!$D$60*(1+'Чувствительность'!$B$3)),0) | F12: =IF(F9=1,F11/('Допущения'!$D$60*(1+'Чувствительность'!$B$3)),0) | G12: =IF(G9=1,G11/('Допущения'!$D$60*(1+'Чувствительность'!$B$3)),0) | H12: =IF(H9=1,H11/('Допущения'!$D$60*(1+'Чувствительность'!$B$3)),0) | I12: =IF(I9=1,I11/('Допущения'!$D$60*(1+'Чувствительность'!$B$3)),0) | J12: =IF(J9=1,J11/('Допущения'!$D$60*(1+'Чувствительность'!$B$3)),0) | ... AL12: =IF(AL9=1,AL11/('Допущения'!$D$60*(1+'Чувствительность'!$B$3)),0)
A13: Органические установки | B13: =SUM(C13:AL13) | C13: =IF(C9=1,MIN('Допущения'!$D$63,'Допущения'!$D$61*(1+'Допущения'!$D$62)^(C6-'Допущения'!$D$9)),0) | D13: =IF(D9=1,MIN('Допущения'!$D$63,'Допущения'!$D$61*(1+'Допущения'!$D$62)^(D6-'Допущения'!$D$9)),0) | E13: =IF(E9=1,MIN('Допущения'!$D$63,'Допущения'!$D$61*(1+'Допущения'!$D$62)^(E6-'Допущения'!$D$9)),0) | F13: =IF(F9=1,MIN('Допущения'!$D$63,'Допущения'!$D$61*(1+'Допущения'!$D$62)^(F6-'Допущения'!$D$9)),0) | G13: =IF(G9=1,MIN('Допущения'!$D$63,'Допущения'!$D$61*(1+'Допущения'!$D$62)^(G6-'Допущения'!$D$9)),0) | H13: =IF(H9=1,MIN('Допущения'!$D$63,'Допущения'!$D$61*(1+'Допущения'!$D$62)^(H6-'Допущения'!$D$9)),0) | I13: =IF(I9=1,MIN('Допущения'!$D$63,'Допущения'!$D$61*(1+'Допущения'!$D$62)^(I6-'Допущения'!$D$9)),0) | J13: =IF(J9=1,MIN('Допущения'!$D$63,'Допущения'!$D$61*(1+'Допущения'!$D$62)^(J6-'Допущения'!$D$9)),0) | ... AL13: =IF(AL9=1,MIN('Допущения'!$D$63,'Допущения'!$D$61*(1+'Допущения'!$D$62)^(AL6-'Допущения'!$D$9)),0)
A14: Вирусные установки | B14: =SUM(C14:AL14) | C14: =(C12+C13)*'Допущения'!$D$64 | D14: =(D12+D13)*'Допущения'!$D$64 | E14: =(E12+E13)*'Допущения'!$D$64 | F14: =(F12+F13)*'Допущения'!$D$64 | G14: =(G12+G13)*'Допущения'!$D$64 | H14: =(H12+H13)*'Допущения'!$D$64 | I14: =(I12+I13)*'Допущения'!$D$64 | J14: =(J12+J13)*'Допущения'!$D$64 | ... AL14: =(AL12+AL13)*'Допущения'!$D$64
A15: Всего установок | B15: =SUM(C15:AL15) | C15: =C12+C13+C14 | D15: =D12+D13+D14 | E15: =E12+E13+E14 | F15: =F12+F13+F14 | G15: =G12+G13+G14 | H15: =H12+H13+H14 | I15: =I12+I13+I14 | J15: =J12+J13+J14 | ... AL15: =AL12+AL13+AL14
A16: Новые активированные | B16: =SUM(C16:AL16) | C16: =C15*'Допущения'!$D$65+IF(C6='Допущения'!$D$9,0*'Допущения'!$D$78,0) | D16: =D15*'Допущения'!$D$65+IF(D6='Допущения'!$D$9,C17*'Допущения'!$D$78,0) | E16: =E15*'Допущения'!$D$65+IF(E6='Допущения'!$D$9,D17*'Допущения'!$D$78,0) | F16: =F15*'Допущения'!$D$65+IF(F6='Допущения'!$D$9,E17*'Допущения'!$D$78,0) | G16: =G15*'Допущения'!$D$65+IF(G6='Допущения'!$D$9,F17*'Допущения'!$D$78,0) | H16: =H15*'Допущения'!$D$65+IF(H6='Допущения'!$D$9,G17*'Допущения'!$D$78,0) | I16: =I15*'Допущения'!$D$65+IF(I6='Допущения'!$D$9,H17*'Допущения'!$D$78,0) | J16: =J15*'Допущения'!$D$65+IF(J6='Допущения'!$D$9,I17*'Допущения'!$D$78,0) | K16: =K15*'Допущения'!$D$65+IF(K6='Допущения'!$D$9,J17*'Допущения'!$D$78,0) | ... AL16: =AL15*'Допущения'!$D$65+IF(AL6='Допущения'!$D$9,AK17*'Допущения'!$D$78,0)
A17: Игроки прототипа (до выхода) | C17: =IF(C9=1,0,'Допущения'!$D$72*(1+'Допущения'!$D$73)^(C6-1)) | D17: =IF(D9=1,0,'Допущения'!$D$72*(1+'Допущения'!$D$73)^(D6-1)) | E17: =IF(E9=1,0,'Допущения'!$D$72*(1+'Допущения'!$D$73)^(E6-1)) | F17: =IF(F9=1,0,'Допущения'!$D$72*(1+'Допущения'!$D$73)^(F6-1)) | G17: =IF(G9=1,0,'Допущения'!$D$72*(1+'Допущения'!$D$73)^(G6-1)) | H17: =IF(H9=1,0,'Допущения'!$D$72*(1+'Допущения'!$D$73)^(H6-1)) | I17: =IF(I9=1,0,'Допущения'!$D$72*(1+'Допущения'!$D$73)^(I6-1)) | J17: =IF(J9=1,0,'Допущения'!$D$72*(1+'Допущения'!$D$73)^(J6-1)) | ... AL17: =IF(AL9=1,0,'Допущения'!$D$72*(1+'Допущения'!$D$73)^(AL6-1))
A18: Активные free (на конец мес.) | C18: =IF(C9=1,0*(1-'Допущения'!$D$68)*'Допущения'!$D$66+C16*(1-'Допущения'!$D$67),0) | D18: =IF(D9=1,C18*(1-'Допущения'!$D$68)*'Допущения'!$D$66+D16*(1-'Допущения'!$D$67),0) | E18: =IF(E9=1,D18*(1-'Допущения'!$D$68)*'Допущения'!$D$66+E16*(1-'Допущения'!$D$67),0) | F18: =IF(F9=1,E18*(1-'Допущения'!$D$68)*'Допущения'!$D$66+F16*(1-'Допущения'!$D$67),0) | G18: =IF(G9=1,F18*(1-'Допущения'!$D$68)*'Допущения'!$D$66+G16*(1-'Допущения'!$D$67),0) | H18: =IF(H9=1,G18*(1-'Допущения'!$D$68)*'Допущения'!$D$66+H16*(1-'Допущения'!$D$67),0) | I18: =IF(I9=1,H18*(1-'Допущения'!$D$68)*'Допущения'!$D$66+I16*(1-'Допущения'!$D$67),0) | J18: =IF(J9=1,I18*(1-'Допущения'!$D$68)*'Допущения'!$D$66+J16*(1-'Допущения'!$D$67),0) | K18: =IF(K9=1,J18*(1-'Допущения'!$D$68)*'Допущения'!$D$66+K16*(1-'Допущения'!$D$67),0) | ... AL18: =IF(AL9=1,AK18*(1-'Допущения'!$D$68)*'Допущения'!$D$66+AL16*(1-'Допущения'!$D$67),0)
A19: Новые платящие | B19: =SUM(C19:AL19) | C19: =IF(C9=1,C16*'Допущения'!$D$67+0*'Допущения'!$D$68,0) | D19: =IF(D9=1,D16*'Допущения'!$D$67+C18*'Допущения'!$D$68,0) | E19: =IF(E9=1,E16*'Допущения'!$D$67+D18*'Допущения'!$D$68,0) | F19: =IF(F9=1,F16*'Допущения'!$D$67+E18*'Допущения'!$D$68,0) | G19: =IF(G9=1,G16*'Допущения'!$D$67+F18*'Допущения'!$D$68,0) | H19: =IF(H9=1,H16*'Допущения'!$D$67+G18*'Допущения'!$D$68,0) | I19: =IF(I9=1,I16*'Допущения'!$D$67+H18*'Допущения'!$D$68,0) | J19: =IF(J9=1,J16*'Допущения'!$D$67+I18*'Допущения'!$D$68,0) | K19: =IF(K9=1,K16*'Допущения'!$D$67+J18*'Допущения'!$D$68,0) | ... AL19: =IF(AL9=1,AL16*'Допущения'!$D$67+AK18*'Допущения'!$D$68,0)
A20: Ушедшие платящие | B20: =SUM(C20:AL20) | C20: =0*'Допущения'!$D$69 | D20: =C21*'Допущения'!$D$69 | E20: =D21*'Допущения'!$D$69 | F20: =E21*'Допущения'!$D$69 | G20: =F21*'Допущения'!$D$69 | H20: =G21*'Допущения'!$D$69 | I20: =H21*'Допущения'!$D$69 | J20: =I21*'Допущения'!$D$69 | K20: =J21*'Допущения'!$D$69 | ... AL20: =AK21*'Допущения'!$D$69
A21: Платящие (на конец мес.) | C21: =0+C19-C20 | D21: =C21+D19-D20 | E21: =D21+E19-E20 | F21: =E21+F19-F20 | G21: =F21+G19-G20 | H21: =G21+H19-H20 | I21: =H21+I19-I20 | J21: =I21+J19-J20 | K21: =J21+K19-K20 | ... AL21: =AK21+AL19-AL20
A22: Активные пользователи всего | C22: =C17+C18+C21 | D22: =D17+D18+D21 | E22: =E17+E18+E21 | F22: =F17+F18+F21 | G22: =G17+G18+G21 | H22: =H17+H18+H21 | I22: =I17+I18+I21 | J22: =J17+J18+J21 | ... AL22: =AL17+AL18+AL21
A23: ВЫРУЧКА, $
A24: Оплаты подписок (брутто) | B24: =SUM(C24:AL24) | C24: =C21*'Себестоимость'!$D$12 | D24: =D21*'Себестоимость'!$D$12 | E24: =E21*'Себестоимость'!$D$12 | F24: =F21*'Себестоимость'!$D$12 | G24: =G21*'Себестоимость'!$D$12 | H24: =H21*'Себестоимость'!$D$12 | I24: =I21*'Себестоимость'!$D$12 | J24: =J21*'Себестоимость'!$D$12 | ... AL24: =AL21*'Себестоимость'!$D$12
A25: Комиссии магазинов/Paddle и НДС | B25: =SUM(C25:AL25) | C25: =C24-C26 | D25: =D24-D26 | E25: =E24-E26 | F25: =F24-F26 | G25: =G24-G26 | H25: =H24-H26 | I25: =I24-I26 | J25: =J24-J26 | ... AL25: =AL24-AL26
A26: Чистая выручка подписок | B26: =SUM(C26:AL26) | C26: =C21*'Себестоимость'!$D$13 | D26: =D21*'Себестоимость'!$D$13 | E26: =E21*'Себестоимость'!$D$13 | F26: =F21*'Себестоимость'!$D$13 | G26: =G21*'Себестоимость'!$D$13 | H26: =H21*'Себестоимость'!$D$13 | I26: =I21*'Себестоимость'!$D$13 | J26: =J21*'Себестоимость'!$D$13 | ... AL26: =AL21*'Себестоимость'!$D$13
A27: Донаты (чистые) | B27: =SUM(C27:AL27) | C27: =C17*'Допущения'!$D$75*'Допущения'!$D$76*(1-'Допущения'!$D$77) | D27: =D17*'Допущения'!$D$75*'Допущения'!$D$76*(1-'Допущения'!$D$77) | E27: =E17*'Допущения'!$D$75*'Допущения'!$D$76*(1-'Допущения'!$D$77) | F27: =F17*'Допущения'!$D$75*'Допущения'!$D$76*(1-'Допущения'!$D$77) | G27: =G17*'Допущения'!$D$75*'Допущения'!$D$76*(1-'Допущения'!$D$77) | H27: =H17*'Допущения'!$D$75*'Допущения'!$D$76*(1-'Допущения'!$D$77) | I27: =I17*'Допущения'!$D$75*'Допущения'!$D$76*(1-'Допущения'!$D$77) | J27: =J17*'Допущения'!$D$75*'Допущения'!$D$76*(1-'Допущения'!$D$77) | ... AL27: =AL17*'Допущения'!$D$75*'Допущения'!$D$76*(1-'Допущения'!$D$77)
A28: Итого чистая выручка | B28: =SUM(C28:AL28) | C28: =C26+C27 | D28: =D26+D27 | E28: =E26+E27 | F28: =F26+F27 | G28: =G26+G27 | H28: =H26+H27 | I28: =I26+I27 | J28: =J26+J27 | ... AL28: =AL26+AL27
A29: ПЕРЕМЕННЫЕ ЗАТРАТЫ, $
A30: LLM: платящие | B30: =SUM(C30:AL30) | C30: =C21*'Себестоимость'!$D$14 | D30: =D21*'Себестоимость'!$D$14 | E30: =E21*'Себестоимость'!$D$14 | F30: =F21*'Себестоимость'!$D$14 | G30: =G21*'Себестоимость'!$D$14 | H30: =H21*'Себестоимость'!$D$14 | I30: =I21*'Себестоимость'!$D$14 | J30: =J21*'Себестоимость'!$D$14 | ... AL30: =AL21*'Себестоимость'!$D$14
A31: LLM: free и прототип | B31: =SUM(C31:AL31) | C31: =C18*'Себестоимость'!$D$16+C17*'Допущения'!$D$74*'Себестоимость'!$D$7 | D31: =D18*'Себестоимость'!$D$16+D17*'Допущения'!$D$74*'Себестоимость'!$D$7 | E31: =E18*'Себестоимость'!$D$16+E17*'Допущения'!$D$74*'Себестоимость'!$D$7 | F31: =F18*'Себестоимость'!$D$16+F17*'Допущения'!$D$74*'Себестоимость'!$D$7 | G31: =G18*'Себестоимость'!$D$16+G17*'Допущения'!$D$74*'Себестоимость'!$D$7 | H31: =H18*'Себестоимость'!$D$16+H17*'Допущения'!$D$74*'Себестоимость'!$D$7 | I31: =I18*'Себестоимость'!$D$16+I17*'Допущения'!$D$74*'Себестоимость'!$D$7 | J31: =J18*'Себестоимость'!$D$16+J17*'Допущения'!$D$74*'Себестоимость'!$D$7 | ... AL31: =AL18*'Себестоимость'!$D$16+AL17*'Допущения'!$D$74*'Себестоимость'!$D$7
A32: Проверка возраста | B32: =SUM(C32:AL32) | C32: =C19*'Допущения'!$D$44*'Допущения'!$D$93 | D32: =D19*'Допущения'!$D$44*'Допущения'!$D$93 | E32: =E19*'Допущения'!$D$44*'Допущения'!$D$93 | F32: =F19*'Допущения'!$D$44*'Допущения'!$D$93 | G32: =G19*'Допущения'!$D$44*'Допущения'!$D$93 | H32: =H19*'Допущения'!$D$44*'Допущения'!$D$93 | I32: =I19*'Допущения'!$D$44*'Допущения'!$D$93 | J32: =J19*'Допущения'!$D$44*'Допущения'!$D$93 | ... AL32: =AL19*'Допущения'!$D$44*'Допущения'!$D$93
A33: Инфраструктура (на пользователя) | B33: =SUM(C33:AL33) | C33: =C22*'Допущения'!$D$86 | D33: =D22*'Допущения'!$D$86 | E33: =E22*'Допущения'!$D$86 | F33: =F22*'Допущения'!$D$86 | G33: =G22*'Допущения'!$D$86 | H33: =H22*'Допущения'!$D$86 | I33: =I22*'Допущения'!$D$86 | J33: =J22*'Допущения'!$D$86 | ... AL33: =AL22*'Допущения'!$D$86
A34: Итого переменные | B34: =SUM(C34:AL34) | C34: =SUM(C30:C33) | D34: =SUM(D30:D33) | E34: =SUM(E30:E33) | F34: =SUM(F30:F33) | G34: =SUM(G30:G33) | H34: =SUM(H30:H33) | I34: =SUM(I30:I33) | J34: =SUM(J30:J33) | ... AL34: =SUM(AL30:AL33)
A35: Валовая прибыль | B35: =SUM(C35:AL35) | C35: =C28-C34 | D35: =D28-D34 | E35: =E28-E34 | F35: =F28-F34 | G35: =G28-G34 | H35: =H28-H34 | I35: =I28-I34 | J35: =J28-J34 | ... AL35: =AL28-AL34
A36: Валовая маржа | B36: =IFERROR(B35/B28,0) | C36: =IFERROR(C35/C28,0) | D36: =IFERROR(D35/D28,0) | E36: =IFERROR(E35/E28,0) | F36: =IFERROR(F35/F28,0) | G36: =IFERROR(G35/G28,0) | H36: =IFERROR(H35/H28,0) | I36: =IFERROR(I35/I28,0) | ... AL36: =IFERROR(AL35/AL28,0)
A37: ПОСТОЯННЫЕ ЗАТРАТЫ И МАРКЕТИНГ, $
A38: Инфраструктура (база) | B38: =SUM(C38:AL38) | C38: ='Допущения'!$D$85 | D38: ='Допущения'!$D$85 | E38: ='Допущения'!$D$85 | F38: ='Допущения'!$D$85 | G38: ='Допущения'!$D$85 | H38: ='Допущения'!$D$85 | I38: ='Допущения'!$D$85 | J38: ='Допущения'!$D$85 | ... AL38: ='Допущения'!$D$85
A39: SaaS-инструменты | B39: =SUM(C39:AL39) | C39: ='Допущения'!$D$87 | D39: ='Допущения'!$D$87 | E39: ='Допущения'!$D$87 | F39: ='Допущения'!$D$87 | G39: ='Допущения'!$D$87 | H39: ='Допущения'!$D$87 | I39: ='Допущения'!$D$87 | J39: ='Допущения'!$D$87 | ... AL39: ='Допущения'!$D$87
A40: Бухгалтерия | B40: =SUM(C40:AL40) | C40: =IF(C6>='Допущения'!$D$10,'Допущения'!$D$88,0) | D40: =IF(D6>='Допущения'!$D$10,'Допущения'!$D$88,0) | E40: =IF(E6>='Допущения'!$D$10,'Допущения'!$D$88,0) | F40: =IF(F6>='Допущения'!$D$10,'Допущения'!$D$88,0) | G40: =IF(G6>='Допущения'!$D$10,'Допущения'!$D$88,0) | H40: =IF(H6>='Допущения'!$D$10,'Допущения'!$D$88,0) | I40: =IF(I6>='Допущения'!$D$10,'Допущения'!$D$88,0) | J40: =IF(J6>='Допущения'!$D$10,'Допущения'!$D$88,0) | ... AL40: =IF(AL6>='Допущения'!$D$10,'Допущения'!$D$88,0)
A41: Юр. сопровождение | B41: =SUM(C41:AL41) | C41: =IF(C9=1,'Допущения'!$D$89,0) | D41: =IF(D9=1,'Допущения'!$D$89,0) | E41: =IF(E9=1,'Допущения'!$D$89,0) | F41: =IF(F9=1,'Допущения'!$D$89,0) | G41: =IF(G9=1,'Допущения'!$D$89,0) | H41: =IF(H9=1,'Допущения'!$D$89,0) | I41: =IF(I9=1,'Допущения'!$D$89,0) | J41: =IF(J9=1,'Допущения'!$D$89,0) | ... AL41: =IF(AL9=1,'Допущения'!$D$89,0)
A42: Магазины приложений | B42: =SUM(C42:AL42) | C42: =IF(C6='Допущения'!$D$9-1,'Допущения'!$D$90+'Допущения'!$D$91,0)+IF(AND(C6>'Допущения'!$D$9-1,MOD(C6-('Допущения'!$D$9-1),12)=0),'Допущения'!$D$90,0) | D42: =IF(D6='Допущения'!$D$9-1,'Допущения'!$D$90+'Допущения'!$D$91,0)+IF(AND(D6>'Допущения'!$D$9-1,MOD(D6-('Допущения'!$D$9-1),12)=0),'Допущения'!$D$90,0) | E42: =IF(E6='Допущения'!$D$9-1,'Допущения'!$D$90+'Допущения'!$D$91,0)+IF(AND(E6>'Допущения'!$D$9-1,MOD(E6-('Допущения'!$D$9-1),12)=0),'Допущения'!$D$90,0) | F42: =IF(F6='Допущения'!$D$9-1,'Допущения'!$D$90+'Допущения'!$D$91,0)+IF(AND(F6>'Допущения'!$D$9-1,MOD(F6-('Допущения'!$D$9-1),12)=0),'Допущения'!$D$90,0) | G42: =IF(G6='Допущения'!$D$9-1,'Допущения'!$D$90+'Допущения'!$D$91,0)+IF(AND(G6>'Допущения'!$D$9-1,MOD(G6-('Допущения'!$D$9-1),12)=0),'Допущения'!$D$90,0) | H42: =IF(H6='Допущения'!$D$9-1,'Допущения'!$D$90+'Допущения'!$D$91,0)+IF(AND(H6>'Допущения'!$D$9-1,MOD(H6-('Допущения'!$D$9-1),12)=0),'Допущения'!$D$90,0) | I42: =IF(I6='Допущения'!$D$9-1,'Допущения'!$D$90+'Допущения'!$D$91,0)+IF(AND(I6>'Допущения'!$D$9-1,MOD(I6-('Допущения'!$D$9-1),12)=0),'Допущения'!$D$90,0) | J42: =IF(J6='Допущения'!$D$9-1,'Допущения'!$D$90+'Допущения'!$D$91,0)+IF(AND(J6>'Допущения'!$D$9-1,MOD(J6-('Допущения'!$D$9-1),12)=0),'Допущения'!$D$90,0) | ... AL42: =IF(AL6='Допущения'!$D$9-1,'Допущения'!$D$90+'Допущения'!$D$91,0)+IF(AND(AL6>'Допущения'!$D$9-1,MOD(AL6-('Допущения'!$D$9-1),12)=0),'Допущения'!$D$90,0)
A43: Разовые стартовые (лист «Старт») | B43: =SUM(C43:AL43) | C43: =SUMIF('Старт'!$C$5:$C$17,C6,'Старт'!$D$5:$D$17) | D43: =SUMIF('Старт'!$C$5:$C$17,D6,'Старт'!$D$5:$D$17) | E43: =SUMIF('Старт'!$C$5:$C$17,E6,'Старт'!$D$5:$D$17) | F43: =SUMIF('Старт'!$C$5:$C$17,F6,'Старт'!$D$5:$D$17) | G43: =SUMIF('Старт'!$C$5:$C$17,G6,'Старт'!$D$5:$D$17) | H43: =SUMIF('Старт'!$C$5:$C$17,H6,'Старт'!$D$5:$D$17) | I43: =SUMIF('Старт'!$C$5:$C$17,I6,'Старт'!$D$5:$D$17) | J43: =SUMIF('Старт'!$C$5:$C$17,J6,'Старт'!$D$5:$D$17) | ... AL43: =SUMIF('Старт'!$C$5:$C$17,AL6,'Старт'!$D$5:$D$17)
A44: Контент / SMM | B44: =SUM(C44:AL44) | C44: =IF(C6>'Допущения'!$D$9,'Допущения'!$D$92,0) | D44: =IF(D6>'Допущения'!$D$9,'Допущения'!$D$92,0) | E44: =IF(E6>'Допущения'!$D$9,'Допущения'!$D$92,0) | F44: =IF(F6>'Допущения'!$D$9,'Допущения'!$D$92,0) | G44: =IF(G6>'Допущения'!$D$9,'Допущения'!$D$92,0) | H44: =IF(H6>'Допущения'!$D$9,'Допущения'!$D$92,0) | I44: =IF(I6>'Допущения'!$D$9,'Допущения'!$D$92,0) | J44: =IF(J6>'Допущения'!$D$9,'Допущения'!$D$92,0) | ... AL44: =IF(AL6>'Допущения'!$D$9,'Допущения'!$D$92,0)
A45: Маркетинг | B45: =SUM(C45:AL45) | C45: =C11 | D45: =D11 | E45: =E11 | F45: =F11 | G45: =G11 | H45: =H11 | I45: =I11 | J45: =J11 | ... AL45: =AL11
A46: Выплаты основателям | B46: =SUM(C46:AL46) | C46: =IF(C6>='Допущения'!$D$94,MIN('Допущения'!$D$95,MAX(0,'Допущения'!$D$96*(0+0))),0) | D46: =IF(D6>='Допущения'!$D$94,MIN('Допущения'!$D$95,MAX(0,'Допущения'!$D$96*(C48+C46))),0) | E46: =IF(E6>='Допущения'!$D$94,MIN('Допущения'!$D$95,MAX(0,'Допущения'!$D$96*(D48+D46))),0) | F46: =IF(F6>='Допущения'!$D$94,MIN('Допущения'!$D$95,MAX(0,'Допущения'!$D$96*(E48+E46))),0) | G46: =IF(G6>='Допущения'!$D$94,MIN('Допущения'!$D$95,MAX(0,'Допущения'!$D$96*(F48+F46))),0) | H46: =IF(H6>='Допущения'!$D$94,MIN('Допущения'!$D$95,MAX(0,'Допущения'!$D$96*(G48+G46))),0) | I46: =IF(I6>='Допущения'!$D$94,MIN('Допущения'!$D$95,MAX(0,'Допущения'!$D$96*(H48+H46))),0) | J46: =IF(J6>='Допущения'!$D$94,MIN('Допущения'!$D$95,MAX(0,'Допущения'!$D$96*(I48+I46))),0) | K46: =IF(K6>='Допущения'!$D$94,MIN('Допущения'!$D$95,MAX(0,'Допущения'!$D$96*(J48+J46))),0) | ... AL46: =IF(AL6>='Допущения'!$D$94,MIN('Допущения'!$D$95,MAX(0,'Допущения'!$D$96*(AK48+AK46))),0)
A47: Итого постоянные + маркетинг | B47: =SUM(C47:AL47) | C47: =SUM(C38:C46) | D47: =SUM(D38:D46) | E47: =SUM(E38:E46) | F47: =SUM(F38:F46) | G47: =SUM(G38:G46) | H47: =SUM(H38:H46) | I47: =SUM(I38:I46) | J47: =SUM(J38:J46) | ... AL47: =SUM(AL38:AL46)
A48: EBITDA | B48: =SUM(C48:AL48) | C48: =C35-C47 | D48: =D35-D47 | E48: =E35-E47 | F48: =F35-F47 | G48: =G35-G47 | H48: =H35-H47 | I48: =I35-I47 | J48: =J35-J47 | ... AL48: =AL35-AL47
A49: Налог на прибыль | B49: =SUM(C49:AL49) | C49: =MAX(0,C48)*'Допущения'!$D$57 | D49: =MAX(0,D48)*'Допущения'!$D$57 | E49: =MAX(0,E48)*'Допущения'!$D$57 | F49: =MAX(0,F48)*'Допущения'!$D$57 | G49: =MAX(0,G48)*'Допущения'!$D$57 | H49: =MAX(0,H48)*'Допущения'!$D$57 | I49: =MAX(0,I48)*'Допущения'!$D$57 | J49: =MAX(0,J48)*'Допущения'!$D$57 | ... AL49: =MAX(0,AL48)*'Допущения'!$D$57
A50: Операционный денежный поток | B50: =SUM(C50:AL50) | C50: =C48-C49 | D50: =D48-D49 | E50: =E48-E49 | F50: =F48-F49 | G50: =G48-G49 | H50: =H48-H49 | I50: =I48-I49 | J50: =J48-J49 | ... AL50: =AL48-AL49
A51: Накопленный операционный поток | B51: =MIN(C51:AL51) | C51: =0+C50 | D51: =C51+D50 | E51: =D51+E50 | F51: =E51+F50 | G51: =F51+G50 | H51: =G51+H50 | I51: =H51+I50 | J51: =I51+J50 | K51: =J51+K50 | ... AL51: =AK51+AL50
A52: ВЛОЖЕНИЯ И КАССА, $
A53: Вложения партнёра (выбранный вариант) | B53: =SUM(C53:AL53) | C53: =(IF(C6=1,INDEX('Допущения'!$C$104:$C$106,'Допущения'!$D$103)*'Допущения'!$D$107,0)+IF(C6='Допущения'!$D$9,INDEX('Допущения'!$C$104:$C$106,'Допущения'!$D$103)*(1-'Допущения'!$D$107),0))/'Допущения'!$D$7 | D53: =(IF(D6=1,INDEX('Допущения'!$C$104:$C$106,'Допущения'!$D$103)*'Допущения'!$D$107,0)+IF(D6='Допущения'!$D$9,INDEX('Допущения'!$C$104:$C$106,'Допущения'!$D$103)*(1-'Допущения'!$D$107),0))/'Допущения'!$D$7 | E53: =(IF(E6=1,INDEX('Допущения'!$C$104:$C$106,'Допущения'!$D$103)*'Допущения'!$D$107,0)+IF(E6='Допущения'!$D$9,INDEX('Допущения'!$C$104:$C$106,'Допущения'!$D$103)*(1-'Допущения'!$D$107),0))/'Допущения'!$D$7 | F53: =(IF(F6=1,INDEX('Допущения'!$C$104:$C$106,'Допущения'!$D$103)*'Допущения'!$D$107,0)+IF(F6='Допущения'!$D$9,INDEX('Допущения'!$C$104:$C$106,'Допущения'!$D$103)*(1-'Допущения'!$D$107),0))/'Допущения'!$D$7 | G53: =(IF(G6=1,INDEX('Допущения'!$C$104:$C$106,'Допущения'!$D$103)*'Допущения'!$D$107,0)+IF(G6='Допущения'!$D$9,INDEX('Допущения'!$C$104:$C$106,'Допущения'!$D$103)*(1-'Допущения'!$D$107),0))/'Допущения'!$D$7 | H53: =(IF(H6=1,INDEX('Допущения'!$C$104:$C$106,'Допущения'!$D$103)*'Допущения'!$D$107,0)+IF(H6='Допущения'!$D$9,INDEX('Допущения'!$C$104:$C$106,'Допущения'!$D$103)*(1-'Допущения'!$D$107),0))/'Допущения'!$D$7 | I53: =(IF(I6=1,INDEX('Допущения'!$C$104:$C$106,'Допущения'!$D$103)*'Допущения'!$D$107,0)+IF(I6='Допущения'!$D$9,INDEX('Допущения'!$C$104:$C$106,'Допущения'!$D$103)*(1-'Допущения'!$D$107),0))/'Допущения'!$D$7 | J53: =(IF(J6=1,INDEX('Допущения'!$C$104:$C$106,'Допущения'!$D$103)*'Допущения'!$D$107,0)+IF(J6='Допущения'!$D$9,INDEX('Допущения'!$C$104:$C$106,'Допущения'!$D$103)*(1-'Допущения'!$D$107),0))/'Допущения'!$D$7 | ... AL53: =(IF(AL6=1,INDEX('Допущения'!$C$104:$C$106,'Допущения'!$D$103)*'Допущения'!$D$107,0)+IF(AL6='Допущения'!$D$9,INDEX('Допущения'!$C$104:$C$106,'Допущения'!$D$103)*(1-'Допущения'!$D$107),0))/'Допущения'!$D$7
